Workbook

Sheet Full Historical Statements
B1: NIKE, Inc. — Full Historical Three-Statement Model
B2: USD $mm, except per share data; historical periods sourced from NIKE 10-Ks.
B4: Assumptions | E4: 2021 | F4: 2022 | G4: 2023 | H4: 2024 | I4: 2025 | J4: 2026 | K4: 2027 | L4: 2028 | M4: 2029 | N4: 2030
B5: Revenue Growth (%) | F5: =F22/E22-1 -> 0.048767345 | G5: =G22/F22-1 -> 0.096488975 | H5: =H22/G22-1 -> 0.0028310912 | I5: =I22/H22-1 -> -0.098380125 | J5: 0.01 | K5: 0.07 | L5: 0.08 | M5: 0.09 | N5: 0.09
B6: COGs (% of Revenue) | E6: =E23/E22 -> 0.55179846 | F6: =F23/F22 -> 0.54016271 | G6: =G23/G22 -> 0.56475389 | H6: =H23/H22 -> 0.55439819 | I6: =I23/I22 -> 0.57265326 | J6: 0.58 | K6: 0.56 | L6: 0.54 | M6: 0.52 | N6: 0.52
B7: Demand creation (Growth Rate) | F7: =F25/E25-1 -> 0.23635196 | G7: =G25/F25-1 -> 0.054545455 | H7: =H25/G25-1 -> 0.055418719 | I7: =I25/H25-1 -> 0.09428238 | J7: 0.1 | K7: 0.12 | L7: 0.12 | M7: 0.14 | N7: 0.14
B8: S&A (% of Revenue) | E8: =E27/E22 -> 0.2924469 | F8: =F27/F22 -> 0.31693428 | G8: =G27/G22 -> 0.31975711 | H8: =H27/H22 -> 0.32272887 | I8: =I27/I22 -> 0.34740547 | J8: 0.35 | K8: 0.36 | L8: 0.36 | M8: 0.36 | N8: 0.36
B9: D&A (% of PPE) | E9: =E27/E22 -> 0.2924469 | F9: =F81/F47 -> 0.1496556 | G9: =G81/G47 -> 0.13835859 | H9: =H81/H47 -> 0.1592 | I9: =I81/I47 -> 0.16052196 | J9: =AVERAGE(G9:I9) -> 0.15269352 | K9: =AVERAGE(H9:J9) -> 0.15747182 | L9: =AVERAGE(I9:K9) -> 0.15689576 | M9: =AVERAGE(J9:L9) -> 0.15568703 | N9: =AVERAGE(K9:M9) -> 0.15668487
B10: Interest (% of Debt) | E10: =E29/E63 -> 0.027833847 | F10: =F29/F63 -> 0.022982063 | G10: =G29/G63 -> -0.00067211829 | H10: =H29/H63 -> -0.020372011 | I10: =I29/I63 -> -0.013440523 | J10: 0.02 | K10: 0.02 | L10: 0.02 | M10: 0.02 | N10: 0.02
B11: Tax Rate | E11: =E32/E31 -> 0.14021919 | F11: =F32/F31 -> 0.090963765 | G11: =G32/G31 -> 0.18238994 | H11: =H32/H31 -> 0.14925373 | I11: =I32/I31 -> 0.17142857 | J11: 0.15 | K11: 0.15 | L11: 0.15 | M11: 0.15 | N11: 0.15
B12: Accounts Receivable (Days) | E12: =E43/E22*365 -> 36.575396 | F12: =F43/F22*365 -> 36.468743 | G12: =G43/G22*365 -> 29.439737 | H12: =H43/H22*365 -> 31.460126 | I12: =I43/I22*365 -> 37.178626 | J12: 31 | K12: 31 | L12: 31 | M12: 31 | N12: 31
B13: Inventory (Days) | E13: =E44/E23*365 -> 101.79484 | F13: =F44/F23*365 -> 121.80651 | G13: =G44/G23*365 -> 106.67969 | H13: =H44/H23*365 -> 96.380509 | I13: =I44/I23*365 -> 103.07647 | J13: 95 | K13: 93 | L13: 90 | M13: 90 | N13: 90
B14: Accounts Payable (Days) | E14: =E58/E23*365 -> 42.119954 | F14: =F58/F23*365 -> 48.57794 | G14: =G58/G23*365 -> 36.115125 | H14: =H58/H23*365 -> 36.544864 | I14: =I58/I23*365 -> 47.88397 | J14: 40 | K14: 40 | L14: 40 | M14: 40 | N14: 40
B15: CAPEX (3% of Revenue) | E15: =E94 -> -695 | F15: =F94 -> -758 | G15: =G94 -> -969 | H15: =H94 -> -812 | I15: =I94 -> -430 | J15: =-J22*3% -> -1403.1627 | K15: =-K22*3% -> -1501.3841 | L15: =-L22*3% -> -1621.4948 | M15: =-M22*3% -> -1767.4293 | N15: =-N22*3% -> -1926.498
B16: Days | E16: 365 | F16: 365 | G16: 365 | H16: 365 | I16: 365 | J16: 365 | K16: 365 | L16: 365 | M16: 365 | N16: 365
B19: Fiscal Year Ended May 31 | E19: 2021 | F19: 2022 | G19: 2023 | H19: 2024 | I19: 2025 | J19: 2026 | K19: 2027 | L19: 2028 | M19: 2029 | N19: 2030
B21: Income Statement | C21: Income Statement | D21: Income Statement | E21: Income Statement | F21: Income Statement | G21: Income Statement | H21: Income Statement | I21: Income Statement | J21: Income Statement | K21: Income Statement | L21: Income Statement | M21: Income Statement | N21: Income Statement
B22: Revenues | E22: 44538 | F22: 46710 | G22: 51217 | H22: 51362 | I22: 46309 | J22: =I22*(1+J5) -> 46772.09 | K22: =J22*(1+K5) -> 50046.136 | L22: =K22*(1+L5) -> 54049.827 | M22: =L22*(1+M5) -> 58914.312 | N22: =M22*(1+N5) -> 64216.6
B23: Cost of sales | E23: 24576 | F23: 25231 | G23: 28925 | H23: 28475 | I23: 26519 | J23: =J22*J6 -> 27127.812 | K23: =K22*K6 -> 28025.836 | L23: =L22*L6 -> 29186.907 | M23: =M22*M6 -> 30635.442 | N23: =N22*N6 -> 33392.632
B24: Gross profit | E24: 19962 | F24: 21479 | G24: 22292 | H24: 22887 | I24: 19790 | J24: =J22-J23 -> 19644.278 | K24: =K22-K23 -> 22020.3 | L24: =L22-L23 -> 24862.921 | M24: =M22-M23 -> 28278.87 | N24: =N22-N23 -> 30823.968
B25: Demand creation expense | E25: 3114 | F25: 3850 | G25: 4060 | H25: 4285 | I25: 4689 | J25: =I25*(1+J7) -> 5157.9 | K25: =J25*(1+K7) -> 5776.848 | L25: =K25*(1+L7) -> 6470.0698 | M25: =L25*(1+M7) -> 7375.8795 | N25: =M25*(1+N7) -> 8408.5027
B26: Operating overhead expense | E26: 9911 | F26: 10954 | G26: 12317 | H26: 12291 | I26: 11399 | J26: =J27-J25 -> 11212.332 | K26: =K27-K25 -> 12239.761 | L26: =L27-L25 -> 12987.868 | M26: =M27-M25 -> 13833.273 | N26: =N27-N25 -> 14709.473
B27: Total selling and administrative expense | E27: 13025 | F27: 14804 | G27: 16377 | H27: 16576 | I27: 16088 | J27: =J22*J8 -> 16370.231 | K27: =K22*K8 -> 18016.609 | L27: =L22*L8 -> 19457.938 | M27: =M22*M8 -> 21209.152 | N27: =N22*N8 -> 23117.976
B28: Income from operations | E28: =E24-E27 -> 6937 | F28: =F24-F27 -> 6675 | G28: =G24-G27 -> 5915 | H28: =H24-H27 -> 6311 | I28: =I24-I27 -> 3702 | J28: =J24-J27 -> 3274.0463 | K28: =K24-K27 -> 4003.6909 | L28: =L24-L27 -> 5404.9827 | ... N28: =N24-N27 -> 7705.992
B29: Interest expense (income), net | E29: 262 | F29: 205 | G29: -6 | H29: -161 | I29: -107 | J29: =J130*J10 -> 140.16 | K29: =K130*K10 -> 140.14 | L29: =L130*L10 -> 140.14 | M29: =M130*M10 -> 130.14 | N29: =N130*N10 -> 130.36
B30: Other (income) expense, net | E30: 14 | F30: -181 | G30: -280 | H30: -228 | I30: -76 | J30: -76 | K30: -76 | L30: -76 | M30: -76 | N30: -76
B31: Income before income taxes | E31: 6661 | F31: 6651 | G31: 6201 | H31: 6700 | I31: 3885 | J31: =J28-J29-J30 -> 3209.8863 | K31: =K28-K29-K30 -> 3939.5509 | L31: =L28-L29-L30 -> 5340.8427 | M31: =M28-M29-M30 -> 7015.5774 | N31: =N28-N29-N30 -> 7651.632
B32: Income tax expense | E32: 934 | F32: 605 | G32: 1131 | H32: 1000 | I32: 666 | J32: =J31*J11 -> 481.48295 | K32: =K31*K11 -> 590.93264 | L32: =L31*L11 -> 801.12641 | M32: =M31*M11 -> 1052.3366 | N32: =N31*N11 -> 1147.7448
B33: Net income | E33: 5727 | F33: 6046 | G33: 5070 | H33: 5700 | I33: 3219 | J33: =J31-J32 -> 2728.4034 | K33: =K31-K32 -> 3348.6183 | L33: =L31-L32 -> 4539.7163 | M33: =M31-M32 -> 5963.2408 | N33: =N31-N32 -> 6503.8872
B34: Basic EPS | E34: 3.64 | F34: 3.83 | G34: 3.27 | H34: 3.76 | I34: 2.17
B35: Diluted EPS | E35: 3.56 | F35: 3.75 | G35: 3.23 | H35: 3.73 | I35: 2.16
B36: Basic weighted average shares | E36: 1573 | F36: 1578.8 | G36: 1551.6 | H36: 1517.6 | I36: 1484.9
B37: Diluted weighted average shares | E37: 1609.4 | F37: 1610.8 | G37: 1569.8 | H37: 1529.7 | I37: 1487.6
B40: Balance Sheet — Assets | C40: Balance Sheet — Assets | D40: Balance Sheet — Assets | E40: Balance Sheet — Assets | F40: Balance Sheet — Assets | G40: Balance Sheet — Assets | H40: Balance Sheet — Assets | I40: Balance Sheet — Assets | J40: Balance Sheet — Assets | K40: Balance Sheet — Assets | L40: Balance Sheet — Assets | M40: Balance Sheet — Assets | N40: Balance Sheet — Assets
B41: Cash and equivalents | E41: 9889 | F41: 8574 | G41: 7441 | H41: 9860 | I41: 7464 | J41: =J107 -> 7380.033 | K41: =K107 -> 9028.7919 | L41: =L107 -> 9830.929 | M41: =M107 -> 11740.446 | N41: =N107 -> 13586.53
B42: Short-term investments | E42: 3587 | F42: 4423 | G42: 3234 | H42: 1722 | I42: 1687 | J42: =AVERAGE(G42:I42) -> 2214.3333 | K42: =AVERAGE(H42:J42) -> 1874.4444 | L42: =AVERAGE(I42:K42) -> 1925.2593 | M42: =AVERAGE(J42:L42) -> 2004.679 | N42: =AVERAGE(K42:M42) -> 1934.7942
B43: Accounts receivable, net | E43: 4463 | F43: 4667 | G43: 4131 | H43: 4427 | I43: 4717 | J43: =J22*J12/J16 -> 3972.4241 | K43: =K22*K12/K16 -> 4250.4938 | L43: =L22*L12/L16 -> 4590.5333 | M43: =M22*M12/M16 -> 5003.6813 | N43: =N22*N12/N16 -> 5454.0126
B44: Inventories | E44: 6854 | F44: 8420 | G44: 8454 | H44: 7519 | I44: 7489 | J44: =J23*J13/J16 -> 7060.6634 | K44: =K23*K13/K16 -> 7140.8295 | L44: =L23*L13/L16 -> 7196.7715 | M44: =M23*M13/M16 -> 7553.9446 | N44: =N23*N13/N16 -> 8233.7996
B45: Prepaid expenses and other current assets | E45: 1498 | F45: 2129 | G45: 1942 | H45: 1854 | I45: 2005 | J45: =AVERAGE(G45:I45) -> 1933.6667 | K45: =AVERAGE(H45:J45) -> 1930.8889 | L45: =AVERAGE(I45:K45) -> 1956.5185 | M45: =AVERAGE(J45:L45) -> 1940.358 | N45: =AVERAGE(K45:M45) -> 1942.5885
B46: Total current assets | E46: 26291 | F46: 28213 | G46: 25202 | H46: 25382 | I46: 23362 | J46: =SUM(J41:J45) -> 22561.121 | K46: =SUM(K41:K45) -> 24225.449 | L46: =SUM(L41:L45) -> 25500.012 | M46: =SUM(M41:M45) -> 28243.109 | N46: =SUM(N41:N45) -> 31151.725
B47: Property, plant and equipment, net | E47: 4904 | F47: 4791 | G47: 5081 | H47: 5000 | I47: 4828 | J47: =J124 -> 4456.8553 | K47: =K124 -> 5256.4102 | L47: =L124 -> 6053.1965 | M47: =M124 -> 6878.2217 | N47: =N124 -> 7727.0064
B48: Operating lease right-of-use assets, net | E48: 3113 | F48: 2926 | G48: 2923 | H48: 2718 | I48: 2712 | J48: =AVERAGE(G48:I48) -> 2784.3333 | K48: =AVERAGE(H48:J48) -> 2738.1111 | L48: =AVERAGE(I48:K48) -> 2744.8148 | M48: =AVERAGE(J48:L48) -> 2755.7531 | N48: =AVERAGE(K48:M48) -> 2746.2263
B49: Identifiable intangible assets, net | E49: 269 | F49: 286 | G49: 274 | H49: 259 | I49: 259 | J49: 300 | K49: 300 | L49: 300 | M49: 300 | N49: 300
B50: Goodwill | E50: 242 | F50: 284 | G50: 281 | H50: 240 | I50: 240 | J50: 340 | K50: 240 | L50: 240 | M50: 240 | N50: 240
B51: Deferred income taxes and other assets | E51: 2921 | F51: 3821 | G51: 3770 | H51: 4511 | I51: 5178 | J51: =AVERAGE(G51:I51) -> 4486.3333 | K51: =AVERAGE(H51:J51) -> 4725.1111 | L51: =AVERAGE(I51:K51) -> 4796.4815 | M51: =AVERAGE(J51:L51) -> 4669.3086 | N51: =AVERAGE(K51:M51) -> 4730.3004
B52: Total assets | E52: 37740 | F52: 40321 | G52: 37531 | H52: 38110 | I52: 36579 | J52: =J46+SUM(J47:J51) -> 34928.643 | K52: =K46+SUM(K47:K51) -> 37485.081 | L52: =L46+SUM(L47:L51) -> 39634.504 | M52: =M46+SUM(M47:M51) -> 43086.392 | N52: =N46+SUM(N47:N51) -> 46895.258
B55: Balance Sheet — Liabilities | C55: Balance Sheet — Liabilities | D55: Balance Sheet — Liabilities | E55: Balance Sheet — Liabilities | F55: Balance Sheet — Liabilities | G55: Balance Sheet — Liabilities | H55: Balance Sheet — Liabilities | I55: Balance Sheet — Liabilities | J55: Balance Sheet — Liabilities | K55: Balance Sheet — Liabilities | L55: Balance Sheet — Liabilities | M55: Balance Sheet — Liabilities | N55: Balance Sheet — Liabilities
B56: Current portion of long-term debt | E56: 0 | F56: 500 | G56: 0 | H56: 1000 | I56: 0 | J56: 1000 | K56: 1000 | L56: 0 | M56: 0 | N56: 1500
B57: Notes payable | E57: 2 | F57: 10 | G57: 6 | H57: 6 | I57: 5 | J57: 5 | K57: 5 | L57: 5 | M57: 5 | N57: 5
B58: Accounts payable | E58: 2836 | F58: 3358 | G58: 2862 | H58: 2851 | I58: 3479 | J58: =J23*J14/J16 -> 2972.9109 | K58: =K23*K14/K16 -> 3071.3245 | L58: =L23*L14/L16 -> 3198.5651 | M58: =M23*M14/M16 -> 3357.3087 | N58: =N23*N14/N16 -> 3659.4665
B59: Current portion of operating lease liabilities | E59: 467 | F59: 420 | G59: 425 | H59: 477 | I59: 502 | J59: =AVERAGE(G59:I59) -> 468 | K59: =AVERAGE(H59:J59) -> 482.33333 | L59: =AVERAGE(I59:K59) -> 484.11111 | M59: =AVERAGE(J59:L59) -> 478.14815 | N59: =AVERAGE(K59:M59) -> 481.53086
B60: Accrued liabilities | E60: 6063 | F60: 6220 | G60: 5723 | H60: 5725 | I60: 5911 | J60: =AVERAGE(G60:I60) -> 5786.3333 | K60: =AVERAGE(H60:J60) -> 5807.4444 | L60: =AVERAGE(I60:K60) -> 5834.9259 | M60: =AVERAGE(J60:L60) -> 5809.5679 | N60: =AVERAGE(K60:M60) -> 5817.3128
B61: Income taxes payable | E61: 306 | F61: 222 | G61: 240 | H61: 534 | I61: 669 | J61: =AVERAGE(G61:I61) -> 481 | K61: =AVERAGE(H61:J61) -> 561.33333 | L61: =AVERAGE(I61:K61) -> 570.44444 | M61: =AVERAGE(J61:L61) -> 537.59259 | N61: =AVERAGE(K61:M61) -> 556.45679
B62: Total current liabilities | E62: 9674 | F62: 10730 | G62: 9256 | H62: 10593 | I62: 10566 | J62: =SUM(J56:J61) -> 10713.244 | K62: =SUM(K56:K61) -> 10927.436 | L62: =SUM(L56:L61) -> 10093.047 | M62: =SUM(M56:M61) -> 10187.617 | N62: =SUM(N56:N61) -> 12019.767
B63: Long-term debt | E63: 9413 | F63: 8920 | G63: 8927 | H63: 7903 | I63: 7961 | J63: =J130 -> 7008 | K63: =K130 -> 7007 | L63: =L130 -> 7007 | M63: =M130 -> 6507 | N63: =N130 -> 6518
B64: Operating lease liabilities | E64: 2931 | F64: 2777 | G64: 2786 | H64: 2566 | I64: 2550 | J64: =AVERAGE(G64:I64) -> 2634 | K64: =AVERAGE(H64:J64) -> 2583.3333 | L64: =AVERAGE(I64:K64) -> 2589.1111 | M64: =AVERAGE(J64:L64) -> 2602.1481 | N64: =AVERAGE(K64:M64) -> 2591.5309
B65: Deferred income taxes and other liabilities | E65: 2955 | F65: 2613 | G65: 2558 | H65: 2618 | I65: 2289 | J65: =AVERAGE(G65:I65) -> 2488.3333 | K65: =AVERAGE(H65:J65) -> 2465.1111 | L65: =AVERAGE(I65:K65) -> 2414.1481 | M65: =AVERAGE(J65:L65) -> 2455.8642 | N65: =AVERAGE(K65:M65) -> 2445.0412
B66: Total liabilities | E66: =E62+E63+E64+E65 -> 24973 | F66: =F62+F63+F64+F65 -> 25040 | G66: =G62+G63+G64+G65 -> 23527 | H66: =H62+H63+H64+H65 -> 23680 | I66: =I62+I63+I64+I65 -> 23366 | J66: =J62+SUM(J63:J65) -> 22843.578 | K66: =K62+SUM(K63:K65) -> 22982.88 | L66: =L62+SUM(L63:L65) -> 22103.306 | M66: =M62+SUM(M63:M65) -> 21752.63 | N66: =N62+SUM(N63:N65) -> 23574.339
B69: Balance Sheet — Shareholders' Equity | C69: Balance Sheet — Shareholders' Equity | D69: Balance Sheet — Shareholders' Equity | E69: Balance Sheet — Shareholders' Equity | F69: Balance Sheet — Shareholders' Equity | G69: Balance Sheet — Shareholders' Equity | H69: Balance Sheet — Shareholders' Equity | I69: Balance Sheet — Shareholders' Equity | J69: Balance Sheet — Shareholders' Equity | K69: Balance Sheet — Shareholders' Equity | L69: Balance Sheet — Shareholders' Equity | M69: Balance Sheet — Shareholders' Equity | N69: Balance Sheet — Shareholders' Equity
B70: Common stock | E70: 3 | F70: 3 | G70: 3 | H70: 3 | I70: 3 | J70: 3 | K70: 3 | L70: 3 | M70: 3 | N70: 3
B71: Capital in excess of stated value | E71: 9965 | F71: 11484 | G71: 12412 | H71: 13409 | I71: 14195 | J71: =I71*(1+0.06) -> 15046.7 | K71: =J71*(1+7%) -> 16099.969 | L71: =K71*(1+7%) -> 17226.967 | M71: =L71*(1+9.3%) -> 18829.075 | N71: =M71*(1+9.3%) -> 20580.179
B72: Accumulated other comprehensive income (loss) | E72: -380 | F72: 318 | G72: 231 | H72: 53 | I72: -258 | J72: -258 | K72: -258 | L72: -258 | M72: -258 | N72: -258
B73: Retained earnings (deficit) | E73: 3179 | F73: 3476 | G73: 1358 | H73: 965 | I73: -727 | J73: =I73+J33 -> 2001.4034 | K73: =J73+K33 -> 5350.0216 | L73: =K73+L33 -> 9889.7379 | M73: =L73+M33 -> 15852.979 | N73: =M73+N33 -> 22356.866
B74: Total shareholders' equity | E74: 12767 | F74: 15281 | G74: 14004 | H74: 14430 | I74: 13213 | J74: =SUM(J70:J73) -> 16793.103 | K74: =SUM(K70:K73) -> 21194.991 | L74: =SUM(L70:L73) -> 26861.705 | M74: =SUM(M70:M73) -> 34427.053 | N74: =SUM(N70:N73) -> 42682.045
B75: Total liabilities and shareholders' equity | E75: 37740 | F75: 40321 | G75: 37531 | H75: 38110 | I75: 36579 | J75: =J66+J74 -> 39636.681 | K75: =K66+K74 -> 44177.871 | L75: =L66+L74 -> 48965.011 | M75: =M66+M74 -> 56179.683 | N75: =N66+N74 -> 66256.384
B76: Balance sheet check | E76: =E52-E75 -> 0 | F76: =F52-F75 -> 0 | G76: =G52-G75 -> 0 | H76: =H52-H75 -> 0 | I76: =I52-I75 -> 0 | J76: =J52-J75 -> -4708.0384 | K76: =K52-K75 -> -6692.7897 | L76: =L52-L75 -> -9330.5062 | ... N76: =N52-N75 -> -19361.126
B79: Cash Flow Statement | C79: Cash Flow Statement | D79: Cash Flow Statement | E79: Cash Flow Statement | F79: Cash Flow Statement | G79: Cash Flow Statement | H79: Cash Flow Statement | I79: Cash Flow Statement | J79: Cash Flow Statement | K79: Cash Flow Statement | L79: Cash Flow Statement | M79: Cash Flow Statement | N79: Cash Flow Statement
B80: Net income | E80: 5727 | F80: 6046 | G80: 5070 | H80: 5700 | I80: 3219 | J80: =J33 -> 2728.4034 | K80: =K33 -> 3348.6183 | L80: =L33 -> 4539.7163 | M80: =M33 -> 5963.2408 | N80: =N33 -> 6503.8872
B81: Depreciation and amortization | E81: 744 | F81: 717 | G81: 703 | H81: 796 | I81: 775 | J81: =J123 -> 550.30743 | K81: =K123 -> 701.82913 | L81: =L123 -> 824.7085 | M81: =M123 -> 942.40422 | N81: =N123 -> 1077.7133
B82: Deferred income taxes | E82: -385 | F82: -650 | G82: -117 | H82: -497 | I82: -288 | J82: =-J80*5% -> -136.42017 | K82: =-K80*5% -> -167.43091 | L82: =-L80*5% -> -226.98582 | M82: =-M80*5% -> -298.16204 | N82: =-N80*5% -> -325.19436
B83: Stock-based compensation | E83: 611 | F83: 638 | G83: 755 | H83: 804 | I83: 709 | J83: =I83*(1+6%) -> 751.54 | K83: =J83*(1+6%) -> 796.6324 | L83: =K83*(1+6%) -> 844.43034 | M83: =L83*(1+6%) -> 895.09616 | N83: =M83*(1+6%) -> 948.80193
B84: Impairment and other | E84: 53 | F84: 123 | G84: 156 | H84: 48 | I84: 33 | J84: 50 | K84: 50 | L84: 50 | M84: 50 | N84: 50
B85: Net foreign currency adjustments | E85: -138 | F85: -26 | G85: -213 | H85: -138 | I85: 37 | J85: =-I85*(1+5%) -> -38.85 | K85: =J85*(1-150%) -> 19.425 | L85: =K85*(1+5%) -> 20.39625 | M85: =L85*(1+5%) -> 21.416063 | N85: =M85*(1+5%) -> 22.486866
B86: (Increase) decrease in accounts receivable | E86: -1606 | F86: -504 | G86: 489 | H86: -329 | I86: -257 | J86: =J43-I43 -> -744.57592 | K86: =K43-J43 -> 278.06969 | L86: =L43-K43 -> 340.0395 | M86: =M43-L43 -> 413.14799 | N86: =N43-M43 -> 450.33131
B87: (Increase) decrease in inventories | E87: 507 | F87: -1676 | G87: -133 | H87: 908 | I87: 120 | J87: =J44-I44 -> -428.33655 | K87: =K44-J44 -> 80.166081 | L87: =L44-K44 -> 55.941982 | M87: =M44-L44 -> 357.1731 | N87: =N44-M44 -> 679.85502
B88: (Increase) decrease in prepaid expenses, ROU assets and other assets | E88: -182 | F88: -845 | G88: -644 | H88: -260 | I88: -224 | J88: =J45-I45 -> -71.333333 | K88: =K45-J45 -> -2.7777778 | L88: =L45-K45 -> 25.62963 | M88: =M45-L45 -> -16.160494 | N88: =N45-M45 -> 2.2304527
B89: Increase (decrease) in accounts payable and other liabilities | E89: 1326 | F89: 1365 | G89: -225 | H89: 397 | I89: -426 | J89: =J58-I58 -> -506.08907 | K89: =K58-J58 -> 98.413603 | L89: =L58-K58 -> 127.24059 | M89: =M58-L58 -> 158.7436 | N89: =N58-M58 -> 302.15778
B90: Cash provided by operations | E90: 6657 | F90: 5188 | G90: 5841 | H90: 7429 | I90: 3698 | J90: =SUM(J80:J89) -> 2154.6457 | K90: =SUM(K80:K89) -> 5202.9455 | L90: =SUM(L80:L89) -> 6601.1173 | M90: =SUM(M80:M89) -> 8486.8994 | N90: =SUM(N80:N89) -> 9712.2695
B91: Purchases of short-term investments | E91: -9961 | F91: -12913 | G91: -6059 | H91: -4767 | I91: -3234 | J91: -2200 | K91: -2500 | L91: -3000 | M91: -3000 | N91: -3000
B92: Maturities of short-term investments | E92: 4236 | F92: 8199 | G92: 3356 | H92: 2269 | I92: 319 | J92: 2000 | K92: 2000 | L92: 2000 | M92: 2000 | N92: 2000
B93: Sales of short-term investments | E93: 2449 | F93: 3967 | G93: 4184 | H93: 4219 | I93: 3062 | J93: 4500 | K93: 4500 | L93: 2000 | M93: 2000 | N93: 2000
B94: Additions to property, plant and equipment | E94: -695 | F94: -758 | G94: -969 | H94: -812 | I94: -430 | J94: =J15 -> -1403.1627 | K94: =K15 -> -1501.3841 | L94: =L15 -> -1621.4948 | M94: =M15 -> -1767.4293 | N94: =N15 -> -1926.498
B95: Other investing activities | E95: 171 | F95: -19 | G95: 52 | H95: -15 | I95: 8 | J95: 8 | K95: 8 | L95: 8 | M95: 8 | N95: 8
B96: Cash provided (used) by investing activities | E96: -3800 | F96: -1524 | G96: 564 | H96: 894 | I96: -275 | J96: =SUM(J91:J95) -> 2904.8373 | K96: =SUM(K91:K95) -> 2506.6159 | L96: =SUM(L91:L95) -> -613.49482 | M96: =SUM(M91:M95) -> -759.42935 | N96: =SUM(N91:N95) -> -918.49799
B97: Increase (decrease) in notes payable, net | E97: -52 | F97: 15 | G97: -4 | H97: 0 | I97: -1 | J97: 0 | K97: 0 | L97: 0 | M97: 0 | N97: 0
B98: Repayment of borrowings | E98: -197 | F98: 0 | G98: -500 | H98: 0 | I98: -1000 | J98: =-J129 -> -1700 | K98: =-K129 -> -1000 | L98: =-L129 -> 0 | M98: =-M129 -> -500 | N98: =-N129 -> -1489
B99: Proceeds from exercise of stock options and other stock issuances | E99: 1172 | F99: 1151 | G99: 651 | H99: 667 | I99: 551 | J99: =I99*(1+5%) -> 578.55 | K99: =J99*(1+5%) -> 607.4775 | L99: =K99*(1+5%) -> 637.85138 | M99: =L99*(1+5%) -> 669.74394 | N99: =M99*(1+5%) -> 703.23114
B100: Repurchase of common stock | E100: -608 | F100: -4014 | G100: -5480 | H100: -4250 | I100: -2985 | J100: -1500 | K100: -3000 | L100: -3000 | M100: -3000 | N100: -3000
B101: Dividends — common and preferred | E101: -1638 | F101: -1837 | G101: -2012 | H101: -2169 | I101: -2300 | J101: =I101*(1+6%) -> -2438 | K101: =J101*(1+6%) -> -2584.28 | L101: =K101*(1+6%) -> -2739.3368 | M101: =L101*(1+6%) -> -2903.697 | N101: =M101*(1+6%) -> -3077.9188
B102: Other financing activities | E102: -136 | F102: -151 | G102: -102 | H102: -136 | I102: -85 | J102: -85 | K102: -85 | L102: -85 | M102: -85 | N102: -85
B103: Cash provided (used) by financing activities | E103: -1459 | F103: -4836 | G103: -7447 | H103: -5888 | I103: -5820 | J103: =SUM(J97:J102) -> -5144.45 | K103: =SUM(K97:K102) -> -6061.8025 | L103: =SUM(L97:L102) -> -5186.4854 | M103: =SUM(M97:M102) -> -5818.9531 | N103: =SUM(N97:N102) -> -6948.6877
B104: Effect of exchange rate changes on cash and equivalents | E104: 143 | F104: -143 | G104: -91 | H104: -16 | I104: 1 | J104: 1 | K104: 1 | L104: 1 | M104: 1 | N104: 1
B105: Net increase (decrease) in cash and equivalents | E105: 1541 | F105: -1315 | G105: -1133 | H105: 2419 | I105: -2396 | J105: =J90+J96+J103+J104 -> -83.966959 | K105: =K90+K96+K103+K104 -> 1648.7589 | L105: =L90+L96+L103+L104 -> 802.13705 | M105: =M90+M96+M103+M104 -> 1909.517 | N105: =N90+N96+N103+N104 -> 1846.0838
B106: Cash and equivalents, beginning of year | E106: 8348 | F106: 9889 | G106: 8574 | H106: 7441 | I106: 9860 | J106: =I107 -> 7464 | K106: =J107 -> 7380.033 | L106: =K107 -> 9028.7919 | M106: =L107 -> 9830.929 | N106: =M107 -> 11740.446
B107: Cash and equivalents, end of year | E107: 9889 | F107: 8574 | G107: 7441 | H107: 9860 | I107: 7464 | J107: =J105+J106 -> 7380.033 | K107: =K105+K106 -> 9028.7919 | L107: =L105+L106 -> 9830.929 | M107: =M105+M106 -> 11740.446 | N107: =N105+N106 -> 13586.53
B108: Cash flow reconciliation check | E108: =E107-E41 -> 0 | F108: =F107-F41 -> 0 | G108: =G107-G41 -> 0 | H108: =H107-H41 -> 0 | I108: =I107-I41 -> 0 | J108: =J107-J41 -> 0 | K108: =K107-K41 -> 0 | L108: =L107-L41 -> 0 | ... N108: =N107-N41 -> 0
B111: Supporting Schedule
B113: Working Capital Schedule
B114: Accounts Receivable | E114: =E43 -> 4463 | F114: =F43 -> 4667 | G114: =G43 -> 4131 | H114: =H43 -> 4427 | I114: =I43 -> 4717 | J114: =J43 -> 3972.4241 | K114: =K43 -> 4250.4938 | L114: =L43 -> 4590.5333 | ... N114: =N43 -> 5454.0126
B115: Inventory | E115: =E44 -> 6854 | F115: =F44 -> 8420 | G115: =G44 -> 8454 | H115: =H44 -> 7519 | I115: =I44 -> 7489 | J115: =J44 -> 7060.6634 | K115: =K44 -> 7140.8295 | L115: =L44 -> 7196.7715 | ... N115: =N44 -> 8233.7996
...

Sheet Simplified Model
B1: NIKE, Inc. — Simplified Three-Statement Model | P1: Model Check | Q1: Target
B2: USD $mm; historical data linked to Full Historical Statements. Forecast columns are intentionally blank for you to complete. | P2: Historical BS check | Q2: 0
P3: Historical cash check | Q3: 0
B4: Fiscal Year Ended May 31 | E4: 2021 | F4: 2022 | G4: 2023 | H4: 2024 | I4: 2025 | J4: 2026 | K4: 2027 | L4: 2028 | M4: 2029 | N4: 2030
J5: Forecast | K5: Forecast | L5: Forecast | M5: Forecast | N5: Forecast
B6: Income Statement | C6: Income Statement | D6: Income Statement | E6: Income Statement | F6: Income Statement | G6: Income Statement | H6: Income Statement | I6: Income Statement | J6: Income Statement | K6: Income Statement | L6: Income Statement | M6: Income Statement | N6: Income Statement
B7: Revenue | E7: ='Full Historical Statements'!E22 -> 44538 | F7: ='Full Historical Statements'!F22 -> 46710 | G7: ='Full Historical Statements'!G22 -> 51217 | H7: ='Full Historical Statements'!H22 -> 51362 | I7: ='Full Historical Statements'!I22 -> 46309 | J7: ='Full Historical Statements'!J22 -> 46772.09 | K7: ='Full Historical Statements'!K22 -> 50046.136 | L7: ='Full Historical Statements'!L22 -> 54049.827 | ... N7: ='Full Historical Statements'!N22 -> 64216.6
B8: Cost of sales | E8: ='Full Historical Statements'!E23 -> 24576 | F8: ='Full Historical Statements'!F23 -> 25231 | G8: ='Full Historical Statements'!G23 -> 28925 | H8: ='Full Historical Statements'!H23 -> 28475 | I8: ='Full Historical Statements'!I23 -> 26519 | J8: ='Full Historical Statements'!J23 -> 27127.812 | K8: ='Full Historical Statements'!K23 -> 28025.836 | L8: ='Full Historical Statements'!L23 -> 29186.907 | ... N8: ='Full Historical Statements'!N23 -> 33392.632
B9: Gross profit | E9: ='Full Historical Statements'!E24 -> 19962 | F9: ='Full Historical Statements'!F24 -> 21479 | G9: ='Full Historical Statements'!G24 -> 22292 | H9: ='Full Historical Statements'!H24 -> 22887 | I9: ='Full Historical Statements'!I24 -> 19790 | J9: ='Full Historical Statements'!J24 -> 19644.278 | K9: ='Full Historical Statements'!K24 -> 22020.3 | L9: ='Full Historical Statements'!L24 -> 24862.921 | ... N9: ='Full Historical Statements'!N24 -> 30823.968
B10: Selling and administrative expense | E10: ='Full Historical Statements'!E27 -> 13025 | F10: ='Full Historical Statements'!F27 -> 14804 | G10: ='Full Historical Statements'!G27 -> 16377 | H10: ='Full Historical Statements'!H27 -> 16576 | I10: ='Full Historical Statements'!I27 -> 16088 | J10: ='Full Historical Statements'!J27 -> 16370.231 | K10: ='Full Historical Statements'!K27 -> 18016.609 | L10: ='Full Historical Statements'!L27 -> 19457.938 | ... N10: ='Full Historical Statements'!N27 -> 23117.976
B11: Income from operations | E11: ='Full Historical Statements'!E28 -> 6937 | F11: ='Full Historical Statements'!F28 -> 6675 | G11: ='Full Historical Statements'!G28 -> 5915 | H11: ='Full Historical Statements'!H28 -> 6311 | I11: ='Full Historical Statements'!I28 -> 3702 | J11: ='Full Historical Statements'!J28 -> 3274.0463 | K11: ='Full Historical Statements'!K28 -> 4003.6909 | L11: ='Full Historical Statements'!L28 -> 5404.9827 | ... N11: ='Full Historical Statements'!N28 -> 7705.992
B12: Interest expense (income), net | E12: ='Full Historical Statements'!E29 -> 262 | F12: ='Full Historical Statements'!F29 -> 205 | G12: ='Full Historical Statements'!G29 -> -6 | H12: ='Full Historical Statements'!H29 -> -161 | I12: ='Full Historical Statements'!I29 -> -107 | J12: ='Full Historical Statements'!J29 -> 140.16 | K12: ='Full Historical Statements'!K29 -> 140.14 | L12: ='Full Historical Statements'!L29 -> 140.14 | ... N12: ='Full Historical Statements'!N29 -> 130.36
B13: Other (income) expense, net | E13: ='Full Historical Statements'!E30 -> 14 | F13: ='Full Historical Statements'!F30 -> -181 | G13: ='Full Historical Statements'!G30 -> -280 | H13: ='Full Historical Statements'!H30 -> -228 | I13: ='Full Historical Statements'!I30 -> -76 | J13: ='Full Historical Statements'!J30 -> -76 | K13: ='Full Historical Statements'!K30 -> -76 | L13: ='Full Historical Statements'!L30 -> -76 | ... N13: ='Full Historical Statements'!N30 -> -76
B14: Income before income taxes | E14: ='Full Historical Statements'!E31 -> 6661 | F14: ='Full Historical Statements'!F31 -> 6651 | G14: ='Full Historical Statements'!G31 -> 6201 | H14: ='Full Historical Statements'!H31 -> 6700 | I14: ='Full Historical Statements'!I31 -> 3885 | J14: ='Full Historical Statements'!J31 -> 3209.8863 | K14: ='Full Historical Statements'!K31 -> 3939.5509 | L14: ='Full Historical Statements'!L31 -> 5340.8427 | ... N14: ='Full Historical Statements'!N31 -> 7651.632
B15: Income tax expense | E15: ='Full Historical Statements'!E32 -> 934 | F15: ='Full Historical Statements'!F32 -> 605 | G15: ='Full Historical Statements'!G32 -> 1131 | H15: ='Full Historical Statements'!H32 -> 1000 | I15: ='Full Historical Statements'!I32 -> 666 | J15: ='Full Historical Statements'!J32 -> 481.48295 | K15: ='Full Historical Statements'!K32 -> 590.93264 | L15: ='Full Historical Statements'!L32 -> 801.12641 | ... N15: ='Full Historical Statements'!N32 -> 1147.7448
B16: Net income | E16: ='Full Historical Statements'!E80 -> 5727 | F16: ='Full Historical Statements'!F80 -> 6046 | G16: ='Full Historical Statements'!G80 -> 5070 | H16: ='Full Historical Statements'!H80 -> 5700 | I16: ='Full Historical Statements'!I80 -> 3219 | J16: ='Full Historical Statements'!J33 -> 2728.4034 | K16: ='Full Historical Statements'!K33 -> 3348.6183 | L16: ='Full Historical Statements'!L33 -> 4539.7163 | M16: ='Full Historical Statements'!M33 -> 5963.2408 | N16: ='Full Historical Statements'!N33 -> 6503.8872
B19: Balance Sheet — Assets | C19: Balance Sheet — Assets | D19: Balance Sheet — Assets | E19: Balance Sheet — Assets | F19: Balance Sheet — Assets | G19: Balance Sheet — Assets | H19: Balance Sheet — Assets | I19: Balance Sheet — Assets | J19: Balance Sheet — Assets | K19: Balance Sheet — Assets | L19: Balance Sheet — Assets | M19: Balance Sheet — Assets | N19: Balance Sheet — Assets
B20: Cash and equivalents | E20: ='Full Historical Statements'!E41 -> 9889 | F20: ='Full Historical Statements'!F41 -> 8574 | G20: ='Full Historical Statements'!G41 -> 7441 | H20: ='Full Historical Statements'!H41 -> 9860 | I20: ='Full Historical Statements'!I41 -> 7464 | J20: ='Full Historical Statements'!J41 -> 7380.033 | K20: ='Full Historical Statements'!K41 -> 9028.7919 | L20: ='Full Historical Statements'!L41 -> 9830.929 | ... N20: ='Full Historical Statements'!N41 -> 13586.53
B21: Short-term investments | E21: ='Full Historical Statements'!E42 -> 3587 | F21: ='Full Historical Statements'!F42 -> 4423 | G21: ='Full Historical Statements'!G42 -> 3234 | H21: ='Full Historical Statements'!H42 -> 1722 | I21: ='Full Historical Statements'!I42 -> 1687 | J21: ='Full Historical Statements'!J42 -> 2214.3333 | K21: ='Full Historical Statements'!K42 -> 1874.4444 | L21: ='Full Historical Statements'!L42 -> 1925.2593 | ... N21: ='Full Historical Statements'!N42 -> 1934.7942
B22: Accounts receivable, net | E22: ='Full Historical Statements'!E43 -> 4463 | F22: ='Full Historical Statements'!F43 -> 4667 | G22: ='Full Historical Statements'!G43 -> 4131 | H22: ='Full Historical Statements'!H43 -> 4427 | I22: ='Full Historical Statements'!I43 -> 4717 | J22: ='Full Historical Statements'!J43 -> 3972.4241 | K22: ='Full Historical Statements'!K43 -> 4250.4938 | L22: ='Full Historical Statements'!L43 -> 4590.5333 | ... N22: ='Full Historical Statements'!N43 -> 5454.0126
B23: Inventories | E23: ='Full Historical Statements'!E44 -> 6854 | F23: ='Full Historical Statements'!F44 -> 8420 | G23: ='Full Historical Statements'!G44 -> 8454 | H23: ='Full Historical Statements'!H44 -> 7519 | I23: ='Full Historical Statements'!I44 -> 7489 | J23: ='Full Historical Statements'!J44 -> 7060.6634 | K23: ='Full Historical Statements'!K44 -> 7140.8295 | L23: ='Full Historical Statements'!L44 -> 7196.7715 | ... N23: ='Full Historical Statements'!N44 -> 8233.7996
B24: Other current assets | E24: ='Full Historical Statements'!E45 -> 1498 | F24: ='Full Historical Statements'!F45 -> 2129 | G24: ='Full Historical Statements'!G45 -> 1942 | H24: ='Full Historical Statements'!H45 -> 1854 | I24: ='Full Historical Statements'!I45 -> 2005 | J24: ='Full Historical Statements'!J45 -> 1933.6667 | K24: ='Full Historical Statements'!K45 -> 1930.8889 | L24: ='Full Historical Statements'!L45 -> 1956.5185 | ... N24: ='Full Historical Statements'!N45 -> 1942.5885
B25: Total current assets | E25: =SUM(E20:E24) -> 26291 | F25: =SUM(F20:F24) -> 28213 | G25: =SUM(G20:G24) -> 25202 | H25: =SUM(H20:H24) -> 25382 | I25: =SUM(I20:I24) -> 23362 | J25: ='Full Historical Statements'!J46 -> 22561.121 | K25: ='Full Historical Statements'!K46 -> 24225.449 | L25: ='Full Historical Statements'!L46 -> 25500.012 | M25: ='Full Historical Statements'!M46 -> 28243.109 | N25: ='Full Historical Statements'!N46 -> 31151.725
B26: Property, plant and equipment, net | E26: ='Full Historical Statements'!E47 -> 4904 | F26: ='Full Historical Statements'!F47 -> 4791 | G26: ='Full Historical Statements'!G47 -> 5081 | H26: ='Full Historical Statements'!H47 -> 5000 | I26: ='Full Historical Statements'!I47 -> 4828 | J26: ='Full Historical Statements'!J47 -> 4456.8553 | K26: ='Full Historical Statements'!K47 -> 5256.4102 | L26: ='Full Historical Statements'!L47 -> 6053.1965 | ... N26: ='Full Historical Statements'!N47 -> 7727.0064
B27: Operating lease right-of-use assets, net | E27: ='Full Historical Statements'!E48 -> 3113 | F27: ='Full Historical Statements'!F48 -> 2926 | G27: ='Full Historical Statements'!G48 -> 2923 | H27: ='Full Historical Statements'!H48 -> 2718 | I27: ='Full Historical Statements'!I48 -> 2712 | J27: ='Full Historical Statements'!J48 -> 2784.3333 | K27: ='Full Historical Statements'!K48 -> 2738.1111 | L27: ='Full Historical Statements'!L48 -> 2744.8148 | ... N27: ='Full Historical Statements'!N48 -> 2746.2263
B28: Intangible assets and goodwill | E28: ='Full Historical Statements'!E49+'Full Historical Statements'!E50 -> 511 | F28: ='Full Historical Statements'!F49+'Full Historical Statements'!F50 -> 570 | G28: ='Full Historical Statements'!G49+'Full Historical Statements'!G50 -> 555 | H28: ='Full Historical Statements'!H49+'Full Historical Statements'!H50 -> 499 | I28: ='Full Historical Statements'!I49+'Full Historical Statements'!I50 -> 499 | J28: ='Full Historical Statements'!J49 -> 300 | K28: ='Full Historical Statements'!K49 -> 300 | L28: ='Full Historical Statements'!L49 -> 300 | M28: ='Full Historical Statements'!M49 -> 300 | N28: ='Full Historical Statements'!N49 -> 300
B29: Other non-current assets | E29: ='Full Historical Statements'!E51 -> 2921 | F29: ='Full Historical Statements'!F51 -> 3821 | G29: ='Full Historical Statements'!G51 -> 3770 | H29: ='Full Historical Statements'!H51 -> 4511 | I29: ='Full Historical Statements'!I51 -> 5178 | J29: ='Full Historical Statements'!J50+'Full Historical Statements'!J51 -> 4826.3333 | K29: ='Full Historical Statements'!K50+'Full Historical Statements'!K51 -> 4965.1111 | L29: ='Full Historical Statements'!L50+'Full Historical Statements'!L51 -> 5036.4815 | M29: ='Full Historical Statements'!M50+'Full Historical Statements'!M51 -> 4909.3086 | N29: ='Full Historical Statements'!N50+'Full Historical Statements'!N51 -> 4970.3004
B30: Total assets | E30: =SUM(E25:E29) -> 37740 | F30: =SUM(F25:F29) -> 40321 | G30: =SUM(G25:G29) -> 37531 | H30: =SUM(H25:H29) -> 38110 | I30: =SUM(I25:I29) -> 36579 | J30: =SUM(J25:J29) -> 34928.643 | K30: =SUM(K25:K29) -> 37485.081 | L30: =SUM(L25:L29) -> 39634.504 | ... N30: =SUM(N25:N29) -> 46895.258
B33: Balance Sheet — Liabilities | C33: Balance Sheet — Liabilities | D33: Balance Sheet — Liabilities | E33: Balance Sheet — Liabilities | F33: Balance Sheet — Liabilities | G33: Balance Sheet — Liabilities | H33: Balance Sheet — Liabilities | I33: Balance Sheet — Liabilities | J33: Balance Sheet — Liabilities | K33: Balance Sheet — Liabilities | L33: Balance Sheet — Liabilities | M33: Balance Sheet — Liabilities | N33: Balance Sheet — Liabilities
B34: Accounts payable | E34: ='Full Historical Statements'!E58 -> 2836 | F34: ='Full Historical Statements'!F58 -> 3358 | G34: ='Full Historical Statements'!G58 -> 2862 | H34: ='Full Historical Statements'!H58 -> 2851 | I34: ='Full Historical Statements'!I58 -> 3479 | J34: ='Full Historical Statements'!J58 -> 2972.9109 | K34: ='Full Historical Statements'!K58 -> 3071.3245 | L34: ='Full Historical Statements'!L58 -> 3198.5651 | ... N34: ='Full Historical Statements'!N58 -> 3659.4665
B35: Other current liabilities | E35: ='Full Historical Statements'!E56+'Full Historical Statements'!E57+'Full Historical Statements'!E59+'Full Historical Statements'!E60+'Full Historical Statements'!E61 -> 6838 | F35: ='Full Historical Statements'!F56+'Full Historical Statements'!F57+'Full Historical Statements'!F59+'Full Historical Statements'!F60+'Full Historical Statements'!F61 -> 7372 | G35: ='Full Historical Statements'!G56+'Full Historical Statements'!G57+'Full Historical Statements'!G59+'Full Historical Statements'!G60+'Full Historical Statements'!G61 -> 6394 | H35: ='Full Historical Statements'!H56+'Full Historical Statements'!H57+'Full Historical Statements'!H59+'Full Historical Statements'!H60+'Full Historical Statements'!H61 -> 7742 | I35: ='Full Historical Statements'!I56+'Full Historical Statements'!I57+'Full Historical Statements'!I59+'Full Historical Statements'!I60+'Full Historical Statements'!I61 -> 7087 | J35: ='Full Historical Statements'!J56+'Full Historical Statements'!J57+'Full Historical Statements'!J59+'Full Historical Statements'!J60+'Full Historical Statements'!J61 -> 7740.3333 | K35: ='Full Historical Statements'!K56+'Full Historical Statements'!K57+'Full Historical Statements'!K59+'Full Historical Statements'!K60+'Full Historical Statements'!K61 -> 7856.1111 | L35: ='Full Historical Statements'!L56+'Full Historical Statements'!L57+'Full Historical Statements'!L59+'Full Historical Statements'!L60+'Full Historical Statements'!L61 -> 6894.4815 | ... N35: ='Full Historical Statements'!N56+'Full Historical Statements'!N57+'Full Historical Statements'!N59+'Full Historical Statements'!N60+'Full Historical Statements'!N61 -> 8360.3004
B36: Total current liabilities | E36: =SUM(E34:E35) -> 9674 | F36: =SUM(F34:F35) -> 10730 | G36: =SUM(G34:G35) -> 9256 | H36: =SUM(H34:H35) -> 10593 | I36: =SUM(I34:I35) -> 10566 | J36: =SUM(J34:J35) -> 10713.244 | K36: =SUM(K34:K35) -> 10927.436 | L36: =SUM(L34:L35) -> 10093.047 | ... N36: =SUM(N34:N35) -> 12019.767
B37: Long-term debt | E37: ='Full Historical Statements'!E63 -> 9413 | F37: ='Full Historical Statements'!F63 -> 8920 | G37: ='Full Historical Statements'!G63 -> 8927 | H37: ='Full Historical Statements'!H63 -> 7903 | I37: ='Full Historical Statements'!I63 -> 7961 | J37: ='Full Historical Statements'!J63 -> 7008 | K37: ='Full Historical Statements'!K63 -> 7007 | L37: ='Full Historical Statements'!L63 -> 7007 | ... N37: ='Full Historical Statements'!N63 -> 6518
B38: Other non-current liabilities | E38: ='Full Historical Statements'!E64+'Full Historical Statements'!E65 -> 5886 | F38: ='Full Historical Statements'!F64+'Full Historical Statements'!F65 -> 5390 | G38: ='Full Historical Statements'!G64+'Full Historical Statements'!G65 -> 5344 | H38: ='Full Historical Statements'!H64+'Full Historical Statements'!H65 -> 5184 | I38: ='Full Historical Statements'!I64+'Full Historical Statements'!I65 -> 4839 | J38: ='Full Historical Statements'!J64+'Full Historical Statements'!J65 -> 5122.3333 | K38: ='Full Historical Statements'!K64+'Full Historical Statements'!K65 -> 5048.4444 | L38: ='Full Historical Statements'!L64+'Full Historical Statements'!L65 -> 5003.2593 | ... N38: ='Full Historical Statements'!N64+'Full Historical Statements'!N65 -> 5036.572
B39: Total liabilities | E39: =E36+E37+E38 -> 24973 | F39: =F36+F37+F38 -> 25040 | G39: =G36+G37+G38 -> 23527 | H39: =H36+H37+H38 -> 23680 | I39: =I36+I37+I38 -> 23366 | J39: =J36+J37+J38 -> 22843.578 | K39: =K36+K37+K38 -> 22982.88 | L39: =L36+L37+L38 -> 22103.306 | ... N39: =N36+N37+N38 -> 23574.339
B42: Balance Sheet — Shareholders' Equity | C42: Balance Sheet — Shareholders' Equity | D42: Balance Sheet — Shareholders' Equity | E42: Balance Sheet — Shareholders' Equity | F42: Balance Sheet — Shareholders' Equity | G42: Balance Sheet — Shareholders' Equity | H42: Balance Sheet — Shareholders' Equity | I42: Balance Sheet — Shareholders' Equity | J42: Balance Sheet — Shareholders' Equity | K42: Balance Sheet — Shareholders' Equity | L42: Balance Sheet — Shareholders' Equity | M42: Balance Sheet — Shareholders' Equity | N42: Balance Sheet — Shareholders' Equity
B43: Common stock | E43: ='Full Historical Statements'!E70 -> 3 | F43: ='Full Historical Statements'!F70 -> 3 | G43: ='Full Historical Statements'!G70 -> 3 | H43: ='Full Historical Statements'!H70 -> 3 | I43: ='Full Historical Statements'!I70 -> 3 | J43: ='Full Historical Statements'!J70 -> 3 | K43: ='Full Historical Statements'!K70 -> 3 | L43: ='Full Historical Statements'!L70 -> 3 | ... N43: ='Full Historical Statements'!N70 -> 3
B44: Capital in excess of stated value | E44: ='Full Historical Statements'!E71 -> 9965 | F44: ='Full Historical Statements'!F71 -> 11484 | G44: ='Full Historical Statements'!G71 -> 12412 | H44: ='Full Historical Statements'!H71 -> 13409 | I44: ='Full Historical Statements'!I71 -> 14195 | J44: ='Full Historical Statements'!J71 -> 15046.7 | K44: ='Full Historical Statements'!K71 -> 16099.969 | L44: ='Full Historical Statements'!L71 -> 17226.967 | ... N44: ='Full Historical Statements'!N71 -> 20580.179
B45: Accumulated other comprehensive income (loss) | E45: ='Full Historical Statements'!E72 -> -380 | F45: ='Full Historical Statements'!F72 -> 318 | G45: ='Full Historical Statements'!G72 -> 231 | H45: ='Full Historical Statements'!H72 -> 53 | I45: ='Full Historical Statements'!I72 -> -258 | J45: ='Full Historical Statements'!J72 -> -258 | K45: ='Full Historical Statements'!K72 -> -258 | L45: ='Full Historical Statements'!L72 -> -258 | ... N45: ='Full Historical Statements'!N72 -> -258
B46: Retained earnings (deficit) | E46: ='Full Historical Statements'!E73 -> 3179 | F46: ='Full Historical Statements'!F73 -> 3476 | G46: ='Full Historical Statements'!G73 -> 1358 | H46: ='Full Historical Statements'!H73 -> 965 | I46: ='Full Historical Statements'!I73 -> -727 | J46: ='Full Historical Statements'!J73 -> 2001.4034 | K46: ='Full Historical Statements'!K73 -> 5350.0216 | L46: ='Full Historical Statements'!L73 -> 9889.7379 | ... N46: ='Full Historical Statements'!N73 -> 22356.866
B47: Total shareholders' equity | E47: =SUM(E43:E46) -> 12767 | F47: =SUM(F43:F46) -> 15281 | G47: =SUM(G43:G46) -> 14004 | H47: =SUM(H43:H46) -> 14430 | I47: =SUM(I43:I46) -> 13213 | J47: =SUM(J43:J46) -> 16793.103 | K47: =SUM(K43:K46) -> 21194.991 | L47: =SUM(L43:L46) -> 26861.705 | ... N47: =SUM(N43:N46) -> 42682.045
B48: Total liabilities and shareholders' equity | E48: =E39+E47 -> 37740 | F48: =F39+F47 -> 40321 | G48: =G39+G47 -> 37531 | H48: =H39+H47 -> 38110 | I48: =I39+I47 -> 36579 | J48: =J39+J47 -> 39636.681 | K48: =K39+K47 -> 44177.871 | L48: =L39+L47 -> 48965.011 | ... N48: =N39+N47 -> 66256.384
B49: Balance sheet check | E49: =E30-E48 -> 0 | F49: =F30-F48 -> 0 | G49: =G30-G48 -> 0 | H49: =H30-H48 -> 0 | I49: =I30-I48 -> 0
B52: Cash Flow Statement | C52: Cash Flow Statement | D52: Cash Flow Statement | E52: Cash Flow Statement | F52: Cash Flow Statement | G52: Cash Flow Statement | H52: Cash Flow Statement | I52: Cash Flow Statement | J52: Cash Flow Statement | K52: Cash Flow Statement | L52: Cash Flow Statement | M52: Cash Flow Statement | N52: Cash Flow Statement
B53: Net income | E53: ='Full Historical Statements'!E80 -> 5727 | F53: ='Full Historical Statements'!F80 -> 6046 | G53: ='Full Historical Statements'!G80 -> 5070 | H53: ='Full Historical Statements'!H80 -> 5700 | I53: ='Full Historical Statements'!I80 -> 3219 | J53: ='Full Historical Statements'!J80 -> 2728.4034 | K53: ='Full Historical Statements'!K80 -> 3348.6183 | L53: ='Full Historical Statements'!L80 -> 4539.7163 | ... N53: ='Full Historical Statements'!N80 -> 6503.8872
B54: Depreciation and amortization | E54: ='Full Historical Statements'!E81 -> 744 | F54: ='Full Historical Statements'!F81 -> 717 | G54: ='Full Historical Statements'!G81 -> 703 | H54: ='Full Historical Statements'!H81 -> 796 | I54: ='Full Historical Statements'!I81 -> 775 | J54: ='Full Historical Statements'!J81 -> 550.30743 | K54: ='Full Historical Statements'!K81 -> 701.82913 | L54: ='Full Historical Statements'!L81 -> 824.7085 | ... N54: ='Full Historical Statements'!N81 -> 1077.7133
B55: Other non-cash adjustments | E55: ='Full Historical Statements'!E82+'Full Historical Statements'!E83+'Full Historical Statements'!E84+'Full Historical Statements'!E85 -> 141 | F55: ='Full Historical Statements'!F82+'Full Historical Statements'!F83+'Full Historical Statements'!F84+'Full Historical Statements'!F85 -> 85 | G55: ='Full Historical Statements'!G82+'Full Historical Statements'!G83+'Full Historical Statements'!G84+'Full Historical Statements'!G85 -> 581 | H55: ='Full Historical Statements'!H82+'Full Historical Statements'!H83+'Full Historical Statements'!H84+'Full Historical Statements'!H85 -> 217 | I55: ='Full Historical Statements'!I82+'Full Historical Statements'!I83+'Full Historical Statements'!I84+'Full Historical Statements'!I85 -> 491 | J55: =SUM('Full Historical Statements'!J82:J85) -> 626.26983 | K55: =SUM('Full Historical Statements'!K82:K85) -> 698.62649 | L55: =SUM('Full Historical Statements'!L82:L85) -> 687.84078 | M55: =SUM('Full Historical Statements'!M82:M85) -> 668.35019 | N55: =SUM('Full Historical Statements'!N82:N85) -> 696.09444
B56: Change in net working capital and other operating items | E56: ='Full Historical Statements'!E86+'Full Historical Statements'!E87+'Full Historical Statements'!E88+'Full Historical Statements'!E89 -> 45 | F56: ='Full Historical Statements'!F86+'Full Historical Statements'!F87+'Full Historical Statements'!F88+'Full Historical Statements'!F89 -> -1660 | G56: ='Full Historical Statements'!G86+'Full Historical Statements'!G87+'Full Historical Statements'!G88+'Full Historical Statements'!G89 -> -513 | H56: ='Full Historical Statements'!H86+'Full Historical Statements'!H87+'Full Historical Statements'!H88+'Full Historical Statements'!H89 -> 716 | I56: ='Full Historical Statements'!I86+'Full Historical Statements'!I87+'Full Historical Statements'!I88+'Full Historical Statements'!I89 -> -787 | J56: =SUM('Full Historical Statements'!J86:J89) -> -1750.3349 | K56: =SUM('Full Historical Statements'!K86:K89) -> 453.87159 | L56: =SUM('Full Historical Statements'!L86:L89) -> 548.8517 | M56: =SUM('Full Historical Statements'!M86:M89) -> 912.90421 | N56: =SUM('Full Historical Statements'!N86:N89) -> 1434.5746
B57: Cash provided by operating activities | E57: ='Full Historical Statements'!E90 -> 6657 | F57: ='Full Historical Statements'!F90 -> 5188 | G57: ='Full Historical Statements'!G90 -> 5841 | H57: ='Full Historical Statements'!H90 -> 7429 | I57: ='Full Historical Statements'!I90 -> 3698 | J57: ='Full Historical Statements'!J90 -> 2154.6457 | K57: ='Full Historical Statements'!K90 -> 5202.9455 | L57: ='Full Historical Statements'!L90 -> 6601.1173 | ... N57: ='Full Historical Statements'!N90 -> 9712.2695
B58: Capital expenditures | E58: ='Full Historical Statements'!E94 -> -695 | F58: ='Full Historical Statements'!F94 -> -758 | G58: ='Full Historical Statements'!G94 -> -969 | H58: ='Full Historical Statements'!H94 -> -812 | I58: ='Full Historical Statements'!I94 -> -430 | J58: ='Full Historical Statements'!J94 -> -1403.1627 | K58: ='Full Historical Statements'!K94 -> -1501.3841 | L58: ='Full Historical Statements'!L94 -> -1621.4948 | ... N58: ='Full Historical Statements'!N94 -> -1926.498
B59: Other investing activities | E59: ='Full Historical Statements'!E91+'Full Historical Statements'!E92+'Full Historical Statements'!E93+'Full Historical Statements'!E95 -> -3105 | F59: ='Full Historical Statements'!F91+'Full Historical Statements'!F92+'Full Historical Statements'!F93+'Full Historical Statements'!F95 -> -766 | G59: ='Full Historical Statements'!G91+'Full Historical Statements'!G92+'Full Historical Statements'!G93+'Full Historical Statements'!G95 -> 1533 | H59: ='Full Historical Statements'!H91+'Full Historical Statements'!H92+'Full Historical Statements'!H93+'Full Historical Statements'!H95 -> 1706 | I59: ='Full Historical Statements'!I91+'Full Historical Statements'!I92+'Full Historical Statements'!I93+'Full Historical Statements'!I95 -> 155 | J59: =SUM('Full Historical Statements'!J91:J93,'Full Historical Statements'!J95) -> 4308 | K59: =SUM('Full Historical Statements'!K91:K93,'Full Historical Statements'!K95) -> 4008 | L59: =SUM('Full Historical Statements'!L91:L93,'Full Historical Statements'!L95) -> 1008 | M59: =SUM('Full Historical Statements'!M91:M93,'Full Historical Statements'!M95) -> 1008 | N59: =SUM('Full Historical Statements'!N91:N93,'Full Historical Statements'!N95) -> 1008
B60: Cash provided by / (used in) investing activities | E60: ='Full Historical Statements'!E96 -> -3800 | F60: ='Full Historical Statements'!F96 -> -1524 | G60: ='Full Historical Statements'!G96 -> 564 | H60: ='Full Historical Statements'!H96 -> 894 | I60: ='Full Historical Statements'!I96 -> -275 | J60: ='Full Historical Statements'!J96 -> 2904.8373 | K60: ='Full Historical Statements'!K96 -> 2506.6159 | L60: ='Full Historical Statements'!L96 -> -613.49482 | ... N60: ='Full Historical Statements'!N96 -> -918.49799
B61: Net debt issuance / (repayment) | E61: ='Full Historical Statements'!E97+'Full Historical Statements'!E98 -> -249 | F61: ='Full Historical Statements'!F97+'Full Historical Statements'!F98 -> 15 | G61: ='Full Historical Statements'!G97+'Full Historical Statements'!G98 -> -504 | H61: ='Full Historical Statements'!H97+'Full Historical Statements'!H98 -> 0 | I61: ='Full Historical Statements'!I97+'Full Historical Statements'!I98 -> -1001 | J61: ='Full Historical Statements'!J97+'Full Historical Statements'!J98 -> -1700 | K61: ='Full Historical Statements'!K97+'Full Historical Statements'!K98 -> -1000 | L61: ='Full Historical Statements'!L97+'Full Historical Statements'!L98 -> 0 | ... N61: ='Full Historical Statements'!N97+'Full Historical Statements'!N98 -> -1489
B62: Share repurchases, dividends and other financing | E62: ='Full Historical Statements'!E99+'Full Historical Statements'!E100+'Full Historical Statements'!E101+'Full Historical Statements'!E102 -> -1210 | F62: ='Full Historical Statements'!F99+'Full Historical Statements'!F100+'Full Historical Statements'!F101+'Full Historical Statements'!F102 -> -4851 | G62: ='Full Historical Statements'!G99+'Full Historical Statements'!G100+'Full Historical Statements'!G101+'Full Historical Statements'!G102 -> -6943 | H62: ='Full Historical Statements'!H99+'Full Historical Statements'!H100+'Full Historical Statements'!H101+'Full Historical Statements'!H102 -> -5888 | I62: ='Full Historical Statements'!I99+'Full Historical Statements'!I100+'Full Historical Statements'!I101+'Full Historical Statements'!I102 -> -4819 | J62: =SUM('Full Historical Statements'!J99:J102) -> -3444.45 | K62: =SUM('Full Historical Statements'!K99:K102) -> -5061.8025 | L62: =SUM('Full Historical Statements'!L99:L102) -> -5186.4854 | M62: =SUM('Full Historical Statements'!M99:M102) -> -5318.9531 | N62: =SUM('Full Historical Statements'!N99:N102) -> -5459.6877
B63: Cash provided by / (used in) financing activities | E63: ='Full Historical Statements'!E103 -> -1459 | F63: ='Full Historical Statements'!F103 -> -4836 | G63: ='Full Historical Statements'!G103 -> -7447 | H63: ='Full Historical Statements'!H103 -> -5888 | I63: ='Full Historical Statements'!I103 -> -5820 | J63: ='Full Historical Statements'!J103 -> -5144.45 | K63: ='Full Historical Statements'!K103 -> -6061.8025 | L63: ='Full Historical Statements'!L103 -> -5186.4854 | ... N63: ='Full Historical Statements'!N103 -> -6948.6877
B64: Effect of exchange rate changes | E64: ='Full Historical Statements'!E104 -> 143 | F64: ='Full Historical Statements'!F104 -> -143 | G64: ='Full Historical Statements'!G104 -> -91 | H64: ='Full Historical Statements'!H104 -> -16 | I64: ='Full Historical Statements'!I104 -> 1 | J64: ='Full Historical Statements'!J104 -> 1 | K64: ='Full Historical Statements'!K104 -> 1 | L64: ='Full Historical Statements'!L104 -> 1 | ... N64: ='Full Historical Statements'!N104 -> 1
B65: Net change in cash | E65: ='Full Historical Statements'!E105 -> 1541 | F65: ='Full Historical Statements'!F105 -> -1315 | G65: ='Full Historical Statements'!G105 -> -1133 | H65: ='Full Historical Statements'!H105 -> 2419 | I65: ='Full Historical Statements'!I105 -> -2396 | J65: ='Full Historical Statements'!J105 -> -83.966959 | K65: ='Full Historical Statements'!K105 -> 1648.7589 | L65: ='Full Historical Statements'!L105 -> 802.13705 | ... N65: ='Full Historical Statements'!N105 -> 1846.0838
B66: Cash — beginning of year | E66: ='Full Historical Statements'!E106 -> 8348 | F66: ='Full Historical Statements'!F106 -> 9889 | G66: ='Full Historical Statements'!G106 -> 8574 | H66: ='Full Historical Statements'!H106 -> 7441 | I66: ='Full Historical Statements'!I106 -> 9860 | J66: ='Full Historical Statements'!J106 -> 7464 | K66: ='Full Historical Statements'!K106 -> 7380.033 | L66: ='Full Historical Statements'!L106 -> 9028.7919 | ... N66: ='Full Historical Statements'!N106 -> 11740.446
B67: Cash — end of year | E67: ='Full Historical Statements'!E107 -> 9889 | F67: ='Full Historical Statements'!F107 -> 8574 | G67: ='Full Historical Statements'!G107 -> 7441 | H67: ='Full Historical Statements'!H107 -> 9860 | I67: ='Full Historical Statements'!I107 -> 7464 | J67: ='Full Historical Statements'!J107 -> 7380.033 | K67: ='Full Historical Statements'!K107 -> 9028.7919 | L67: ='Full Historical Statements'!L107 -> 9830.929 | ... N67: ='Full Historical Statements'!N107 -> 13586.53
B68: Cash flow reconciliation check | E68: =E67-E20 -> 0 | F68: =F67-F20 -> 0 | G68: =G67-G20 -> 0 | H68: =H67-H20 -> 0 | I68: =I67-I20 -> 0

Sheet DCF
F5: Year -2 | G5: Year -2 | H5: Year 0 | I5: Year 1 | J5: Year 2 | K5: Year 3 | L5: Year 4 | M5: Year 5 | N5: Term
B7: Revenue Growth | G7: =G13/F13-1 -> 0.0028310912 | H7: =H13/G13-1 -> -0.098380125 | I7: =I13/H13-1 -> 0.01 | J7: =J13/I13-1 -> 0.07 | K7: =K13/J13-1 -> 0.08 | L7: =L13/K13-1 -> 0.09 | M7: =M13/L13-1 -> 0.09 | N7: 0.1
B8: COGS | C8: (% of Revenue) | F8: =-F14/F13 -> 0.56475389 | G8: =-G14/G13 -> 0.55439819 | H8: =-H14/H13 -> 0.57265326 | I8: =-I14/I13 -> 0.58 | J8: =-J14/J13 -> 0.56 | K8: =-K14/K13 -> 0.54 | L8: =-L14/L13 -> 0.52 | M8: =-M14/M13 -> 0.52 | N8: 0.01
B9: SG&A | C9: (% of Revenue) | F9: =F17/F13 -> 0.31975711 | G9: =G17/G13 -> 0.32272887 | H9: =H17/H13 -> 0.34740547 | I9: =I17/I13 -> 0.35 | J9: =J17/J13 -> 0.36 | K9: =K17/K13 -> 0.36 | L9: =L17/L13 -> 0.36 | M9: =M17/M13 -> 0.36 | N9: 0.35
B11: Depreciation Growth | G11: =G20/F20-1 -> 0.13229018 | H11: =H20/G20-1 -> -0.02638191 | I11: =I20/H20-1 -> -0.2899259 | J11: =J20/I20-1 -> 0.27534009 | K11: =K20/J20-1 -> 0.17508446 | L11: =L20/K20-1 -> 0.1427119 | M11: =M20/L20-1 -> 0.1435786 | N11: 0.14
B13: Revenue | F13: ='Simplified Model'!G7 -> 51217 | G13: ='Simplified Model'!H7 -> 51362 | H13: ='Simplified Model'!I7 -> 46309 | I13: ='Simplified Model'!J7 -> 46772.09 | J13: ='Simplified Model'!K7 -> 50046.136 | K13: ='Simplified Model'!L7 -> 54049.827 | L13: ='Simplified Model'!M7 -> 58914.312 | M13: ='Simplified Model'!N7 -> 64216.6 | N13: =M13*(1+N7) -> 70638.26
B14: COGS | F14: =-'Simplified Model'!G8 -> -28925 | G14: =-'Simplified Model'!H8 -> -28475 | H14: =-'Simplified Model'!I8 -> -26519 | I14: =-'Simplified Model'!J8 -> -27127.812 | J14: =-'Simplified Model'!K8 -> -28025.836 | K14: =-'Simplified Model'!L8 -> -29186.907 | L14: =-'Simplified Model'!M8 -> -30635.442 | M14: =-'Simplified Model'!N8 -> -33392.632 | N14: =M14*(1+N8) -> -33726.558
B15: Gross Profit | F15: =F13+F14 -> 22292 | G15: =G13+G14 -> 22887 | H15: =H13+H14 -> 19790 | I15: =I13+I14 -> 19644.278 | J15: =J13+J14 -> 22020.3 | K15: =K13+K14 -> 24862.921 | L15: =L13+L14 -> 28278.87 | M15: =M13+M14 -> 30823.968 | N15: =N13+N14 -> 36911.702
B17: SG&A | F17: ='Simplified Model'!G10 -> 16377 | G17: ='Simplified Model'!H10 -> 16576 | H17: ='Simplified Model'!I10 -> 16088 | I17: ='Simplified Model'!J10 -> 16370.231 | J17: ='Simplified Model'!K10 -> 18016.609 | K17: ='Simplified Model'!L10 -> 19457.938 | L17: ='Simplified Model'!M10 -> 21209.152 | M17: ='Simplified Model'!N10 -> 23117.976 | N17: =N13*N9 -> 24723.391
B18: EBITDA | F18: =F21-F20 -> 6618 | G18: =G21-G20 -> 7107 | H18: =H21-H20 -> 4477 | I18: =I21-I20 -> 3824.3537 | J18: =J21-J20 -> 4705.52 | K18: =K21-K20 -> 6229.6912 | L18: =L21-L20 -> 8012.1216 | M18: =M21-M20 -> 8783.7053 | N18: =N21-N20 -> 13416.904
B20: Depreciation | F20: =-'Simplified Model'!G54 -> -703 | G20: =-'Simplified Model'!H54 -> -796 | H20: =-'Simplified Model'!I54 -> -775 | I20: =-'Simplified Model'!J54 -> -550.30743 | J20: =-'Simplified Model'!K54 -> -701.82913 | K20: =-'Simplified Model'!L54 -> -824.7085 | L20: =-'Simplified Model'!M54 -> -942.40422 | M20: =-'Simplified Model'!N54 -> -1077.7133 | N20: =M20*(1+N11) -> -1228.5932
B21: Operating Profit | F21: =F15-F17 -> 5915 | G21: =G15-G17 -> 6311 | H21: =H15-H17 -> 3702 | I21: =I15-I17 -> 3274.0463 | J21: =J15-J17 -> 4003.6909 | K21: =K15-K17 -> 5404.9827 | L21: =L15-L17 -> 7069.7174 | M21: =M15-M17 -> 7705.992 | N21: =N15-N17 -> 12188.311
B23: Tax Rate | F23: ='Full Historical Statements'!G11 -> 0.18238994 | G23: ='Full Historical Statements'!H11 -> 0.14925373 | H23: ='Full Historical Statements'!I11 -> 0.17142857 | I23: ='Full Historical Statements'!J11 -> 0.15 | J23: ='Full Historical Statements'!K11 -> 0.15 | K23: ='Full Historical Statements'!L11 -> 0.15 | L23: ='Full Historical Statements'!M11 -> 0.15 | M23: ='Full Historical Statements'!N11 -> 0.15 | N23: 0.15
B24: Current Tax | F24: ='Simplified Model'!G15 -> 1131 | G24: ='Simplified Model'!H15 -> 1000 | H24: ='Simplified Model'!I15 -> 666 | I24: ='Simplified Model'!J15 -> 481.48295 | J24: ='Simplified Model'!K15 -> 590.93264 | K24: ='Simplified Model'!L15 -> 801.12641 | L24: ='Simplified Model'!M15 -> 1052.3366 | M24: ='Simplified Model'!N15 -> 1147.7448 | N24: =N21*N23 -> 1828.2466
B29: UNLEVERED FREE CASH FLOW
F32: Year -2 | G32: Year -2 | H32: Year 0 | I32: Year 1 | J32: Year 2 | K32: Year 3 | L32: Year 4 | M32: Year 5 | N32: Term
B33: Unlevered Free Cash Flow
B34: EBIT | F34: =F21 -> 5915 | G34: =G21 -> 6311 | H34: =H21 -> 3702 | I34: =I21 -> 3274.0463 | J34: =J21 -> 4003.6909 | K34: =K21 -> 5404.9827 | L34: =L21 -> 7069.7174 | M34: =M21 -> 7705.992 | N34: =N21 -> 12188.311
B35: Current Taxes | F35: =F24 -> 1131 | G35: =G24 -> 1000 | H35: =H24 -> 666 | I35: =I24 -> 481.48295 | J35: =J24 -> 590.93264 | K35: =K24 -> 801.12641 | L35: =L24 -> 1052.3366 | M35: =M24 -> 1147.7448 | N35: =N24 -> 1828.2466
B36: NOPAT | F36: =F34-F35 -> 4784 | G36: =G34-G35 -> 5311 | H36: =H34-H35 -> 3036 | I36: =I34-I35 -> 2792.5634 | J36: =J34-J35 -> 3412.7583 | K36: =K34-K35 -> 4603.8563 | L36: =L34-L35 -> 6017.3808 | M36: =M34-M35 -> 6558.2472 | N36: =N34-N35 -> 10360.064
B37: D&A | F37: =-F20 -> 703 | G37: =-G20 -> 796 | H37: =-H20 -> 775 | I37: =-I20 -> 550.30743 | J37: =-J20 -> 701.82913 | K37: =-K20 -> 824.7085 | L37: =-L20 -> 942.40422 | M37: =-M20 -> 1077.7133 | N37: =-N20 -> 1228.5932
B38: Capital Expenditure | F38: ='Simplified Model'!G58 -> -969 | G38: ='Simplified Model'!H58 -> -812 | H38: ='Simplified Model'!I58 -> -430 | I38: ='Simplified Model'!J58 -> -1403.1627 | J38: ='Simplified Model'!K58 -> -1501.3841 | K38: ='Simplified Model'!L58 -> -1621.4948 | L38: ='Simplified Model'!M58 -> -1767.4293 | M38: ='Simplified Model'!N58 -> -1926.498 | N38: -1800
B39: Cash from Working Capital | F39: ='Simplified Model'!G56 -> -513 | G39: ='Simplified Model'!H56 -> 716 | H39: ='Simplified Model'!I56 -> -787 | I39: ='Simplified Model'!J56 -> -1750.3349 | J39: ='Simplified Model'!K56 -> 453.87159 | K39: ='Simplified Model'!L56 -> 548.8517 | L39: ='Simplified Model'!M56 -> 912.90421 | M39: ='Simplified Model'!N56 -> 1434.5746 | N39: 1500
B40: Unlevered Free Cash Flow | F40: =SUM(F36:F39) -> 4005 | G40: =SUM(G36:G39) -> 6011 | H40: =SUM(H36:H39) -> 2594 | I40: =SUM(I36:I39) -> 189.37321 | J40: =SUM(J36:J39) -> 3067.0749 | K40: =SUM(K36:K39) -> 4355.9217 | L40: =SUM(L36:L39) -> 6105.2599 | M40: =SUM(M36:M39) -> 7144.037 | N40: =SUM(N36:N39) -> 11288.657
B44: DISCOUNTED CASH FLOW SCHEDULE
I46: Year 1 | J46: Year 2 | K46: Year 3 | L46: Year 4 | M46: Year 5 | N46: Term
B48: Unlevered Free Cash Flow | I48: =I40 -> 189.37321 | J48: =J40 -> 3067.0749 | K48: =K40 -> 4355.9217 | L48: =L40 -> 6105.2599 | M48: =M40 -> 7144.037 | N48: =N40 -> 11288.657
B49: EBITDA | N49: =N48+N18 -> 24705.561
B52: UNDISCOUNTED CASH FLOW
B53: Discrete Forecast | I53: =I48 -> 189.37321 | J53: =J48 -> 3067.0749 | K53: =K48 -> 4355.9217 | L53: =L48 -> 6105.2599 | M53: =M48 -> 7144.037 | N53: =N48 -> 11288.657
B54: Terminal Value | I54: 0 | J54: 0 | K54: 0 | L54: 0 | M54: 0 | N54: =N53*D61 -> 135463.89
B55: Total Cash Flow | I55: =SUM(I53:I54) -> 189.37321 | J55: =SUM(J53:J54) -> 3067.0749 | K55: =SUM(K53:K54) -> 4355.9217 | L55: =SUM(L53:L54) -> 6105.2599 | M55: =SUM(M53:M54) -> 7144.037 | N55: =SUM(N53:N54) -> 146752.54
B59: ASSUMPTIONS | G59: ENTERPRISE VALUE | K59: EQUITY VALUE PER SHARE
B60: First Year of Forecast | D60: 2026 | G60: PV of Discrete | I60: =NPV(D62,I53,J53,K53,L53,M53) -> 14802.199 | K60: Equity Value | N60: =I75 -> 87783.543
B61: Terminal Multiple | D61: 12 | G61: PV of Terminal | I61: =NPV(D62,I54:N54) -> 78317.344 | K61: Shares Outstanding | N61: =D80 -> 1480
B62: Discount Rate | D62: =(D82*D69)+(D88*D75) -> 0.095622468 | G62: Enterprise Value | I62: =I60+I61 -> 93119.543 | K62: Equity Value | N62: =N60/N61 -> 59.313205
B65: COST OF EQUITY | G65: NET DEBT
B66: Risk-free rate (US 10y) | D66: 0.0462 | G66: Short-term debt | I66: ='Simplified Model'!I38 -> 4839
B67: Beta | D67: 1.13 | G67: Long-term debt | I67: ='Simplified Model'!I37 -> 7961
B68: Market risk premium | D68: 0.05 | G68: Cash and cash equivalent | I68: ='Simplified Model'!I20 -> 7464
B69: CAPM | D69: =D66*D67+D68 -> 0.102206 | G69: Net debt | I69: =(I66+I67)-I68 -> 5336
B72: AFTER-TAX COST OF DEBT | G72: EQUITY VALUE
B73: Interest Rate on Debt | D73: 0.035 | G73: Enterprise Value | I73: =I62 -> 93119.543
B74: Tax Rate | D74: =J23 -> 0.15 | G74: Less: Net Debt | I74: =-I69 -> -5336
B75: After-tax Cost of Debt | D75: =D73*(1-D74) -> 0.02975 | G75: Equity Value | I75: =SUM(I73:I74) -> 87783.543
B78: MARKET VALUE OF EQUITY AND DEBT | G78: AVERAGE MATURITY
B79: Share price (16/07/26) | D79: 42.77 | H79: 2026 | I79: Outstanding | J79: Maturity | K79: YTM
B80: Shares Outstanding | D80: 1480 | G80: November 1 2026 | I80: 999 | J80: 2026 | K80: =J80-$H$79 -> 0 | L80: =I80*K80 -> 0
B81: Market Value of Equity | D81: =D79*D80 -> 63299.6 | G81: March 27 2027 | I81: 999 | J81: 2027 | K81: =J81-$H$79 -> 1 | L81: =I81*K81 -> 999
B82: Weight | D82: =D81/(D81+D87) -> 0.90913752 | G82: March 27 2030 | I82: 1495 | J82: 2030 | K82: =J82-$H$79 -> 4 | L82: =I82*K82 -> 5980
B83: Interest Expense | D83: =-'Simplified Model'!I12 -> 107 | G83: March 27 2040 | I83: 993 | J83: 2040 | K83: =J83-$H$79 -> 14 | L83: =I83*K83 -> 13902
B84: Current Cost of Debt | D84: =D73 -> 0.035 | G84: May 1 2043 | I84: 502 | J84: 2043 | K84: =J84-$H$79 -> 17 | L84: =I84*K84 -> 8534
B85: Total Debt | D85: ='Simplified Model'!I37 -> 7961 | G85: November 1 2045 | I85: 997 | J85: 2045 | K85: =J85-$H$79 -> 19 | L85: =I85*K85 -> 18943
B86: Average Maturity (years) | D86: =L88/D85 -> 11.786208 | G86: November 1 2046 | I86: 494 | J86: 2046 | K86: =J86-$H$79 -> 20 | L86: =I86*K86 -> 9880
B87: Market Value of Debt | D87: =-PV(D84,D86,D83,D85) -> 6326.3899 | G87: March 27 2050 | I87: 1483 | J87: 2050 | K87: =J87-$H$79 -> 24 | L87: =I87*K87 -> 35592
B88: Weight | D88: =D87/(D81+D87) -> 0.090862477 | G88: Total | L88: =SUM(L80:L87) -> 93830

Sheet Source Notes
A1: Source Notes
A3: Model sheet | B3: Source | C3: Financial statement coverage | D3: URL
A4: Full Historical Statements | B4: NIKE FY2022 Form 10-K | C4: FY2021 balance sheet; FY2021–FY2022 income statement and cash flow data | D4: https://www.sec.gov/Archives/edgar/data/320187/000032018722000038/nke-20220531.htm
A5: Full Historical Statements | B5: NIKE FY2023 Form 10-K | C5: FY2021–FY2023 income statement and cash flow data; FY2022–FY2023 balance sheets | D5: https://www.sec.gov/Archives/edgar/data/320187/000032018723000039/nke-20230531.htm
A6: Full Historical Statements | B6: NIKE FY2025 Form 10-K | C6: FY2023–FY2025 income statement and cash flow data; FY2024–FY2025 balance sheets | D6: https://www.sec.gov/Archives/edgar/data/320187/000032018725000047/nke-20250531.htm
