Workbook

Sheet Full Historical Statements
A1: Crocs, Inc. — Full Historical Three-Statement Model
A2: USD $000s, except per share data; historical periods sourced from Crocs 10-Ks.
A4: Fiscal Year Ended Dec 31 | O4: Source / notes | BYS4: 4 | BYT4: 5 | BYU4: 6 | BYV4: 7 | BYW4: 8
A5: Key Assumptions | D5: 2021 | E5: 2022 | F5: 2023 | G5: 2024 | H5: 2025 | I5: 2026 | J5: 2027 | K5: 2028 | L5: 2029 | M5: 2030 | O5: 2021: Crocs FY2021 10-K; 2022-2023: Crocs FY2023 10-K; 2024-2025: Crocs FY2025 10-K.
A6: Revenue Growth (% Change) | E6: =E20/D20-1 -> 0.53668212 | F6: =F20/E20-1 -> 0.11458895 | G6: =G20/F20-1 -> 0.035272277 | H6: =H20/G20-1 -> -0.014982784 | I6: -0.006 | J6: 0.01 | K6: 0.02 | L6: 0.02 | M6: 0.03
A7: Cost of Goods Sold (% of Revenue) | D7: =D21/D20 -> 0.38609398 | E7: =E21/E20 -> 0.47671172 | F7: =F21/F20 -> 0.44224723 | G7: =G21/G20 -> 0.41243429 | H7: =H21/H20 -> 0.41666396 | I7: 0.42 | J7: 0.42 | K7: 0.43 | L7: 0.44 | M7: 0.45
A8: SGA (% of Revenue) | D8: =D23/D20 -> 0.31864394 | E8: =E23/E20 -> 0.28397476 | F8: =F23/F20 -> 0.29375014 | G8: =G23/G20 -> 0.33257657 | H8: =H23/H20 -> 0.36366082 | I8: 0.32 | J8: 0.33 | K8: 0.36 | L8: 0.36 | M8: 0.35 | O8: Key checks
A9: Depreciation & Amortization (% of PP&E) | D9: =D81/-D99 -> 0.57185779 | E9: =E81/-E99 -> 0.37651406 | F9: =F81/-F99 -> 0.46965622 | G9: =G81/-G99 -> 1.0071092 | H9: =H81/-H99 -> 1.5475396 | I9: 0.9 | J9: 0.9 | K9: 0.3 | L9: 0.3 | M9: 0.3 | O9: 2021 BS check | P9: =D76 -> 0
A10: Interest (% of Debt) | D10: 0.044864249 | E10: 0.10593586 | F10: 0.094207593 | G10: 0.090664773 | H10: 0.090272176 | I10: 0.02706513 | J10: 0.048305632 | K10: 0.057459948 | L10: 0.089442732 | M10: 0.021732428 | O10: 2022 BS check | P10: =E76 -> 0
A11: Tax Rate (% of Earnings Before Tax) | D11: =-D32/(D26+D27+D28) -> 0.090456473 | E11: =E32/E31 -> 0.24822131 | F11: =F32/F31 -> 0.095525134 | G11: =G32/-G31 -> 0.043363332 | H11: =H32/H31 -> 2.1126367 | I11: 0.25 | J11: 0.25 | K11: 0.25 | L11: 0.25 | M11: 0.25 | O11: 2023 BS check | P11: =F76 -> 0
A12: Accounts Receivable (Days) | D12: =D39/D20*D17 -> 28.814353 | E12: =E39/E20*E17 -> 30.349442 | F12: =F39/F20*F17 -> 28.164534 | G12: =G39/G20*G17 -> 22.92597 | H12: =H39/H20*H17 -> 25.129568 | I12: =AVERAGE(D12:H12) -> 27.076773 | J12: 27 | K12: 27 | L12: 27 | M12: 27 | O12: 2024 BS check | P12: =G76 -> 0
A13: Inventory (Days) | D13: =D40/D21*D17 -> 87.253861 | E13: =E40/E21*E17 -> 101.56123 | F13: =F40/F21*F17 -> 80.204156 | G13: =G40/G21*G17 -> 76.858297 | H13: =H40/H21*H17 -> 79.93074 | I13: =AVERAGE(D13:H13) -> 85.161656 | J13: 85 | K13: 85 | L13: 85 | M13: 85 | O13: 2025 BS check | P13: =H76 -> 0
A14: Accounts Payable (Days) | D14: =D55/D21*D17 -> 66.259729 | E14: =E55/E21*E17 -> 49.713528 | F14: =F55/F21*F17 -> 54.35996 | G14: =G55/G21*G17 -> 57.149786 | H14: =H55/H21*H17 -> 57.687878 | I14: =AVERAGE(D14:H14) -> 57.034176 | J14: 57 | K14: 57 | L14: 57 | M14: 57 | O14: 2021 cash tie | P14: =D116 -> 0
A15: Capital Expenditures ($000's) | E15: =(E45-D45)+E81 -> 112360 | F15: =(F45-E45)+F81 -> 111090 | G15: =(G45-F45)+G81 -> 75860 | H15: =(H45-G45)+H81 -> 73138 | I15: 20000 | J15: 20000 | K15: 100000 | L15: 120000 | M15: 100000 | O15: 2022 cash tie | P15: =E116 -> 0
A16: Equity Issued (Repaid) ($000's) | D16: =-(D108+D109) -> 1020119 | E16: =-(E108+E109) -> 11477 | F16: =-(F108+F109) -> 192105 | G16: =-(G108+G109) -> 560690 | H16: =-(H108+H109) -> 586565 | I16: 300000 | J16: 300000 | K16: 300000 | L16: 300000 | M16: 300000
A17: Days in Period | D17: 365 | E17: 365 | F17: 365 | G17: 365 | H17: 365 | I17: 365 | J17: 365 | K17: 365 | L17: 365 | M17: 365
A19: Income Statement | D19: 2021 | E19: 2022 | F19: 2023 | G19: 2024 | H19: 2025 | I19: 2026 | J19: 2027 | K19: 2028 | L19: 2029 | M19: 2030
A20: Revenues | D20: 2313416 | E20: 3554985 | F20: 3962347 | G20: 4102108 | H20: 4040647 | I20: =H20*(1+I6) -> 4016403.1 | J20: =I20*(1+J6) -> 4056567.1 | K20: =J20*(1+K6) -> 4137698.5 | L20: =K20*(1+L6) -> 4220452.5 | M20: =L20*(1+M6) -> 4347066
A21: Cost of sales | D21: 893196 | E21: 1694703 | F21: 1752337 | G21: 1691850 | H21: 1683592 | I21: =I20*I7 -> 1686889.3 | J21: =J20*J7 -> 1703758.2 | K21: =K20*K7 -> 1779210.4 | L21: =L20*L7 -> 1856999.1 | M21: =M20*M7 -> 1956179.7
A22: Gross profit | D22: =D20-D21 -> 1420220 | E22: =E20-E21 -> 1860282 | F22: =F20-F21 -> 2210010 | G22: =G20-G21 -> 2410258 | H22: =H20-H21 -> 2357055 | I22: =I20-I21 -> 2329513.8 | J22: =J20-J21 -> 2352808.9 | K22: =K20-K21 -> 2358488.1 | ... M22: =M20-M21 -> 2390886.3
A23: Selling, general and administrative expenses | D23: 737156 | E23: 1009526 | F23: 1163940 | G23: 1364265 | H23: 1469425 | I23: =I20*I8 -> 1285249 | J23: =J20*J8 -> 1338667.2 | K23: =K20*K8 -> 1489571.5 | L23: =L20*L8 -> 1519362.9 | M23: =M20*M8 -> 1521473.1
A24: Goodwill impairment | D24: 0 | E24: 0 | F24: 0 | G24: 0 | H24: 307000 | I24: 307000 | J24: 307000 | K24: 307000 | L24: 307000 | M24: 307000
A25: Asset impairments | D25: 0 | E25: 0 | F25: 9287 | G25: 24082 | H25: 431115 | I25: 290000 | J25: 102000 | K25: 60000 | L25: 15000 | M25: 7000
A26: Income from operations | D26: =D22-D23-D24-D25 -> 683064 | E26: =E22-E23-E24-E25 -> 850756 | F26: =F22-F23-F24-F25 -> 1036783 | G26: =G22-G23-G24-G25 -> 1021911 | H26: =H22-H23-H24-H25 -> 149515 | I26: =I22-I23-I24-I25 -> 447264.81 | J26: =J22-J23-J24-J25 -> 605141.79 | K26: =K22-K23-K24-K25 -> 501916.68 | ... M26: =M22-M23-M24-M25 -> 555413.21
A27: Foreign currency gains (losses), net | D27: -140 | E27: 3228 | F27: -1240 | G27: -6777 | H27: 9843 | I27: 9843 | J27: 9843 | K27: 9843 | L27: 9843 | M27: 9843
A28: Interest income | D28: 775 | E28: 1020 | F28: 2406 | G28: 3484 | H28: 1844 | I28: 1844 | J28: 1844 | K28: 1844 | L28: 1844 | M28: 1844
A29: Interest expense | D29: -21647 | E29: -136158 | F29: -161351 | G29: -109264 | H29: -88287 | I29: =-I144 -> -42453.443 | J29: =-J145 -> -16240 | K29: =-K146 -> -15225 | L29: =-L144 -> -49353.546 | M29: =-M144 -> -17941.553
A30: Other income (expense), net | D30: 1797 | E30: -338 | F30: -326 | G30: 1231 | H30: 63 | I30: =AVERAGE(D30:H30) -> 485.4 | J30: =AVERAGE(E30:I30) -> 223.08 | K30: =AVERAGE(F30:J30) -> 335.296 | L30: =AVERAGE(G30:K30) -> 467.5552 | M30: =AVERAGE(H30:L30) -> 314.86624
A31: Income before income taxes | D31: =D26+D27+D28+D29+D30 -> 663849 | E31: =E26+E27+E28+E29+E30 -> 718508 | F31: =F26+F27+F28+F29+F30 -> 876272 | G31: =G26+G27+G28+G29+G30 -> 910585 | H31: =H26+H27+H28+H29+H30 -> 72978 | I31: =I26+I27+I28+I29+I30 -> 416983.77 | J31: =J26+J27+J28+J29+J30 -> 600811.87 | K31: =K26+K27+K28+K29+K30 -> 498713.98 | ... M31: =M26+M27+M28+M29+M30 -> 549473.52
A32: Income tax expense (benefit) | D32: -61845 | E32: 178349 | F32: 83706 | G32: -39486 | H32: 154176 | I32: =I31*I11 -> 104245.94 | J32: =J31*J11 -> 150202.97 | K32: =K31*K11 -> 124678.49 | L32: =L31*L11 -> 121222.88 | M32: =M31*M11 -> 137368.38
A33: Net income (loss) | D33: =D31-D32 -> 725694 | E33: =E31-E32 -> 540159 | F33: =F31-F32 -> 792566 | G33: =G31-G32 -> 950071 | H33: =H31-H32 -> -81198 | I33: =I31-I32 -> 312737.83 | J33: =J31-J32 -> 450608.9 | K33: =K31-K32 -> 374035.48 | ... M33: =M31-M32 -> 412105.14
A36: Balance Sheet — Assets
A37: Cash and cash equivalents | D37: 213197 | E37: 191629 | F37: 149288 | G37: 180485 | H37: 130354 | I37: =I115 -> 361852.26 | J37: =J115 -> 389596.82 | K37: =K115 -> 231889.89 | L37: =L115 -> 87162.314 | M37: =M115 -> 55638.584
A38: Restricted cash — current | D38: 65 | E38: 2 | F38: 2 | G38: 0 | H38: 0 | I38: 0 | J38: 0 | K38: 0 | L38: 0 | M38: 0
A39: Accounts receivable, net | D39: 182629 | E39: 295594 | F39: 305747 | G39: 257657 | H39: 278191 | I39: =I20*I12/I17 -> 297948.59 | J39: =J20*J12/J17 -> 300074.83 | K39: =K20*K12/K17 -> 306076.33 | L39: =L20*L12/L17 -> 312197.85 | M39: =M20*M12/M17 -> 321563.79
A40: Inventories | D40: 213520 | E40: 471551 | F40: 385054 | G40: 356254 | H40: 368687 | I40: =I21*I13/I17 -> 393584.35 | J40: =J21*J13/J17 -> 396765.61 | K40: =K21*K13/K17 -> 414336.66 | L40: =L21*L13/L17 -> 432451.84 | M40: =M21*M13/M17 -> 455548.7
A41: Income taxes receivable | D41: 22301 | E41: 14752 | F41: 4413 | G41: 4046 | H41: 32782 | I41: =AVERAGE(F41:H41) -> 13747 | J41: =AVERAGE(G41:I41) -> 16858.333 | K41: =AVERAGE(H41:J41) -> 21129.111 | L41: =AVERAGE(I41:K41) -> 17244.815 | M41: =AVERAGE(J41:L41) -> 18410.753
A42: Other receivables | D42: 12252 | E42: 18842 | F42: 21071 | G42: 22204 | H42: 22082 | I42: =H42*(1+(H42/G42-1)) -> 21960.67 | J42: =I42*(1+(I42/H42-1)) -> 21840.007 | K42: =J42*(1+(J42/I42-1)) -> 21720.007 | L42: =K42*(1+(K42/J42-1)) -> 21600.667 | M42: =L42*(1+(L42/K42-1)) -> 21481.982
A43: Prepaid expenses and other assets | D43: 22605 | E43: 33605 | F43: 45129 | G43: 51623 | H43: 53787 | I43: =H43*(1+(H43/G43-1)) -> 56041.713 | J43: =I43*(1+(I43/H43-1)) -> 58390.943 | K43: =J43*(1+(J43/I43-1)) -> 60838.65 | L43: =K43*(1+(K43/J43-1)) -> 63388.964 | M43: =L43*(1+(L43/K43-1)) -> 66046.185
A44: Total current assets | D44: =SUM(D37:D43) -> 666569 | E44: =SUM(E37:E43) -> 1025975 | F44: =SUM(F37:F43) -> 910704 | G44: =SUM(G37:G43) -> 872269 | H44: =SUM(H37:H43) -> 885883 | I44: =SUM(I37:I43) -> 1145134.6 | J44: =SUM(J37:J43) -> 1183526.5 | K44: =SUM(K37:K43) -> 1055990.6 | ... M44: =SUM(M37:M43) -> 938689.99
A45: Property and equipment, net | D45: 108398 | E45: 181529 | F45: 238315 | G45: 244335 | H45: 238191 | I45: =AVERAGE(F45:H45) -> 240280.33 | J45: =AVERAGE(G45:I45) -> 240935.44 | K45: 320000 | L45: 350000 | M45: 360000
A46: Intangible assets, net | D46: 28802 | E46: 1800167 | F46: 1792562 | G46: 1777080 | H46: 1324680 | I46: =AVERAGE(F46:H46) -> 1631440.7 | J46: =AVERAGE(G46:I46) -> 1577733.6 | K46: =AVERAGE(H46:J46) -> 1511284.7 | L46: =AVERAGE(I46:K46) -> 1573486.3 | M46: =AVERAGE(J46:L46) -> 1554168.2
A47: Goodwill | D47: 1600 | E47: 714814 | F47: 711588 | G47: 711491 | H47: 404689 | I47: =AVERAGE(F47:H47) -> 609256 | J47: =AVERAGE(G47:I47) -> 575145.33 | K47: =AVERAGE(H47:J47) -> 529696.78 | L47: =AVERAGE(I47:K47) -> 571366.04 | M47: =AVERAGE(J47:L47) -> 558736.05
A48: Deferred tax assets, net | D48: 567201 | E48: 528278 | F48: 667972 | G48: 872350 | H48: 935054 | I48: =AVERAGE(F48:H48) -> 825125.33 | J48: =AVERAGE(G48:I48) -> 877509.78 | K48: =AVERAGE(H48:J48) -> 879229.7 | L48: =AVERAGE(I48:K48) -> 860621.6 | M48: =AVERAGE(J48:L48) -> 872453.7
A49: Restricted cash | D49: 3663 | E49: 3254 | F49: 3807 | G49: 3193 | H49: 3557 | I49: =AVERAGE(F49:H49) -> 3519 | J49: =AVERAGE(G49:I49) -> 3423 | K49: =AVERAGE(H49:J49) -> 3499.6667 | L49: =AVERAGE(I49:K49) -> 3480.5556 | M49: =AVERAGE(J49:L49) -> 3467.7407
A50: Right-of-use assets | D50: 160768 | E50: 239905 | F50: 287440 | G50: 307228 | H50: 338669 | I50: =AVERAGE(F50:H50) -> 311112.33 | J50: =AVERAGE(G50:I50) -> 319003.11 | K50: 500000 | L50: 530000 | M50: 550000
A51: Other assets | D51: 8067 | E51: 7875 | F51: 31446 | G51: 24207 | H51: 44027 | I51: =AVERAGE(F51:H51) -> 33226.667 | J51: =AVERAGE(G51:I51) -> 33820.222 | K51: =AVERAGE(H51:J51) -> 37024.63 | L51: =AVERAGE(I51:K51) -> 34690.506 | M51: =AVERAGE(J51:L51) -> 35178.453
A52: Total assets | D52: =D44+SUM(D45:D51) -> 1545068 | E52: =E44+SUM(E45:E51) -> 4501797 | F52: =F44+SUM(F45:F51) -> 4643834 | G52: =G44+SUM(G45:G51) -> 4812153 | H52: =H44+SUM(H45:H51) -> 4174750 | I52: =I44+SUM(I45:I51) -> 4799094.9 | J52: =J44+SUM(J45:J51) -> 4811097 | K52: =K44+SUM(K45:K51) -> 4836726.2 | ... M52: =M44+SUM(M45:M51) -> 4872694.1
A54: Balance Sheet — Liabilities
A55: Accounts payable | D55: 162145 | E55: 230821 | F55: 260978 | G55: 264901 | H55: 266090 | I55: =I21*I14/I17 -> 263589.98 | J55: =J21*J14/J17 -> 266066.35 | K55: =K21*K14/K17 -> 277849.29 | L55: =L21*L14/L17 -> 289997.12 | M55: =M21*M14/M17 -> 305485.6
A56: Accrued expenses and other liabilities | D56: 166887 | E56: 239424 | F56: 285771 | G56: 298068 | H56: 300959 | I56: =H56*(1+(H56/G56-1)) -> 303878.04 | J56: =I56*(1+(I56/H56-1)) -> 306825.39 | K56: =J56*(1+(J56/I56-1)) -> 309801.33 | L56: =K56*(1+(K56/J56-1)) -> 312806.13 | M56: =L56*(1+(L56/K56-1)) -> 315840.08
A57: Income taxes payable | D57: 16279 | E57: 89211 | F57: 65952 | G57: 108688 | H57: 47308 | I57: =AVERAGE(F57:H57) -> 73982.667 | J57: =AVERAGE(G57:I57) -> 76659.556 | K57: =AVERAGE(H57:J57) -> 65983.407 | L57: =AVERAGE(I57:K57) -> 72208.543 | M57: =AVERAGE(J57:L57) -> 71617.169
A58: Current borrowings | D58: 0 | E58: 24362 | F58: 23328 | G58: 0 | H58: 0 | I58: 0 | J58: 0 | K58: 0 | L58: 0 | M58: 0
A59: Current operating lease liabilities | D59: 42932 | E59: 57456 | F59: 62267 | G59: 68551 | H59: 85772 | I59: =AVERAGE(F59:H59) -> 72196.667 | J59: =AVERAGE(G59:I59) -> 75506.556 | K59: =AVERAGE(H59:J59) -> 77825.074 | L59: =AVERAGE(I59:K59) -> 75176.099 | M59: =AVERAGE(J59:L59) -> 76169.243
A60: Total current liabilities | D60: =SUM(D55:D59) -> 388243 | E60: =SUM(E55:E59) -> 641274 | F60: =SUM(F55:F59) -> 698296 | G60: =SUM(G55:G59) -> 740208 | H60: =SUM(H55:H59) -> 700129 | I60: =SUM(I55:I59) -> 713647.35 | J60: =SUM(J55:J59) -> 725057.85 | K60: =SUM(K55:K59) -> 731459.1 | ... M60: =SUM(M55:M59) -> 769112.09
A61: Deferred tax liabilities, net | D61: 0 | E61: 302030 | F61: 12912 | G61: 4086 | H61: 882 | I61: 500 | J61: 300 | K61: 0 | L61: 0 | M61: 0
A62: Long-term income taxes payable | D62: 219744 | E62: 224837 | F62: 565171 | G62: 595434 | H62: 649057 | I62: =H62*(1+(H62/G62-1)) -> 707509.13 | J62: =I62*(1+(I62/H62-1)) -> 771225.28 | K62: =J62*(1+(J62/I62-1)) -> 840679.51 | L62: =K62*(1+(K62/J62-1)) -> 916388.59 | M62: =L62*(1+(L62/K62-1)) -> 998915.79
A63: Long-term borrowings | D63: 771390 | E63: 2298027 | F63: 1640996 | G63: 1349339 | H63: 1230885 | I63: =I143 -> 950566 | J63: =J143 -> 750566 | K63: =K143 -> 900566 | L63: =L143 -> 550566 | M63: =M143 -> 400566
A64: Long-term operating lease liabilities | D64: 149237 | E64: 215119 | F64: 269769 | G64: 283406 | H64: 297192 | I64: =H64*(1+(H64/G64-1)) -> 311648.61 | J64: =I64*(1+(I64/H64-1)) -> 326808.44 | K64: 450000 | L64: 470000 | M64: 500000
A65: Other liabilities | D65: 2372 | E65: 2579 | F65: 2767 | G65: 3948 | H65: 3322 | I65: =AVERAGE(F65:H65) -> 3345.6667 | J65: =AVERAGE(G65:I65) -> 3538.5556 | K65: =AVERAGE(H65:J65) -> 3402.0741 | L65: =AVERAGE(I65:K65) -> 3428.7654 | M65: =AVERAGE(J65:L65) -> 3456.465
A66: Total liabilities | D66: =D60+SUM(D61:D65) -> 1530986 | E66: =E60+SUM(E61:E65) -> 3683866 | F66: =F60+SUM(F61:F65) -> 3189911 | G66: =G60+SUM(G61:G65) -> 2976421 | H66: =H60+SUM(H61:H65) -> 2881467 | I66: =I60+SUM(I61:I65) -> 2687216.8 | J66: =J60+SUM(J61:J65) -> 2577496.1 | K66: =K60+SUM(K61:K65) -> 2926106.7 | ... M66: =M60+SUM(M61:M65) -> 2672050.4
A68: Balance Sheet — Stockholders’ Equity
A69: Common stock | D69: 106 | E69: 110 | F69: 110 | G69: 110 | H69: 111 | I69: 110 | J69: 110 | K69: 110 | L69: 110 | M69: 110
A70: Treasury stock, at cost | D70: -1684262 | E70: -1695501 | F70: -1888869 | G70: -2453473 | H70: -3040416 | I70: =H70-I108 -> -2890416 | J70: =I70-J108 -> -2740416 | K70: =J70-K108 -> -2590416 | L70: =K70-L108 -> -2440416 | M70: =L70-M108 -> -2290416
A71: Additional paid-in capital | D71: 496036 | E71: 797614 | F71: 826685 | G71: 859904 | H71: 896605 | I71: =H71+I86 -> 929547 | J71: =I71+J86 -> 963779 | K71: =J71+K86 -> 998404 | L71: =K71+L86 -> 1032337 | M71: =L71+M86 -> 1066600.3
A72: Retained earnings | D72: 1279040 | E72: 1819199 | F72: 2611765 | G72: 3561836 | H72: 3480638 | I72: =H72+I33 -> 3793375.8 | J72: =I72+J33 -> 4243984.7 | K72: =J72+K33 -> 4618020.2 | L72: =K72+L33 -> 4981688.8 | M72: =L72+M33 -> 5393794
A73: Accumulated other comprehensive loss | D73: -76838 | E73: -103491 | F73: -95768 | G73: -132645 | H73: -43655 | I73: =AVERAGE(F73:H73) -> -90689.333 | J73: =AVERAGE(G73:I73) -> -88996.444 | K73: =AVERAGE(H73:J73) -> -74446.926 | L73: =AVERAGE(I73:K73) -> -84710.901 | M73: =AVERAGE(J73:L73) -> -82718.091
A74: Total stockholders' equity | D74: =SUM(D69:D73) -> 14082 | E74: =SUM(E69:E73) -> 817931 | F74: =SUM(F69:F73) -> 1453923 | G74: =SUM(G69:G73) -> 1835732 | H74: =SUM(H69:H73) -> 1293283 | I74: =SUM(I69:I73) -> 1741927.5 | J74: =SUM(J69:J73) -> 2378461.3 | K74: =SUM(K69:K73) -> 2951671.3 | ... M74: =SUM(M69:M73) -> 4087370.2
A75: Total liabilities and stockholders' equity | D75: =D66+D74 -> 1545068 | E75: =E66+E74 -> 4501797 | F75: =F66+F74 -> 4643834 | G75: =G66+G74 -> 4812153 | H75: =H66+H74 -> 4174750 | I75: =I66+I74 -> 4429144.2 | J75: =J66+J74 -> 4955957.4 | K75: =K66+K74 -> 5877778 | ... M75: =M66+M74 -> 6759420.6
A76: Balance sheet check | D76: =D75-D52 -> 0 | E76: =E75-E52 -> 0 | F76: =F75-F52 -> 0 | G76: =G75-G52 -> 0 | H76: =H75-H52 -> 0 | I76: =I75-I52 -> -369950.67 | J76: =J75-J52 -> 144860.42 | K76: =K75-K52 -> 1041051.8 | ... M76: =M75-M52 -> 1886726.4
A79: Cash Flow Statement
A80: Net income (loss) | D80: =D33 -> 725694 | E80: =E33 -> 540159 | F80: =F33 -> 792566 | G80: =G33 -> 950071 | H80: =H33 -> -81198 | I80: =I33 -> 312737.83 | J80: =J33 -> 450608.9 | K80: =K33 -> 374035.48 | ... M80: =M33 -> 412105.14
A81: Depreciation and amortization | D81: 31976 | E81: 39229 | F81: 54304 | G81: 69840 | H81: 79282 | I81: =I130 -> 174203.1 | J81: =J130 -> 35420.31 | K81: =K130 -> 7180.677 | L81: =L130 -> 11026.474 | M81: =M130 -> 43718.532
A82: Loss on disposal of assets | D82: 310 | E82: 9063 | F82: 419 | G82: 0 | H82: 0 | I82: 0 | J82: 0 | K82: 0 | L82: 0 | M82: 0
A83: Operating lease cost | D83: 58283 | E83: 66012 | F83: 79543 | G83: 85130 | H83: 104313 | I83: =H83*(1+(H83/G83-1)) -> 127818.65 | J83: =I83*(1+(I83/H83-1)) -> 156621.02 | K83: =J83*(1+(J83/I83-1)) -> 191913.64 | L83: =K83*(1+(K83/J83-1)) -> 235159.02 | M83: =L83*(1+(L83/K83-1)) -> 288149.22
A84: Inventory donations | D84: 1264 | E84: 2770 | F84: 2078 | G84: 812 | H84: 871 | I84: 1000 | J84: 1000 | K84: 1000 | L84: 1000 | M84: 1000
A85: Provision for (recovery of) doubtful accounts, net | D85: -2629 | E85: 1101 | F85: 3568 | G85: 1352 | H85: -190 | I85: 0 | J85: 0 | K85: 0 | L85: 0 | M85: 0
A86: Share-based compensation | D86: 38122 | E86: 31303 | F86: 29072 | G86: 33053 | H86: 36701 | I86: =AVERAGE(F86:H86) -> 32942 | J86: =AVERAGE(G86:I86) -> 34232 | K86: =AVERAGE(H86:J86) -> 34625 | L86: =AVERAGE(I86:K86) -> 33933 | M86: =AVERAGE(J86:L86) -> 34263.333
A87: Asset impairments | D87: 0 | E87: 0 | F87: 9287 | G87: 24081 | H87: 738115 | I87: 0 | J87: 0 | K87: 0 | L87: 0 | M87: 0
A88: Deferred taxes | D88: -241283 | E88: -4760 | F88: -410319 | G88: -254454 | H88: 47093
A89: Other non-cash items | D89: -46 | E89: 9947 | F89: 3401 | G89: 14171 | H89: 5931 | I89: 0 | J89: 0 | K89: 0 | L89: 0 | M89: 0
A90: Accounts receivable change | D90: -35063 | E90: -56766 | F90: -13317 | G90: 42587 | H90: -6169 | I90: -10000 | J90: -10000 | K90: -10000 | L90: -10000 | M90: -10000
A91: Inventories change | D91: -43063 | E91: -91614 | F91: 86350 | G91: 22055 | H91: -13842 | I91: =AVERAGE(F91:H91) -> 31521 | J91: =AVERAGE(G91:I91) -> 13244.667 | K91: =AVERAGE(H91:J91) -> 10307.889 | L91: =AVERAGE(I91:K91) -> 18357.852 | M91: =AVERAGE(J91:L91) -> 13970.136
A92: Prepaid expenses and other assets change | D92: -6212 | E92: -14435 | F92: -31839 | G92: -13892 | H92: -22317 | I92: =AVERAGE(F92:H92) -> -22682.667 | J92: =AVERAGE(G92:I92) -> -19630.556 | K92: =AVERAGE(H92:J92) -> -21543.407 | L92: =AVERAGE(I92:K92) -> -21285.543 | M92: =AVERAGE(J92:L92) -> -20819.835
A93: Accounts payable change | D93: 34868 | E93: 41701 | F93: 37197 | G93: 3951 | H93: 709 | I93: 500 | J93: 500 | K93: 2500 | L93: 15700 | M93: 30000
A94: Accrued expenses and other liabilities change | D94: 38448 | E94: 38629 | F94: 46695 | G94: 9971 | H94: 524 | I94: 100 | J94: 100 | K94: 100 | L94: 100 | M94: 100
A95: Right-of-use assets and operating lease liabilities change | D95: -52752 | E95: -63355 | F95: -75107 | G95: -88772 | H95: -105293 | I95: =H95*(1+(H95/G95-1)) -> -124888.66 | J95: =I95*(1+(I95/H95-1)) -> -148131.18 | K95: =J95*(1+(J95/I95-1)) -> -175699.28 | L95: =K95*(1+(K95/J95-1)) -> -208397.97 | M95: =L95*(1+(L95/K95-1)) -> -247182.08
A96: Income taxes change | D96: 19248 | E96: 54158 | F96: 316546 | G96: 92530 | H96: -74099 | I96: =AVERAGE(F96:H96) -> 111659 | J96: =AVERAGE(G96:I96) -> 43363.333 | K96: =AVERAGE(H96:J96) -> 26974.444 | L96: =AVERAGE(I96:K96) -> 60665.593 | M96: =AVERAGE(J96:L96) -> 43667.79
A97: Less; Changes in Working Capital | D97: =D125 -> 234004 | E97: =E125 -> 302320 | F97: =F125 -> -106501 | G97: =G125 -> -80813 | H97: =H125 -> 31778 | I97: =I125 -> 47154.964 | J97: =J125 -> 2831.1253 | K97: =K125 -> 11789.607 | ... M97: =M125 -> 16974.313
A98: Cash provided by operating activities | D98: =SUM(D80:D96) -> 567165 | E98: =SUM(E80:E96) -> 603142 | F98: =SUM(F80:F96) -> 930444 | G98: =SUM(G80:G96) -> 992486 | H98: =SUM(H80:H96) -> 710431 | I98: =SUM(I80:I96) -> 634910.26 | J98: =SUM(J80:J96) -> 557328.49 | K98: =SUM(K80:K96) -> 441394.45 | ... M98: =SUM(M80:M96) -> 588972.24
A99: Purchases of property, equipment, and software | D99: -55916 | E99: -104190 | F99: -115625 | G99: -69347 | H99: -51231 | I99: =I129 -> 20000 | J99: =J129 -> 20000 | K99: =K129 -> 20000 | L99: =L129 -> 120000 | M99: =M129 -> 100000
A100: Acquisition of HEYDUDE, net of cash acquired | D100: 0 | E100: -2046881 | F100: 0 | G100: 0 | H100: 0 | I100: 0 | J100: - | K100: -400000 | L100: -200000 | M100: -500000
A101: Proceeds from disposal of property and equipment | D101: 6 | E101: 0 | F101: 0 | G101: 0 | H101: 0 | I101: 0 | J101: 0 | K101: 0 | L101: 0 | M101: 0
A102: Other investing activity | D102: -15 | E102: -20 | F102: -46 | G102: 0 | H102: 0 | I102: 0 | J102: 0 | K102: 0 | L102: 0 | M102: 0
A103: Cash used in investing activities | D103: =SUM(D99:D102) -> -55925 | E103: =SUM(E99:E102) -> -2151091 | F103: =SUM(F99:F102) -> -115671 | G103: =SUM(G99:G102) -> -69347 | H103: =SUM(H99:H102) -> -51231 | I103: =SUM(I99:I102) -> 20000 | J103: =SUM(J99:J102) -> 20000 | K103: =SUM(K99:K102) -> -380000 | ... M103: =SUM(M99:M102) -> -400000
A104: Proceeds from notes issuance | D104: 700000 | E104: 0 | F104: 0 | G104: 0 | H104: 0 | I104: 0 | J104: 0 | K104: 0 | L104: 0 | M104: 0
A105: Proceeds from bank borrowings | D105: 390000 | E105: 2169898 | F105: 257905 | G105: 102156 | H105: 819000 | I105: =I136+I137 -> 0 | J105: =J135+J136+J137 -> 0 | K105: =K135+K136+K137 -> 350000 | L105: =L135+L136+L137 -> 0 | M105: =M135+M136+M137 -> 0
A106: Repayments of bank borrowings | D106: -485000 | E106: -575285 | F106: -923703 | G106: -425405 | H106: -947000 | I106: =-I$141-I$142 -> -312000 | J106: =-J141-J142 -> -200000 | K106: =-K141-K142 -> -200000 | L106: =-L141-L142-L138 -> -350000 | M106: =-M141-M142 -> -150000
A107: Deferred debt issuance costs | D107: -14755 | E107: -53596 | F107: -1736 | G107: 0 | H107: 0 | I107: 0 | J107: 0 | K107: 0 | L107: 0 | M107: 0
A108: Repurchases of common stock, incl. excise taxes paid | D108: -1000000 | E108: 0 | F108: -175019 | G108: -552451 | H108: -582320 | I108: -150000 | J108: -150000 | K108: -150000 | L108: -150000 | M108: -150000
...

Sheet Source Notes
A1: Source Notes
A2: Model sheet | B2: Source | C2: PDF section/page | D2: Purpose
A3: Full Historical Statements | B3: Crocs FY2021 10-K | C3: Consolidated Statements of Operations, Balance Sheets, Cash Flows / F-4, F-6, F-8 | D3: 2021 historical income statement, balance sheet and cash flow statement
A4: Full Historical Statements | B4: Crocs FY2023 10-K | C4: Consolidated Statements of Income, Balance Sheets, Cash Flows / F-4, F-6, F-8 | D4: 2022–2023 historical income statement, balance sheet and cash flow statement
A5: Full Historical Statements | B5: Crocs FY2025 10-K | C5: Consolidated Statements of Operations, Balance Sheets, Cash Flows / F-4, F-6, F-8 | D5: 2024–2025 historical income statement, balance sheet and cash flow statement

Sheet Simplified Model
A1: Crocs, Inc. — Simplified Three-Statement Model | O1: Model note
A2: USD $000s; historical and forecast data linked to Full Historical Statements. Forecast cash is used as a balancing line. | O2: Forecast cash is a balancing line
O3: This makes the balance sheet balance mechanically.
A4: Fiscal Year Ended Dec 31 | D4: 2021 | E4: 2022 | F4: 2023 | G4: 2024 | H4: 2025 | I4: 2026 | J4: 2027 | K4: 2028 | L4: 2029 | M4: 2030 | O4: Replace the balancing line with cash from the fully integrated cash flow statement once the schedules are final.
A6: Income Statement | O6: Check | P6: Target
A7: Revenue | D7: ='Full Historical Statements'!D20 -> 2313416 | E7: ='Full Historical Statements'!E20 -> 3554985 | F7: ='Full Historical Statements'!F20 -> 3962347 | G7: ='Full Historical Statements'!G20 -> 4102108 | H7: ='Full Historical Statements'!H20 -> 4040647 | I7: ='Full Historical Statements'!I20 -> 4016403.1 | J7: ='Full Historical Statements'!J20 -> 4056567.1 | K7: ='Full Historical Statements'!K20 -> 4137698.5 | ... M7: ='Full Historical Statements'!M20 -> 4347066 | O7: Balance sheet check | P7: 0
A8: Cost of sales | D8: ='Full Historical Statements'!D21 -> 893196 | E8: ='Full Historical Statements'!E21 -> 1694703 | F8: ='Full Historical Statements'!F21 -> 1752337 | G8: ='Full Historical Statements'!G21 -> 1691850 | H8: ='Full Historical Statements'!H21 -> 1683592 | I8: ='Full Historical Statements'!I21 -> 1686889.3 | J8: ='Full Historical Statements'!J21 -> 1703758.2 | K8: ='Full Historical Statements'!K21 -> 1779210.4 | ... M8: ='Full Historical Statements'!M21 -> 1956179.7 | O8: Cash flow reconciliation | P8: 0
A9: Gross profit | D9: ='Full Historical Statements'!D22 -> 1420220 | E9: ='Full Historical Statements'!E22 -> 1860282 | F9: ='Full Historical Statements'!F22 -> 2210010 | G9: ='Full Historical Statements'!G22 -> 2410258 | H9: ='Full Historical Statements'!H22 -> 2357055 | I9: ='Full Historical Statements'!I22 -> 2329513.8 | J9: ='Full Historical Statements'!J22 -> 2352808.9 | K9: ='Full Historical Statements'!K22 -> 2358488.1 | ... M9: ='Full Historical Statements'!M22 -> 2390886.3
A10: Selling, general and administrative expenses | D10: ='Full Historical Statements'!D23 -> 737156 | E10: ='Full Historical Statements'!E23 -> 1009526 | F10: ='Full Historical Statements'!F23 -> 1163940 | G10: ='Full Historical Statements'!G23 -> 1364265 | H10: ='Full Historical Statements'!H23 -> 1469425 | I10: ='Full Historical Statements'!I23 -> 1285249 | J10: ='Full Historical Statements'!J23 -> 1338667.2 | K10: ='Full Historical Statements'!K23 -> 1489571.5 | ... M10: ='Full Historical Statements'!M23 -> 1521473.1
A11: Asset impairments | D11: =SUM('Full Historical Statements'!D24:D25) -> 0 | E11: =SUM('Full Historical Statements'!E24:E25) -> 0 | F11: =SUM('Full Historical Statements'!F24:F25) -> 9287 | G11: =SUM('Full Historical Statements'!G24:G25) -> 24082 | H11: =SUM('Full Historical Statements'!H24:H25) -> 738115 | I11: =SUM('Full Historical Statements'!I24:I25) -> 597000 | J11: =SUM('Full Historical Statements'!J24:J25) -> 409000 | K11: =SUM('Full Historical Statements'!K24:K25) -> 367000 | ... M11: =SUM('Full Historical Statements'!M24:M25) -> 314000
A12: Income from operations | D12: ='Full Historical Statements'!D26 -> 683064 | E12: ='Full Historical Statements'!E26 -> 850756 | F12: ='Full Historical Statements'!F26 -> 1036783 | G12: ='Full Historical Statements'!G26 -> 1021911 | H12: ='Full Historical Statements'!H26 -> 149515 | I12: ='Full Historical Statements'!I26 -> 447264.81 | J12: ='Full Historical Statements'!J26 -> 605141.79 | K12: ='Full Historical Statements'!K26 -> 501916.68 | ... M12: ='Full Historical Statements'!M26 -> 555413.21
A13: Foreign currency gains (losses), net | D13: ='Full Historical Statements'!D27 -> -140 | E13: ='Full Historical Statements'!E27 -> 3228 | F13: ='Full Historical Statements'!F27 -> -1240 | G13: ='Full Historical Statements'!G27 -> -6777 | H13: ='Full Historical Statements'!H27 -> 9843 | I13: ='Full Historical Statements'!I27 -> 9843 | J13: ='Full Historical Statements'!J27 -> 9843 | K13: ='Full Historical Statements'!K27 -> 9843 | ... M13: ='Full Historical Statements'!M27 -> 9843
A14: Interest income | D14: ='Full Historical Statements'!D28 -> 775 | E14: ='Full Historical Statements'!E28 -> 1020 | F14: ='Full Historical Statements'!F28 -> 2406 | G14: ='Full Historical Statements'!G28 -> 3484 | H14: ='Full Historical Statements'!H28 -> 1844 | I14: ='Full Historical Statements'!I28 -> 1844 | J14: ='Full Historical Statements'!J28 -> 1844 | K14: ='Full Historical Statements'!K28 -> 1844 | ... M14: ='Full Historical Statements'!M28 -> 1844
A15: Interest expense | D15: ='Full Historical Statements'!D29 -> -21647 | E15: ='Full Historical Statements'!E29 -> -136158 | F15: ='Full Historical Statements'!F29 -> -161351 | G15: ='Full Historical Statements'!G29 -> -109264 | H15: ='Full Historical Statements'!H29 -> -88287 | I15: ='Full Historical Statements'!I29 -> -42453.443 | J15: ='Full Historical Statements'!J29 -> -16240 | K15: ='Full Historical Statements'!K29 -> -15225 | ... M15: ='Full Historical Statements'!M29 -> -17941.553
A16: Other income (expense), net | D16: ='Full Historical Statements'!D30 -> 1797 | E16: ='Full Historical Statements'!E30 -> -338 | F16: ='Full Historical Statements'!F30 -> -326 | G16: ='Full Historical Statements'!G30 -> 1231 | H16: ='Full Historical Statements'!H30 -> 63 | I16: ='Full Historical Statements'!I30 -> 485.4 | J16: ='Full Historical Statements'!J30 -> 223.08 | K16: ='Full Historical Statements'!K30 -> 335.296 | ... M16: ='Full Historical Statements'!M30 -> 314.86624
A17: Income before income taxes | D17: ='Full Historical Statements'!D31 -> 663849 | E17: ='Full Historical Statements'!E31 -> 718508 | F17: ='Full Historical Statements'!F31 -> 876272 | G17: ='Full Historical Statements'!G31 -> 910585 | H17: ='Full Historical Statements'!H31 -> 72978 | I17: ='Full Historical Statements'!I31 -> 416983.77 | J17: ='Full Historical Statements'!J31 -> 600811.87 | K17: ='Full Historical Statements'!K31 -> 498713.98 | ... M17: ='Full Historical Statements'!M31 -> 549473.52
A18: Income tax expense (benefit) | D18: ='Full Historical Statements'!D32 -> -61845 | E18: ='Full Historical Statements'!E32 -> 178349 | F18: ='Full Historical Statements'!F32 -> 83706 | G18: ='Full Historical Statements'!G32 -> -39486 | H18: ='Full Historical Statements'!H32 -> 154176 | I18: ='Full Historical Statements'!I32 -> 104245.94 | J18: =200157*28% -> 56043.96 | K18: ='Full Historical Statements'!K32 -> 124678.49 | L18: =341758*28% -> 95692.24 | M18: =446069*28% -> 124899.32
A19: Net income (loss) | D19: ='Full Historical Statements'!D33 -> 725694 | E19: ='Full Historical Statements'!E33 -> 540159 | F19: ='Full Historical Statements'!F33 -> 792566 | G19: ='Full Historical Statements'!G33 -> 950071 | H19: ='Full Historical Statements'!H33 -> -81198 | I19: ='Full Historical Statements'!I33 -> 312737.83 | J19: ='Full Historical Statements'!J33 -> 450608.9 | K19: ='Full Historical Statements'!K33 -> 374035.48 | ... M19: ='Full Historical Statements'!M33 -> 412105.14
A22: Balance Sheet — Assets
A23: Cash and cash equivalents | D23: ='Full Historical Statements'!D37 -> 213197 | E23: ='Full Historical Statements'!E37 -> 191629 | F23: ='Full Historical Statements'!F37 -> 149288 | G23: ='Full Historical Statements'!G37 -> 180485 | H23: ='Full Historical Statements'!H37 -> 130354 | I23: =I51-SUM(I24:I26,I28:I31) -> -8098.416 | J23: =J51-SUM(J24:J26,J28:J31) -> 534457.24 | K23: =K51-SUM(K24:K26,K28:K31) -> 1272941.7 | L23: =L51-SUM(L24:L26,L28:L31) -> 1409051 | M23: =M51-SUM(M24:M26,M28:M31) -> 1942365
A24: Accounts receivable, net | D24: ='Full Historical Statements'!D39 -> 182629 | E24: ='Full Historical Statements'!E39 -> 295594 | F24: ='Full Historical Statements'!F39 -> 305747 | G24: ='Full Historical Statements'!G39 -> 257657 | H24: ='Full Historical Statements'!H39 -> 278191 | I24: ='Full Historical Statements'!I39 -> 297948.59 | J24: ='Full Historical Statements'!J39 -> 300074.83 | K24: ='Full Historical Statements'!K39 -> 306076.33 | ... M24: ='Full Historical Statements'!M39 -> 321563.79
A25: Inventories | D25: ='Full Historical Statements'!D40 -> 213520 | E25: ='Full Historical Statements'!E40 -> 471551 | F25: ='Full Historical Statements'!F40 -> 385054 | G25: ='Full Historical Statements'!G40 -> 356254 | H25: ='Full Historical Statements'!H40 -> 368687 | I25: ='Full Historical Statements'!I40 -> 393584.35 | J25: ='Full Historical Statements'!J40 -> 396765.61 | K25: ='Full Historical Statements'!K40 -> 414336.66 | ... M25: ='Full Historical Statements'!M40 -> 455548.7
A26: Other current assets | D26: =SUM('Full Historical Statements'!D38,'Full Historical Statements'!D41:D43) -> 57223 | E26: =SUM('Full Historical Statements'!E38,'Full Historical Statements'!E41:E43) -> 67201 | F26: =SUM('Full Historical Statements'!F38,'Full Historical Statements'!F41:F43) -> 70615 | G26: =SUM('Full Historical Statements'!G38,'Full Historical Statements'!G41:G43) -> 77873 | H26: =SUM('Full Historical Statements'!H38,'Full Historical Statements'!H41:H43) -> 108651 | I26: =SUM('Full Historical Statements'!I38,'Full Historical Statements'!I41:I43) -> 91749.384 | J26: =SUM('Full Historical Statements'!J38,'Full Historical Statements'!J41:J43) -> 97089.283 | K26: =SUM('Full Historical Statements'!K38,'Full Historical Statements'!K41:K43) -> 103687.77 | ... M26: =SUM('Full Historical Statements'!M38,'Full Historical Statements'!M41:M43) -> 105938.92
A27: Total current assets | D27: =SUM(D23:D26) -> 666569 | E27: =SUM(E23:E26) -> 1025975 | F27: =SUM(F23:F26) -> 910704 | G27: =SUM(G23:G26) -> 872269 | H27: =SUM(H23:H26) -> 885883 | I27: =SUM(I23:I26) -> 775183.91 | J27: =SUM(J23:J26) -> 1328387 | K27: =SUM(K23:K26) -> 2097042.5 | ... M27: =SUM(M23:M26) -> 2825416.4
A28: Property and equipment, net | D28: ='Full Historical Statements'!D45 -> 108398 | E28: ='Full Historical Statements'!E45 -> 181529 | F28: ='Full Historical Statements'!F45 -> 238315 | G28: ='Full Historical Statements'!G45 -> 244335 | H28: ='Full Historical Statements'!H45 -> 238191 | I28: ='Full Historical Statements'!I45 -> 240280.33 | J28: ='Full Historical Statements'!J45 -> 240935.44 | K28: ='Full Historical Statements'!K45 -> 320000 | ... M28: ='Full Historical Statements'!M45 -> 360000
A29: Intangible assets, net | D29: ='Full Historical Statements'!D46 -> 28802 | E29: ='Full Historical Statements'!E46 -> 1800167 | F29: ='Full Historical Statements'!F46 -> 1792562 | G29: ='Full Historical Statements'!G46 -> 1777080 | H29: ='Full Historical Statements'!H46 -> 1324680 | I29: ='Full Historical Statements'!I46 -> 1631440.7 | J29: ='Full Historical Statements'!J46 -> 1577733.6 | K29: ='Full Historical Statements'!K46 -> 1511284.7 | ... M29: ='Full Historical Statements'!M46 -> 1554168.2
A30: Goodwill | D30: ='Full Historical Statements'!D47 -> 1600 | E30: ='Full Historical Statements'!E47 -> 714814 | F30: ='Full Historical Statements'!F47 -> 711588 | G30: ='Full Historical Statements'!G47 -> 711491 | H30: ='Full Historical Statements'!H47 -> 404689 | I30: ='Full Historical Statements'!I47 -> 609256 | J30: ='Full Historical Statements'!J47 -> 575145.33 | K30: ='Full Historical Statements'!K47 -> 529696.78 | ... M30: ='Full Historical Statements'!M47 -> 558736.05
A31: Other non-current assets | D31: =SUM('Full Historical Statements'!D48:D51) -> 739699 | E31: =SUM('Full Historical Statements'!E48:E51) -> 779312 | F31: =SUM('Full Historical Statements'!F48:F51) -> 990665 | G31: =SUM('Full Historical Statements'!G48:G51) -> 1206978 | H31: =SUM('Full Historical Statements'!H48:H51) -> 1321307 | I31: =SUM('Full Historical Statements'!I48:I51) -> 1172983.3 | J31: =SUM('Full Historical Statements'!J48:J51) -> 1233756.1 | K31: =SUM('Full Historical Statements'!K48:K51) -> 1419754 | ... M31: =SUM('Full Historical Statements'!M48:M51) -> 1461099.9
A32: Total assets | D32: =D27+SUM(D28:D31) -> 1545068 | E32: =E27+SUM(E28:E31) -> 4501797 | F32: =F27+SUM(F28:F31) -> 4643834 | G32: =G27+SUM(G28:G31) -> 4812153 | H32: =H27+SUM(H28:H31) -> 4174750 | I32: =I27+SUM(I28:I31) -> 4429144.2 | J32: =J27+SUM(J28:J31) -> 4955957.4 | K32: =K27+SUM(K28:K31) -> 5877778 | ... M32: =M27+SUM(M28:M31) -> 6759420.6
A35: Balance Sheet — Liabilities
A36: Accounts payable | D36: ='Full Historical Statements'!D55 -> 162145 | E36: ='Full Historical Statements'!E55 -> 230821 | F36: ='Full Historical Statements'!F55 -> 260978 | G36: ='Full Historical Statements'!G55 -> 264901 | H36: ='Full Historical Statements'!H55 -> 266090 | I36: ='Full Historical Statements'!I55 -> 263589.98 | J36: ='Full Historical Statements'!J55 -> 266066.35 | K36: ='Full Historical Statements'!K55 -> 277849.29 | ... M36: ='Full Historical Statements'!M55 -> 305485.6
A37: Other current liabilities | D37: =SUM('Full Historical Statements'!D56:D59) -> 226098 | E37: =SUM('Full Historical Statements'!E56:E59) -> 410453 | F37: =SUM('Full Historical Statements'!F56:F59) -> 437318 | G37: =SUM('Full Historical Statements'!G56:G59) -> 475307 | H37: =SUM('Full Historical Statements'!H56:H59) -> 434039 | I37: =SUM('Full Historical Statements'!I56:I59) -> 450057.37 | J37: =SUM('Full Historical Statements'!J56:J59) -> 458991.5 | K37: =SUM('Full Historical Statements'!K56:K59) -> 453609.81 | ... M37: =SUM('Full Historical Statements'!M56:M59) -> 463626.49
A38: Total current liabilities | D38: =SUM(D36:D37) -> 388243 | E38: =SUM(E36:E37) -> 641274 | F38: =SUM(F36:F37) -> 698296 | G38: =SUM(G36:G37) -> 740208 | H38: =SUM(H36:H37) -> 700129 | I38: =SUM(I36:I37) -> 713647.35 | J38: =SUM(J36:J37) -> 725057.85 | K38: =SUM(K36:K37) -> 731459.1 | ... M38: =SUM(M36:M37) -> 769112.09
A39: Long-term borrowings | D39: ='Full Historical Statements'!D63 -> 771390 | E39: ='Full Historical Statements'!E63 -> 2298027 | F39: ='Full Historical Statements'!F63 -> 1640996 | G39: ='Full Historical Statements'!G63 -> 1349339 | H39: ='Full Historical Statements'!H63 -> 1230885 | I39: ='Full Historical Statements'!I63 -> 950566 | J39: ='Full Historical Statements'!J63 -> 750566 | K39: ='Full Historical Statements'!K63 -> 900566 | ... M39: ='Full Historical Statements'!M63 -> 400566
A40: Other non-current liabilities | D40: =SUM('Full Historical Statements'!D61:D62,'Full Historical Statements'!D64:D65) -> 371353 | E40: =SUM('Full Historical Statements'!E61:E62,'Full Historical Statements'!E64:E65) -> 744565 | F40: =SUM('Full Historical Statements'!F61:F62,'Full Historical Statements'!F64:F65) -> 850619 | G40: =SUM('Full Historical Statements'!G61:G62,'Full Historical Statements'!G64:G65) -> 886874 | H40: =SUM('Full Historical Statements'!H61:H62,'Full Historical Statements'!H64:H65) -> 950453 | I40: =SUM('Full Historical Statements'!I61:I62,'Full Historical Statements'!I64:I65) -> 1023003.4 | J40: =SUM('Full Historical Statements'!J61:J62,'Full Historical Statements'!J64:J65) -> 1101872.3 | K40: =SUM('Full Historical Statements'!K61:K62,'Full Historical Statements'!K64:K65) -> 1294081.6 | ... M40: =SUM('Full Historical Statements'!M61:M62,'Full Historical Statements'!M64:M65) -> 1502372.3
A41: Total liabilities | D41: =D38+SUM(D39:D40) -> 1530986 | E41: =E38+SUM(E39:E40) -> 3683866 | F41: =F38+SUM(F39:F40) -> 3189911 | G41: =G38+SUM(G39:G40) -> 2976421 | H41: =H38+SUM(H39:H40) -> 2881467 | I41: =I38+SUM(I39:I40) -> 2687216.8 | J41: =J38+SUM(J39:J40) -> 2577496.1 | K41: =K38+SUM(K39:K40) -> 2926106.7 | ... M41: =M38+SUM(M39:M40) -> 2672050.4
A44: Balance Sheet — Stockholders' Equity
A45: Common stock | D45: ='Full Historical Statements'!D69 -> 106 | E45: ='Full Historical Statements'!E69 -> 110 | F45: ='Full Historical Statements'!F69 -> 110 | G45: ='Full Historical Statements'!G69 -> 110 | H45: ='Full Historical Statements'!H69 -> 111 | I45: ='Full Historical Statements'!I69 -> 110 | J45: ='Full Historical Statements'!J69 -> 110 | K45: ='Full Historical Statements'!K69 -> 110 | ... M45: ='Full Historical Statements'!M69 -> 110
A46: Treasury stock, at cost | D46: ='Full Historical Statements'!D70 -> -1684262 | E46: ='Full Historical Statements'!E70 -> -1695501 | F46: ='Full Historical Statements'!F70 -> -1888869 | G46: ='Full Historical Statements'!G70 -> -2453473 | H46: ='Full Historical Statements'!H70 -> -3040416 | I46: ='Full Historical Statements'!I70 -> -2890416 | J46: ='Full Historical Statements'!J70 -> -2740416 | K46: ='Full Historical Statements'!K70 -> -2590416 | ... M46: ='Full Historical Statements'!M70 -> -2290416
A47: Additional paid-in capital | D47: ='Full Historical Statements'!D71 -> 496036 | E47: ='Full Historical Statements'!E71 -> 797614 | F47: ='Full Historical Statements'!F71 -> 826685 | G47: ='Full Historical Statements'!G71 -> 859904 | H47: ='Full Historical Statements'!H71 -> 896605 | I47: ='Full Historical Statements'!I71 -> 929547 | J47: ='Full Historical Statements'!J71 -> 963779 | K47: ='Full Historical Statements'!K71 -> 998404 | ... M47: ='Full Historical Statements'!M71 -> 1066600.3
A48: Retained earnings | D48: ='Full Historical Statements'!D72 -> 1279040 | E48: ='Full Historical Statements'!E72 -> 1819199 | F48: ='Full Historical Statements'!F72 -> 2611765 | G48: ='Full Historical Statements'!G72 -> 3561836 | H48: ='Full Historical Statements'!H72 -> 3480638 | I48: ='Full Historical Statements'!I72 -> 3793375.8 | J48: ='Full Historical Statements'!J72 -> 4243984.7 | K48: ='Full Historical Statements'!K72 -> 4618020.2 | ... M48: ='Full Historical Statements'!M72 -> 5393794
A49: Accumulated other comprehensive loss | D49: ='Full Historical Statements'!D73 -> -76838 | E49: ='Full Historical Statements'!E73 -> -103491 | F49: ='Full Historical Statements'!F73 -> -95768 | G49: ='Full Historical Statements'!G73 -> -132645 | H49: ='Full Historical Statements'!H73 -> -43655 | I49: ='Full Historical Statements'!I73 -> -90689.333 | J49: ='Full Historical Statements'!J73 -> -88996.444 | K49: ='Full Historical Statements'!K73 -> -74446.926 | ... M49: ='Full Historical Statements'!M73 -> -82718.091
A50: Total stockholders' equity | D50: ='Full Historical Statements'!D74 -> 14082 | E50: ='Full Historical Statements'!E74 -> 817931 | F50: ='Full Historical Statements'!F74 -> 1453923 | G50: ='Full Historical Statements'!G74 -> 1835732 | H50: ='Full Historical Statements'!H74 -> 1293283 | I50: ='Full Historical Statements'!I74 -> 1741927.5 | J50: ='Full Historical Statements'!J74 -> 2378461.3 | K50: ='Full Historical Statements'!K74 -> 2951671.3 | ... M50: ='Full Historical Statements'!M74 -> 4087370.2
A51: Total liabilities and stockholders' equity | D51: =D41+D50 -> 1545068 | E51: =E41+E50 -> 4501797 | F51: =F41+F50 -> 4643834 | G51: =G41+G50 -> 4812153 | H51: =H41+H50 -> 4174750 | I51: =I41+I50 -> 4429144.2 | J51: =J41+J50 -> 4955957.4 | K51: =K41+K50 -> 5877778 | ... M51: =M41+M50 -> 6759420.6
A52: Balance sheet check | D52: =D32-D51 -> 0 | E52: =E32-E51 -> 0 | F52: =F32-F51 -> 0 | G52: =G32-G51 -> 0 | H52: =H32-H51 -> 0 | I52: =I32-I51 -> 0 | J52: =J32-J51 -> 0 | K52: =K32-K51 -> 0 | ... M52: =M32-M51 -> 0
A55: Cash Flow Statement
A56: Net income (loss) | D56: ='Full Historical Statements'!D80 -> 725694 | E56: ='Full Historical Statements'!E80 -> 540159 | F56: ='Full Historical Statements'!F80 -> 792566 | G56: ='Full Historical Statements'!G80 -> 950071 | H56: ='Full Historical Statements'!H80 -> -81198 | I56: ='Full Historical Statements'!I80 -> 312737.83 | J56: ='Full Historical Statements'!J80 -> 450608.9 | K56: ='Full Historical Statements'!K80 -> 374035.48 | ... M56: ='Full Historical Statements'!M80 -> 412105.14
A57: Depreciation and amortization | D57: ='Full Historical Statements'!D81 -> 31976 | E57: ='Full Historical Statements'!E81 -> 39229 | F57: ='Full Historical Statements'!F81 -> 54304 | G57: ='Full Historical Statements'!G81 -> 69840 | H57: ='Full Historical Statements'!H81 -> 79282 | I57: ='Full Historical Statements'!I81 -> 174203.1 | J57: ='Full Historical Statements'!J81 -> 35420.31 | K57: ='Full Historical Statements'!K81 -> 7180.677 | ... M57: ='Full Historical Statements'!M81 -> 43718.532
A58: Other non-cash adjustments | D58: ='Full Historical Statements'!D82+'Full Historical Statements'!D83+'Full Historical Statements'!D84+'Full Historical Statements'!D85+'Full Historical Statements'!D86+'Full Historical Statements'!D87+'Full Historical Statements'!D88 -> -145933 | E58: ='Full Historical Statements'!E82+'Full Historical Statements'!E83+'Full Historical Statements'!E84+'Full Historical Statements'!E85+'Full Historical Statements'!E86+'Full Historical Statements'!E87+'Full Historical Statements'!E88 -> 105489 | F58: ='Full Historical Statements'!F82+'Full Historical Statements'!F83+'Full Historical Statements'!F84+'Full Historical Statements'!F85+'Full Historical Statements'!F86+'Full Historical Statements'!F87+'Full Historical Statements'!F88 -> -286352 | G58: ='Full Historical Statements'!G82+'Full Historical Statements'!G83+'Full Historical Statements'!G84+'Full Historical Statements'!G85+'Full Historical Statements'!G86+'Full Historical Statements'!G87+'Full Historical Statements'!G88 -> -110026 | H58: ='Full Historical Statements'!H82+'Full Historical Statements'!H83+'Full Historical Statements'!H84+'Full Historical Statements'!H85+'Full Historical Statements'!H86+'Full Historical Statements'!H87+'Full Historical Statements'!H88 -> 926903 | I58: ='Full Historical Statements'!I82+'Full Historical Statements'!I83+'Full Historical Statements'!I84+'Full Historical Statements'!I85+'Full Historical Statements'!I86+'Full Historical Statements'!I87+'Full Historical Statements'!I88 -> 161760.65 | J58: ='Full Historical Statements'!J82+'Full Historical Statements'!J83+'Full Historical Statements'!J84+'Full Historical Statements'!J85+'Full Historical Statements'!J86+'Full Historical Statements'!J87+'Full Historical Statements'!J88 -> 191853.02 | K58: ='Full Historical Statements'!K82+'Full Historical Statements'!K83+'Full Historical Statements'!K84+'Full Historical Statements'!K85+'Full Historical Statements'!K86+'Full Historical Statements'!K87+'Full Historical Statements'!K88 -> 227538.64 | ... M58: ='Full Historical Statements'!M82+'Full Historical Statements'!M83+'Full Historical Statements'!M84+'Full Historical Statements'!M85+'Full Historical Statements'!M86+'Full Historical Statements'!M87+'Full Historical Statements'!M88 -> 323412.55
A59: Change in net working capital and other operating items | D59: =SUM('Full Historical Statements'!D89:D96) -> -44572 | E59: =SUM('Full Historical Statements'!E89:E96) -> -81735 | F59: =SUM('Full Historical Statements'!F89:F96) -> 369926 | G59: =SUM('Full Historical Statements'!G89:G96) -> 82601 | H59: =SUM('Full Historical Statements'!H89:H96) -> -214556 | I59: =SUM('Full Historical Statements'!I89:I96) -> -13791.324 | J59: =SUM('Full Historical Statements'!J89:J96) -> -120553.74 | K59: =SUM('Full Historical Statements'!K89:K96) -> -167360.36 | ... M59: =SUM('Full Historical Statements'!M89:M96) -> -190263.99
A60: Cash provided by operating activities | D60: ='Full Historical Statements'!D97 -> 234004 | E60: ='Full Historical Statements'!E97 -> 302320 | F60: ='Full Historical Statements'!F97 -> -106501 | G60: ='Full Historical Statements'!G97 -> -80813 | H60: ='Full Historical Statements'!H97 -> 31778 | I60: ='Full Historical Statements'!I97 -> 47154.964 | J60: ='Full Historical Statements'!J97 -> 2831.1253 | K60: ='Full Historical Statements'!K97 -> 11789.607 | ... M60: ='Full Historical Statements'!M97 -> 16974.313
A61: Capital expenditures | D61: ='Full Historical Statements'!D99 -> -55916 | E61: ='Full Historical Statements'!E99 -> -104190 | F61: ='Full Historical Statements'!F99 -> -115625 | G61: ='Full Historical Statements'!G99 -> -69347 | H61: ='Full Historical Statements'!H99 -> -51231 | I61: ='Full Historical Statements'!I99 -> 20000 | J61: ='Full Historical Statements'!J99 -> 20000 | K61: ='Full Historical Statements'!K99 -> 20000 | ... M61: ='Full Historical Statements'!M99 -> 100000
A62: Other investing activities | D62: =SUM('Full Historical Statements'!D100:D102) -> -9 | E62: =SUM('Full Historical Statements'!E100:E102) -> -2046901 | F62: =SUM('Full Historical Statements'!F100:F102) -> -46 | G62: =SUM('Full Historical Statements'!G100:G102) -> 0 | H62: =SUM('Full Historical Statements'!H100:H102) -> 0 | I62: =SUM('Full Historical Statements'!I100:I102) -> 0 | J62: =SUM('Full Historical Statements'!J100:J102) -> 0 | K62: =SUM('Full Historical Statements'!K100:K102) -> -400000 | ... M62: =SUM('Full Historical Statements'!M100:M102) -> -500000
A63: Cash used in investing activities | D63: ='Full Historical Statements'!D103 -> -55925 | E63: ='Full Historical Statements'!E103 -> -2151091 | F63: ='Full Historical Statements'!F103 -> -115671 | G63: ='Full Historical Statements'!G103 -> -69347 | H63: ='Full Historical Statements'!H103 -> -51231 | I63: ='Full Historical Statements'!I103 -> 20000 | J63: ='Full Historical Statements'!J103 -> 20000 | K63: ='Full Historical Statements'!K103 -> -380000 | ... M63: ='Full Historical Statements'!M103 -> -400000
A64: Net debt issuance / (repayment) | D64: =SUM('Full Historical Statements'!D104:D106) -> 605000 | E64: =SUM('Full Historical Statements'!E104:E106) -> 1594613 | F64: =SUM('Full Historical Statements'!F104:F106) -> -665798 | G64: =SUM('Full Historical Statements'!G104:G106) -> -323249 | H64: =SUM('Full Historical Statements'!H104:H106) -> -128000 | I64: =SUM('Full Historical Statements'!I104:I106) -> -312000 | J64: =SUM('Full Historical Statements'!J104:J106) -> -200000 | K64: =SUM('Full Historical Statements'!K104:K106) -> 150000 | ... M64: =SUM('Full Historical Statements'!M104:M106) -> -150000
A65: Share repurchases and other financing | D65: =SUM('Full Historical Statements'!D107:D110) -> -1034638 | E65: =SUM('Full Historical Statements'!E107:E110) -> -64954 | F65: =SUM('Full Historical Statements'!F107:F110) -> -193841 | G65: =SUM('Full Historical Statements'!G107:G110) -> -562799 | H65: =SUM('Full Historical Statements'!H107:H110) -> -586565 | I65: =SUM('Full Historical Statements'!I107:I110) -> -159000 | J65: =SUM('Full Historical Statements'!J107:J110) -> -159000 | K65: =SUM('Full Historical Statements'!K107:K110) -> -159000 | ... M65: =SUM('Full Historical Statements'!M107:M110) -> -159000
A66: Cash provided by / (used in) financing activities | D66: ='Full Historical Statements'!D111 -> -429638 | E66: ='Full Historical Statements'!E111 -> 1529659 | F66: ='Full Historical Statements'!F111 -> -859639 | G66: ='Full Historical Statements'!G111 -> -886048 | H66: ='Full Historical Statements'!H111 -> -714565 | I66: ='Full Historical Statements'!I111 -> -471000 | J66: ='Full Historical Statements'!J111 -> -359000 | K66: ='Full Historical Statements'!K111 -> -9000 | ... M66: ='Full Historical Statements'!M111 -> -309000
A67: Effect of exchange rate changes | D67: ='Full Historical Statements'!D112 -> -3950 | E67: ='Full Historical Statements'!E112 -> -3750 | F67: ='Full Historical Statements'!F112 -> 3078 | G67: ='Full Historical Statements'!G112 -> -6510 | H67: ='Full Historical Statements'!H112 -> 5598 | I67: ='Full Historical Statements'!I112 -> 722 | J67: ='Full Historical Statements'!J112 -> -63.333333 | K67: ='Full Historical Statements'!K112 -> 2085.5556 | ... M67: ='Full Historical Statements'!M112 -> 978.98765
A68: Net change in cash | D68: ='Full Historical Statements'!D113 -> 77652 | E68: ='Full Historical Statements'!E113 -> -22040 | F68: ='Full Historical Statements'!F113 -> -41788 | G68: ='Full Historical Statements'!G113 -> 30581 | H68: ='Full Historical Statements'!H113 -> -49767 | I68: ='Full Historical Statements'!I113 -> 184632.26 | J68: ='Full Historical Statements'!J113 -> 218265.16 | K68: ='Full Historical Statements'!K113 -> 54480.001 | ... M68: ='Full Historical Statements'!M113 -> -119048.77
A69: Cash — beginning of year | D69: ='Full Historical Statements'!D114 -> 139273 | E69: ='Full Historical Statements'!E114 -> 216925 | F69: ='Full Historical Statements'!F114 -> 194885 | G69: ='Full Historical Statements'!G114 -> 153097 | H69: ='Full Historical Statements'!H114 -> 183678 | I69: ='Full Historical Statements'!I114 -> 177220 | J69: ='Full Historical Statements'!J114 -> 171331.67 | K69: ='Full Historical Statements'!K114 -> 177409.89 | ... M69: ='Full Historical Statements'!M114 -> 174687.36
A70: Cash — end of year | D70: ='Full Historical Statements'!D115 -> 216925 | E70: ='Full Historical Statements'!E115 -> 194885 | F70: ='Full Historical Statements'!F115 -> 153097 | G70: ='Full Historical Statements'!G115 -> 183678 | H70: ='Full Historical Statements'!H115 -> 133911 | I70: ='Full Historical Statements'!I115 -> 361852.26 | J70: ='Full Historical Statements'!J115 -> 389596.82 | K70: ='Full Historical Statements'!K115 -> 231889.89 | ... M70: ='Full Historical Statements'!M115 -> 55638.584
A71: Cash flow reconciliation check | D71: =D70-D23 -> 3728 | E71: =E70-E23 -> 3256 | F71: =F70-F23 -> 3809 | G71: =G70-G23 -> 3193 | H71: =H70-H23 -> 3557 | I71: =I70-I23 -> 369950.67 | J71: =J70-J23 -> -144860.42 | K71: =K70-K23 -> -1041051.8 | ... M71: =M70-M23 -> -1886726.4

Sheet DCF
B2: Revenue Growth | F2: =F8/E8-1 -> 0.035272277 | G2: =G8/F8-1 -> -0.014982784 | H2: =H8/G8-1 -> -0.006 | I2: 0.06 | J2: 0.06 | K2: 0.06 | L2: 0.07 | M2: 0.08
B3: COGS | C3: (% of Revenue) | E3: =-E9/E8 -> 0.44224723 | F3: =-F9/F8 -> 0.41243429 | G3: =-G9/G8 -> 0.41666396 | H3: =-H9/H8 -> 0.42 | I3: =-I9/I8 -> 0.42 | J3: =-J9/J8 -> 0.43 | K3: =-K9/K8 -> 0.44 | L3: =-L9/L8 -> 0.45 | M3: 0.4
B4: SG&A | C4: (% of Revenue) | E4: =E12/E8 -> 0.29375014 | F4: =F12/F8 -> 0.33257657 | G4: =G12/G8 -> 0.36366082 | H4: =H12/H8 -> 0.32 | I4: =I12/I8 -> 0.33 | J4: =J12/J8 -> 0.36 | K4: =K12/K8 -> 0.36 | L4: =L12/L8 -> 0.35 | M4: 0.3
B6: Depreciation | F6: =F15/E15-1 -> 0.28609311 | G6: =G15/F15-1 -> 0.13519473 | H6: =H15/G15-1 -> 1.1972592 | I6: =I15/H15-1 -> -0.79667233 | J6: =J15/I15-1 -> -0.79727233 | K6: =K15/J15-1 -> 0.53557581 | L6: =L15/K15-1 -> 2.9648697 | M6: 0.049
B8: Revenue | E8: ='Simplified Model'!F7 -> 3962347 | F8: ='Simplified Model'!G7 -> 4102108 | G8: ='Simplified Model'!H7 -> 4040647 | H8: ='Simplified Model'!I7 -> 4016403.1 | I8: ='Simplified Model'!J7 -> 4056567.1 | J8: ='Simplified Model'!K7 -> 4137698.5 | K8: ='Simplified Model'!L7 -> 4220452.5 | L8: ='Simplified Model'!M7 -> 4347066 | M8: =L8*(1+M2) -> 4694831.3
B9: COGS | E9: =-'Simplified Model'!F8 -> -1752337 | F9: =-'Simplified Model'!G8 -> -1691850 | G9: =-'Simplified Model'!H8 -> -1683592 | H9: =-'Simplified Model'!I8 -> -1686889.3 | I9: =-'Simplified Model'!J8 -> -1703758.2 | J9: =-'Simplified Model'!K8 -> -1779210.4 | K9: =-'Simplified Model'!L8 -> -1856999.1 | L9: =-'Simplified Model'!M8 -> -1956179.7 | M9: =L9*(1+M3) -> -2738651.6
B10: Gross Profit | E10: =E8+E9 -> 2210010 | F10: =F8+F9 -> 2410258 | G10: =G8+G9 -> 2357055 | H10: =H8+H9 -> 2329513.8 | I10: =I8+I9 -> 2352808.9 | J10: =J8+J9 -> 2358488.1 | K10: =K8+K9 -> 2363453.4 | L10: =L8+L9 -> 2390886.3 | M10: =M8+M9 -> 1956179.7
B12: SG&A | E12: ='Simplified Model'!F10 -> 1163940 | F12: ='Simplified Model'!G10 -> 1364265 | G12: ='Simplified Model'!H10 -> 1469425 | H12: ='Simplified Model'!I10 -> 1285249 | I12: ='Simplified Model'!J10 -> 1338667.2 | J12: ='Simplified Model'!K10 -> 1489571.5 | K12: ='Simplified Model'!L10 -> 1519362.9 | L12: ='Simplified Model'!M10 -> 1521473.1 | M12: =L12*(1+M4) -> 1977915
B13: EBITDA | E13: =E10-E12-E15 -> 1100374 | F13: =F10-F12-F15 -> 1115833 | G13: =G10-G12-G15 -> 966912 | H13: =H10-H12-H15 -> 1218467.9 | I13: =I10-I12-I15 -> 1049562.1 | J13: =J10-J12-J15 -> 876097.36 | K13: =K10-K12-K15 -> 855116.97 | L13: =L10-L12-L15 -> 913131.74 | M13: =M10-M12-M15 -> 24125.41
B15: Tax Depreciation | E15: =-'Simplified Model'!F57 -> -54304 | F15: =-'Simplified Model'!G57 -> -69840 | G15: =-'Simplified Model'!H57 -> -79282 | H15: =-'Simplified Model'!I57 -> -174203.1 | I15: =-'Simplified Model'!J57 -> -35420.31 | J15: =-'Simplified Model'!K57 -> -7180.677 | K15: =-'Simplified Model'!L57 -> -11026.474 | L15: =-'Simplified Model'!M57 -> -43718.532 | M15: =L15*(1+M6) -> -45860.74
B16: Operating Profit | E16: =E10-E12 -> 1046070 | F16: =F10-F12 -> 1045993 | G16: =G10-G12 -> 887630 | H16: =H10-H12 -> 1044264.8 | I16: =I10-I12 -> 1014141.8 | J16: =J10-J12 -> 868916.68 | K16: =K10-K12 -> 844090.49 | L16: =L10-L12 -> 869413.21 | M16: =M10-M12 -> -21735.33
B18: Tax Rate | E18: ='Full Historical Statements'!F11 -> 0.095525134 | F18: ='Full Historical Statements'!G11 -> 0.043363332 | G18: ='Full Historical Statements'!H11 -> 2.1126367 | H18: ='Full Historical Statements'!I11 -> 0.25 | I18: ='Full Historical Statements'!J11 -> 0.25 | J18: ='Full Historical Statements'!K11 -> 0.25 | K18: ='Full Historical Statements'!L11 -> 0.25 | L18: ='Full Historical Statements'!M11 -> 0.25 | M18: 0.28
B19: Current Tax | E19: =-'Simplified Model'!F18 -> -83706 | F19: =-'Simplified Model'!G18 -> 39486 | G19: =-'Simplified Model'!H18 -> -154176 | H19: =-'Simplified Model'!I18 -> -104245.94 | I19: =-'Simplified Model'!J18 -> -56043.96 | J19: =-'Simplified Model'!K18 -> -124678.49 | K19: =-'Simplified Model'!L18 -> -95692.24 | L19: =-'Simplified Model'!M18 -> -124899.32 | M19: =M16*M18 -> -6085.8925
B24: Unlevered Free Cash Flow Schedule
E27: Year -2 | F27: Year - 1 | G27: Year 0 | H27: Year 1 | I27: Year 2 | J27: Year 3 | K27: Year 4 | L27: Year 5 | M27: Term
B28: Unlevered Free Cash Flow
B29: EBIT | E29: =E16 -> 1046070 | F29: =F16 -> 1045993 | G29: =G16 -> 887630 | H29: =H16 -> 1044264.8 | I29: =I16 -> 1014141.8 | J29: =J16 -> 868916.68 | K29: =K16 -> 844090.49 | L29: =L16 -> 869413.21 | M29: =M16 -> -21735.33
B30: Current Taxes | E30: =E19 -> -83706 | F30: =F19 -> 39486 | G30: =G19 -> -154176 | H30: =H19 -> -104245.94 | I30: =I19 -> -56043.96 | J30: =J19 -> -124678.49 | K30: =K19 -> -95692.24 | L30: =L19 -> -124899.32 | M30: =M19 -> -6085.8925
B31: NOPAT | E31: =SUM(E29:E30) -> 962364 | F31: =SUM(F29:F30) -> 1085479 | G31: =SUM(G29:G30) -> 733454 | H31: =SUM(H29:H30) -> 940018.87 | I31: =SUM(I29:I30) -> 958097.83 | J31: =SUM(J29:J30) -> 744238.19 | K31: =SUM(K29:K30) -> 748398.25 | L31: =SUM(L29:L30) -> 744513.89 | M31: =SUM(M29:M30) -> -27821.223
B32: D&A | E32: =-E15 -> 54304 | F32: =-F15 -> 69840 | G32: =-G15 -> 79282 | H32: =-H15 -> 174203.1 | I32: =-I15 -> 35420.31 | J32: =-J15 -> 7180.677 | K32: =-K15 -> 11026.474 | L32: =-L15 -> 43718.532 | M32: =-M15 -> 45860.74
B33: Capital Expenditure | E33: ='Simplified Model'!F61 -> -115625 | F33: ='Simplified Model'!G61 -> -69347 | G33: ='Simplified Model'!H61 -> -51231 | H33: =-'Simplified Model'!I61 -> -20000 | I33: =-'Simplified Model'!J61 -> -20000 | J33: =-'Simplified Model'!K61 -> -20000 | K33: =-'Simplified Model'!L61 -> -120000 | L33: =-'Simplified Model'!M61 -> -100000 | M33: -70000
B34: Cash from Working Capital | E34: ='Full Historical Statements'!F125 -> -106501 | F34: ='Full Historical Statements'!G125 -> -80813 | G34: ='Full Historical Statements'!H125 -> 31778 | H34: ='Full Historical Statements'!I125 -> 47154.964 | I34: ='Full Historical Statements'!J125 -> 2831.1253 | J34: ='Full Historical Statements'!K125 -> 11789.607 | K34: ='Full Historical Statements'!L125 -> 12088.881 | L34: ='Full Historical Statements'!M125 -> 16974.313 | M34: 46000
B35: Unlevered Free Cash Flow | E35: =SUM(E31:E34) -> 794542 | F35: =SUM(F31:F34) -> 1005159 | G35: =SUM(G31:G34) -> 793283 | H35: =SUM(H31:H34) -> 1141376.9 | I35: =SUM(I31:I34) -> 976349.26 | J35: =SUM(J31:J34) -> 743208.47 | K35: =SUM(K31:K34) -> 651513.61 | L35: =SUM(L31:L34) -> 705206.73 | M35: =SUM(M31:M34) -> -5960.4828
B38: Discounted Cash Flow Schedule
H40: Year 1 | I40: Year 2 | J40: Year 3 | K40: Year 4 | L40: Year 5 | M40: Term
B42: Unlevered Free Cash Flow | H42: 794542 | I42: =I35 -> 976349.26 | J42: =J35 -> 743208.47 | K42: =K35 -> 651513.61 | L42: =L35 -> 705206.73 | M42: =M35 -> -5960.4828
B43: EBITDA | M43: =M13 -> 24125.41
B46: UNDISCOUNTED CASH FLOW
B47: Discrete Forecast | H47: =H42 -> 794542 | I47: =I42 -> 976349.26 | J47: =J42 -> 743208.47 | K47: =K42 -> 651513.61 | L47: =L42 -> 705206.73 | M47: =M42 -> -5960.4828
B48: Terminal Value | H48: 0 | I48: 0 | J48: 0 | K48: 0 | L48: 0 | M48: =M43*C54 -> 1930.0328
B49: Total Cash Flow | H49: =SUM(H47:H48) -> 794542 | I49: =SUM(I47:I48) -> 976349.26 | J49: =SUM(J47:J48) -> 743208.47 | K49: =SUM(K47:K48) -> 651513.61 | L49: =SUM(L47:L48) -> 705206.73 | M49: =SUM(M47:M48) -> -4030.4501
C51: 8
B52: ASSUMPTIONS | F52: ENTERPRISE VALUE | J52: EQUITY VALUE PER SHARE
B53: First Year of Forecast | C53: 2026 | F53: PV of Discrete | H53: =NPV(C55,H47,I47,J47,K47,L47) -> 2862298.8 | J53: Equity Value | M53: =H61 -> 2021526.2
B54: Terminal Multiple | C54: 0.08 | F54: PV of Terminal | H54: =NPV(C55,H48:M48) -> 1002.4352 | J54: Shares Outstanding | L54: (000s) | M54: 54200
B55: Discount Rate | C55: =(C75*C62)+(C81*C68) -> 0.1153677 | F55: Enterprise Value | H55: =H53+H54 -> 2863301.2 | J55: Equity Value | L55: (USD) | M55: =M53/M54 -> 37.297532
B58: COST OF EQUITY | F58: EQUITY VALUE
B59: Risk-free rate (US 10y) | C59: 0.0462 | F59: Enterprise Value | H59: =H55 -> 2863301.2
B60: Beta | C60: 1.55 | F60: Less: Net Debt | H60: =-(1542341-700566) -> -841775
B61: Market risk premium | C61: 0.05 | F61: Equity Value | H61: =SUM(H59:H60) -> 2021526.2
B62: CAPM | C62: =C59+C60*C61 -> 0.1237
B65: AFTER-TAX COST OF DEBT
B66: Interest rate on debt | C66: 0.09
B67: Tax rate | C67: =28% -> 0.28
B68: After-tax cost of debt | C68: =C66*(1-C67) -> 0.0648
B71: MARKET VALUE OF EQUITY AND DEBT
B72: Share price (13/07/26) | C72: 130.46
B73: Shares Outstanding | C73: =M54 -> 54200
B74: Market Value of Equity | C74: =C72*C73 -> 7070932
B75: Weight | C75: =C74/(C80+C74) -> 0.85853474
B76: Interest Expense | C76: =-'Simplified Model'!H15 -> 88287
B77: Current Cost of Debt | C77: =C66 -> 0.09
B78: Total Debt | C78: ='Simplified Model'!H39 -> 1230885
B79: Average Maturity | C79: =4362000/C78 -> 3.5437917
B80: Market Value of Debt | C80: =-PV(C77,C79,C76,C78) -> 1165114.4
B81: Weight | C81: =C80/(C80+C74) -> 0.14146526
