Workbook

Sheet Summary
B2: Paramount Skydance Corporation
B4: Ticker | C4: PSKY | E4: Today's Share Price | G4: 8.07
B5: Date | C5: 46232 | E5: Upside | G5: =G6-G4 -> 39.218809
E6: Implied Share Price | G6: =DCF!N60 -> 47.288809
B9: ASSUMPTIONS
B10: Discount Rate | D10: =DCF!D61 -> 0.07595328
B11: Growth Rate | D11: =DCF!D60 -> 0.03
B12: Terminal Value | D12: =DCF!I59 -> 48622.812
B13: Enterprise Value | D13: =DCF!I60 -> 62496.267
B16: DCF | E16: 2023 | F16: 2024 | G16: 2025 | H16: 2026 | I16: 2027 | J16: 2028 | K16: 2029 | L16: 2030
B17: Revenue | E17: =DCF!F11 -> 29652 | F17: =DCF!G11 -> 29213 | G17: =DCF!H11 -> 28891 | H17: =DCF!I11 -> 29244.815 | I17: =DCF!J11 -> 29850.199 | J17: =DCF!K11 -> 30577.804 | K17: =DCF!L11 -> 31474.798 | L17: =DCF!M11 -> 32473.32
B18: % growth | F18: =F17/E17-1 -> -0.014805072 | G18: =G17/F17-1 -> -0.01102249 | H18: =H17/G17-1 -> 0.012246548 | I18: =I17/H17-1 -> 0.020700573 | J18: =J17/I17-1 -> 0.024375211 | K18: =K17/J17-1 -> 0.029334793 | L18: =L17/K17-1 -> 0.031724486
B20: EBIT | E20: =DCF!F16 -> -33 | F20: =DCF!G16 -> -4877 | G20: =DCF!H16 -> 1693 | H20: =DCF!I16 -> 2997.935 | I20: =DCF!J16 -> 3006.9872 | J20: =DCF!K16 -> 3289.2668 | K20: =DCF!L16 -> 4047.0332 | L20: =DCF!M16 -> 4898.3747
B21: % margin | E21: =E20/E17 -> -0.0011129098 | F21: =F20/F17 -> -0.16694622 | G21: =G20/G17 -> 0.058599564 | H21: =H20/H17 -> 0.10251168 | I21: =I20/I17 -> 0.10073592 | J21: =J20/J17 -> 0.1075704 | K21: =K20/K17 -> 0.12858012 | L21: =L20/L17 -> 0.15084305
B23: Taxes | E23: =DCF!F22 -> -361 | F23: =DCF!G22 -> -305 | G23: =DCF!H22 -> -119 | H23: =DCF!I22 -> 323.7244 | I23: =DCF!J22 -> 335.3487 | J23: =DCF!K22 -> 414.79735 | K23: =DCF!L22 -> 604.17694 | L23: =DCF!M22 -> 818.5088
B24: % of EBIT | E24: =E23/E20 -> 10.939394 | F24: =F23/F20 -> 0.062538446 | G24: =G23/G20 -> -0.070289427 | H24: =H23/H20 -> 0.10798246 | I24: =I23/I20 -> 0.11152316 | J24: =J23/J20 -> 0.12610633 | K24: =K23/K20 -> 0.14928885 | L24: =L23/L20 -> 0.16709804
B26: NOPAT | E26: =DCF!F34 -> -25.608 | F26: =DCF!G34 -> -4647.781 | G26: =DCF!H34 -> 876.974 | H26: =DCF!I34 -> 2278.4306 | I26: =DCF!J34 -> 2285.3103 | J26: =DCF!K34 -> 2499.8427 | K26: =DCF!L34 -> 3075.7452 | L26: =DCF!M34 -> 3722.7648
B27: Plus: D&A | E27: =DCF!F35 -> 418 | F27: =DCF!G35 -> 392 | G27: =DCF!H35 -> 794 | H27: =DCF!I35 -> 797.97 | I27: =DCF!J35 -> 801.95985 | J27: =DCF!K35 -> 805.96965 | K27: =DCF!L35 -> 809.9995 | L27: =DCF!M35 -> 814.04949
B28: Less: Capital Expenditure | E28: =DCF!F36 -> -328 | F28: =DCF!G36 -> -263 | G28: =DCF!H36 -> -296 | H28: =DCF!I36 -> -290.08 | I28: =DCF!J36 -> -284.2784 | J28: =DCF!K36 -> -278.59283 | K28: =DCF!L36 -> -273.02098 | L28: =DCF!M36 -> -267.56056
B29: Less: Change in Net Working Capital | E29: =DCF!F37 -> 78 | F29: =DCF!G37 -> -33 | G29: =DCF!H37 -> -226 | H29: =DCF!I37 -> 168.0119 | I29: =DCF!J37 -> 168.60629 | J29: =DCF!K37 -> 161.04275 | K29: =DCF!L37 -> 237.52835 | L29: =DCF!M37 -> 241.81706
B31: Unlevered Free Cash Flow | E31: =DCF!F38 -> 142.392 | F31: =DCF!G38 -> -4551.781 | G31: =DCF!H38 -> 1148.974 | H31: =DCF!I38 -> 2954.3325 | I31: =DCF!J38 -> 2971.598 | J31: =DCF!K38 -> 3188.2623 | K31: =DCF!L38 -> 3850.2521 | L31: =DCF!M38 -> 4511.0708
B33: Present Value (PV) of UFCF | H33: =H31/(1+$D$10)^1 -> 2745.7814 | I33: =I31/(1+$D$10)^2 -> 2566.8662 | J33: =J31/(1+$D$10)^3 -> 2559.61 | K33: =K31/(1+$D$10)^4 -> 2872.8669 | L33: =L31/(1+$D$10)^5 -> 3128.3301
B35: Total PV of UFCF | L35: =SUM(H33:L33) -> 13873.455

Sheet Historicals
B2: Paramount – Historical Three-Statement Model
B3: USD in millions, except per-share data. 2025 combines reported predecessor and successor periods; the 2025 balance sheet is Successor.
B5: Revenue growth | D5: =D19/C19-1 -> 0.054852025 | E5: =E19/D19-1 -> -0.016647874 | F5: =F19/E19-1 -> -0.014805072 | G5: =G19/F19-1 -> -0.01102249
B6: Operating Expenese Growth (% of Revenue) | C6: =-C20/C19 -> 0.62072343 | D6: =-D20/D19 -> 0.65812164 | E6: =-E20/E19 -> 0.67506408 | F6: =-F20/F19 -> 0.66535447 | G6: =-G20/G19 -> 0.68170018
B7: SGA (% of Revenue) | C7: =-C22/C19 -> 0.22381585 | D7: =-D22/D19 -> 0.23323605 | E7: =-E22/E19 -> 0.24433428 | F7: =-F22/F19 -> 0.22791223 | G7: =-G22/G19 -> 0.21183067
B8: D&A (% of PPE) | C8: =-C23/C57 -> 0.22465438 | D8: =-D23/D57 -> 0.21452894 | E8: =-E23/E57 -> 0.25090036 | F8: =-F23/F57 -> 0.25031928 | G8: =-G23/G57 -> 0.36173121
B9: Interest (% of Debt) | C9: =-C30/(C71+C75) -> 0.055677904 | D9: =-D30/(D71+D75) -> 0.058752998 | E9: =-E30/(E71+E75) -> 0.063005068 | F9: =-F30/(F71+F75) -> 0.059306255 | G9: =-G30/(G71+G75) -> 0.064577537
B10: Accounts Receivable (Days) | C10: =C52/C19*365 -> 89.175121 | D10: =D52/D19*365 -> 89.718777 | E10: =E52/E19*365 -> 87.581782 | F10: =F52/F19*365 -> 86.461507 | G10: =G52/G19*365 -> 83.571874
B11: Inventory (Days) | C11: =C53/-C20*365 -> 30.937782 | D11: =D53/-D20*365 -> 24.682792 | E11: =E53/-E20*365 -> 25.783584 | F11: =F53/-F20*365 -> 26.834645 | G11: =G53/-G20*365 -> 27.076161
B12: Accounts Payable (Days) | C12: =C66/-C20*365 -> 16.456267 | D12: =D66/-D20*365 -> 25.804737 | E12: =E66/-E20*365 -> 20.057951 | F12: =F66/-F20*365 -> 17.896023 | G12: =G66/-G20*365 -> 16.790556
B13: CAPEX | C13: =C119 -> -354 | D13: =D119 -> -358 | E13: =E119 -> -328 | F13: =F119 -> -263 | G13: =G119 -> -296
B14: Tax Rate | C14: =-C36/C35 -> 0.12408759 | D14: =-D36/D35 -> 0.1793049 | E14: =-E36/E35 -> 0.28810854 | F14: =-F36/F35 -> 0.04937672 | G14: =G36/G35 -> 4.25
C17: 2021A | D17: 2022A | E17: 2023A | F17: 2024A | G17: 2025A*
B18: Income Statement
B19: Revenues | C19: 28586 | D19: 30154 | E19: 29652 | F19: 29213 | G19: 28891
B20: Operating expenses | C20: -17744 | D20: -19845 | E20: -20017 | F20: -19437 | G20: -19695
B21: Programming charges | C21: 0 | D21: 0 | E21: -2371 | F21: -1118 | G21: -41
B22: Selling, general and administrative | C22: -6398 | D22: -7033 | E22: -7245 | F22: -6658 | G22: -6120
B23: Depreciation and amortization | C23: -390 | D23: -378 | E23: -418 | F23: -392 | G23: -794
B24: Impairment charges | C24: 0 | D24: -27 | E24: -83 | F24: -6130 | G24: -157
B25: Restructuring, transaction-related and other corporate matters | C25: -100 | D25: -585 | E25: 31 | F25: -747 | G25: -1185
B26: Total costs and expenses | C26: =SUM(C20:C25) -> -24632 | D26: =SUM(D20:D25) -> -27868 | E26: =SUM(E20:E25) -> -30103 | F26: =SUM(F20:F25) -> -34482 | G26: =SUM(G20:G25) -> -27992
B27: Gain on dispositions | C27: 2343 | D27: 56 | E27: 0 | F27: 0 | G27: 35
B28: Operating income (loss) | C28: =C19+C26+C27 -> 6297 | D28: =D19+D26+D27 -> 2342 | E28: =E19+E26+E27 -> -451 | F28: =F19+F26+F27 -> -5269 | G28: =G19+G26+G27 -> 934
B29: Operating margin | C29: =C28/C19 -> 0.22028266 | D29: =D28/D19 -> 0.077667971 | E29: =E28/E19 -> -0.015209767 | F29: =F28/F19 -> -0.18036491 | G29: =G28/G19 -> 0.032328407
B30: Interest expense | C30: -986 | D30: -931 | E30: -920 | F30: -860 | G30: -882
B31: Interest income | C31: 53 | D31: 108 | E31: 137 | F31: 151 | G31: 147
B32: Gain (loss) from investments | C32: 47 | D32: -9 | E32: 168 | F32: -17 | G32: -40
B33: Gain (loss) on extinguishment of debt | C33: -128 | D33: -120 | E33: 29 | F33: 0 | G33: 0
B34: Other items, net | C34: -77 | D34: -124 | E34: -216 | F34: -182 | G34: -131
B35: Pretax income (loss) | C35: =SUM(C28,C30:C34) -> 5206 | D35: =SUM(D28,D30:D34) -> 1266 | E35: =SUM(E28,E30:E34) -> -1253 | F35: =SUM(F28,F30:F34) -> -6177 | G35: =SUM(G28,G30:G34) -> 28
B36: Benefit from (provision for) income taxes | C36: -646 | D36: -227 | E36: 361 | F36: 305 | G36: 119
B37: Equity in loss of investee companies, net of tax | C37: -91 | D37: -204 | E37: -360 | F37: -291 | G37: -275
B38: Net earnings (loss) from continuing operations | C38: =SUM(C35:C37) -> 4469 | D38: =SUM(D35:D37) -> 835 | E38: =SUM(E35:E37) -> -1252 | F38: =SUM(F35:F37) -> -6163 | G38: =SUM(G35:G37) -> -128
B39: Net earnings from discontinued operations, net of tax | C39: 162 | D39: 379 | E39: 676 | F39: 14 | G39: 0
B40: Net earnings (loss) – Parent and NCI | C40: =C38+C39 -> 4631 | D40: =D38+D39 -> 1214 | E40: =E38+E39 -> -576 | F40: =F38+F39 -> -6149 | G40: =G38+G39 -> -128
B41: Net earnings attributable to noncontrolling interests | C41: -88 | D41: -110 | E41: -32 | F41: -41 | G41: -493
B42: Net earnings (loss) attributable to Parent | C42: =C40+C41 -> 4543 | D42: =D40+D41 -> 1104 | E42: =E40+E41 -> -608 | F42: =F40+F41 -> -6190 | G42: =G40+G41 -> -621
B43: Net margin | C43: =C42/C19 -> 0.15892395 | D43: =D42/D19 -> 0.036612058 | E43: =E42/E19 -> -0.020504519 | F43: =F42/F19 -> -0.21189197 | G43: =G42/G19 -> -0.021494583
B44: Basic EPS | C44: 7.02 | D44: 1.61 | E44: -1.02 | F44: -9.34
B45: Diluted EPS | C45: 6.94 | D45: 1.61 | E45: -1.02 | F45: -9.34
B46: Basic weighted-average shares | C46: 641 | D46: 649 | E46: 652 | F46: 664 | G46: 1102
B47: Diluted weighted-average shares | C47: 655 | D47: 650 | E47: 652 | F47: 664 | G47: 1102
B50: Balance Sheet
B51: Cash and cash equivalents | C51: 6267 | D51: 2885 | E51: 2460 | F51: 2661 | G51: 3274
B52: Receivables, net | C52: 6984 | D52: 7412 | E52: 7115 | F52: 6920 | G52: 6615
B53: Programming and other inventory – current | C53: 1504 | D53: 1342 | E53: 1414 | F53: 1429 | G53: 1461
B54: Prepaid expenses and other current assets | C54: 1176 | D54: 1308 | E54: 1677 | F54: 1532 | G54: 1970
B55: Current assets of discontinued operations | C55: 745 | D55: 787 | E55: 37 | F55: 0 | G55: 0
B56: Total current assets | C56: =SUM(C51:C55) -> 16676 | D56: =SUM(D51:D55) -> 13734 | E56: =SUM(E51:E55) -> 12703 | F56: =SUM(F51:F55) -> 12542 | G56: =SUM(G51:G55) -> 13320
B57: Property and equipment, net | C57: 1736 | D57: 1762 | E57: 1666 | F57: 1566 | G57: 2195
B58: Programming and other inventory – non-current | C58: 13358 | D58: 16278 | E58: 13851 | F58: 13924 | G58: 15028
B59: Goodwill | C59: 16584 | D59: 16499 | E59: 16516 | F59: 10508 | G59: 1600
B60: Intangible assets, net | C60: 2772 | D60: 2694 | E60: 2589 | F60: 2406 | G60: 6238
B61: Operating lease assets | C61: 1630 | D61: 1391 | E61: 1183 | F61: 1012 | G61: 1126
B62: Deferred income tax assets, net | C62: 1206 | D62: 1242 | E62: 1242 | F62: 1386 | G62: 1282
B63: Other assets | C63: 3824 | D63: 3991 | E63: 3793 | F63: 2828 | G63: 2553
B64: Assets held for sale / discontinued operations | C64: 834 | D64: 802 | E64: 0 | F64: 0 | G64: 0
B65: Total assets | C65: =SUM(C56,C57:C64) -> 58620 | D65: =SUM(D56,D57:D64) -> 58393 | E65: =SUM(E56,E57:E64) -> 53543 | F65: =SUM(F56,F57:F64) -> 46172 | G65: =SUM(G56,G57:G64) -> 43342
B66: Accounts payable | C66: 800 | D66: 1403 | E66: 1100 | F66: 953 | G66: 906
B67: Accrued expenses | C67: 2323 | D67: 2071 | E67: 2104 | F67: 2199 | G67: 2077
B68: Participants' share and royalties payable – current | C68: 2159 | D68: 2416 | E68: 2702 | F68: 2574 | G68: 2646
B69: Accrued programming and production costs | C69: 1342 | D69: 2063 | E69: 1842 | F69: 1720 | G69: 1832
B70: Deferred revenues | C70: 1091 | D70: 973 | E70: 746 | F70: 825 | G70: 1355
B71: Current debt | C71: 11 | D71: 239 | E71: 1 | F71: 0 | G71: 433
B72: Other current liabilities | C72: 1182 | D72: 1477 | E72: 1153 | F72: 1360 | G72: 1350
B73: Current liabilities of discontinued operations | C73: 571 | D73: 549 | E73: 8 | F73: 0 | G73: 0
B74: Total current liabilities | C74: =SUM(C66:C73) -> 9479 | D74: =SUM(D66:D73) -> 11191 | E74: =SUM(E66:E73) -> 9656 | F74: =SUM(F66:F73) -> 9631 | G74: =SUM(G66:G73) -> 10599
B75: Long-term debt | C75: 17698 | D75: 15607 | E75: 14601 | F75: 14501 | G75: 13225
B76: Participants' share and royalties payable – non-current | C76: 1244 | D76: 1744 | E76: 1394 | F76: 1310 | G76: 1361
B77: Pension and postretirement benefit obligations | C77: 1946 | D77: 1458 | E77: 1337 | F77: 1226 | G77: 1185
B78: Deferred income tax liabilities, net | C78: 1063 | D78: 1077 | E78: 503 | F78: 34 | G78: 85
B79: Operating lease liabilities | C79: 1598 | D79: 1428 | E79: 1256 | F79: 1048 | G79: 1150
B80: Programming obligations | C80: 404 | D80: 367 | E80: 204 | F80: 260 | G80: 400
B81: Other liabilities | C81: 1898 | D81: 1715 | E81: 1534 | F81: 1380 | G81: 2450
B82: Liabilities of discontinued operations | C82: 213 | D82: 200 | E82: 8 | F82: 0 | G82: 0
B83: Redeemable noncontrolling interest | C83: 107 | D83: 0 | E83: 0 | F83: 0 | G83: 0
B84: Total liabilities | C84: =SUM(C74,C75:C83) -> 35650 | D84: =SUM(D74,D75:D83) -> 34787 | E84: =SUM(E74,E75:E83) -> 30493 | F84: =SUM(F74,F75:F83) -> 29390 | G84: =SUM(G74,G75:G83) -> 30455
B85: Common stock | C85: 1 | D85: 1 | E85: 1 | F85: 1 | G85: 1
B86: Additional paid-in capital | C86: 32918 | D86: 33063 | E86: 33210 | F86: 33394 | G86: 13386
B87: Treasury stock | C87: -22958 | D87: -22958 | E87: -22958 | F87: -22958 | G87: 0
B88: Retained earnings (accumulated deficit) | C88: 14343 | D88: 14737 | E88: 13829 | F88: 7487 | G88: -1753
B89: Accumulated other comprehensive income (loss) | C89: -1902 | D89: -1807 | E89: -1556 | F89: -1604 | G89: 59
B90: Total Parent stockholders' equity | C90: =SUM(C85:C89) -> 22402 | D90: =SUM(D85:D89) -> 23036 | E90: =SUM(E85:E89) -> 22526 | F90: =SUM(F85:F89) -> 16320 | G90: =SUM(G85:G89) -> 11693
B91: Noncontrolling interests | C91: 568 | D91: 570 | E91: 524 | F91: 462 | G91: 1194
B92: Total equity | C92: =C90+C91 -> 22970 | D92: =D90+D91 -> 23606 | E92: =E90+E91 -> 23050 | F92: =F90+F91 -> 16782 | G92: =G90+G91 -> 12887
B93: Total liabilities and equity | C93: =C84+C92 -> 58620 | D93: =D84+D92 -> 58393 | E93: =E84+E92 -> 53543 | F93: =F84+F92 -> 46172 | G93: =G84+G92 -> 43342
B94: Balance sheet check | C94: =C65-C93 -> 0 | D94: =D65-D93 -> 0 | E94: =E65-E93 -> 0 | F94: =F65-F93 -> 0 | G94: =G65-G93 -> 0
B97: Cash Flow Statement
B98: Net earnings (loss) – continuing operations | C98: 4469 | D98: 835 | E98: -1252 | F98: -6163 | G98: -128
B99: Programming charges | C99: 0 | D99: 0 | E99: 2371 | F99: 1118 | G99: 41
B100: Depreciation and amortization | C100: 390 | D100: 378 | E100: 418 | F100: 392 | G100: 794
B101: Impairment charges | C101: 0 | D101: 27 | E101: 83 | F101: 6130 | G101: 157
B102: Amortization of content costs and participation and residuals | C102: 13649 | D102: 14951 | E102: 14713 | F102: 13888 | G102: 14071
B103: Deferred tax benefit (provision) | C103: 90 | D103: -106 | E103: -650 | F103: -630 | G103: -516
B104: Stock-based compensation | C104: 192 | D104: 172 | E104: 177 | F104: 245 | G104: 273
B105: Gain on dispositions | C105: -2343 | D105: -56 | E105: 0 | F105: 0 | G105: -35
B106: (Gain) loss from investments | C106: -47 | D106: 9 | E106: -168 | F106: 17 | G106: 40
B107: (Gain) loss on extinguishment of debt | C107: 128 | D107: 120 | E107: -29 | F107: 0 | G107: 0
B108: Equity in loss of investee companies, net of tax and distributions | C108: 96 | D108: 207 | E108: 363 | F108: 304 | G108: 284
...

Sheet Forecast
D2: Historical Period | I2: Forecast Period
D3: 2021 | E3: 2022 | F3: 2023 | G3: 2024 | H3: 2025 | I3: 2026 | J3: 2027 | K3: 2028 | L3: 2029 | M3: 2030
B4: Income Statement
B5: Revenues | D5: 28586 | E5: 30154 | F5: 29652 | G5: 29213 | H5: 28891 | I5: =H5*(1+Assumptions!C7) -> 29244.815 | J5: =I5*(1+Assumptions!D7) -> 29850.199 | K5: =J5*(1+Assumptions!E7) -> 30577.804 | L5: =K5*(1+Assumptions!F7) -> 31474.798 | M5: =L5*(1+Assumptions!G7) -> 32473.32
B6: Operating expenses | D6: -17744 | E6: -19845 | F6: -20017 | G6: -19437 | H6: -19695 | I6: =H6*(1+Assumptions!C8) -> -20088.9 | J6: =I6*(1+Assumptions!D8) -> -21093.345 | K6: =J6*(1+Assumptions!E8) -> -21831.612 | L6: =K6*(1+Assumptions!F8) -> -22268.244 | M6: =L6*(1+Assumptions!G8) -> -22713.609
B7: Programming charges | D7: 0 | E7: 0 | F7: -2371 | G7: -1118 | H7: -41 | I7: =H7*(1+Assumptions!C9) -> -42.23 | J7: =I7*(1+Assumptions!D9) -> -43.9192 | K7: =J7*(1+Assumptions!E9) -> -46.11516 | L7: =K7*(1+Assumptions!F9) -> -48.420918 | M7: =L7*(1+Assumptions!G9) -> -50.841964
B8: Selling, general and administrative | D8: -6398 | E8: -7033 | F8: -7245 | G8: -6658 | H8: -6120 | I8: =H8*(1+Assumptions!C10) -> -4773.6 | J8: =I8*(1+Assumptions!D10) -> -4487.184 | K8: =J8*(1+Assumptions!E10) -> -4307.6966 | L8: =K8*(1+Assumptions!F10) -> -4113.8503 | M8: =L8*(1+Assumptions!G10) -> -3908.1578
B9: Depreciation and amortization | D9: -390 | E9: -378 | F9: -418 | G9: -392 | H9: -794 | I9: =H9*(1+Assumptions!C11) -> -797.97 | J9: =I9*(1+Assumptions!D11) -> -801.95985 | K9: =J9*(1+Assumptions!E11) -> -805.96965 | L9: =K9*(1+Assumptions!F11) -> -809.9995 | M9: =L9*(1+Assumptions!G11) -> -814.04949
B10: Impairment charges | D10: 0 | E10: -27 | F10: -83 | G10: -6130 | H10: -157 | I10: =H10*(1+Assumptions!C12) -> -133.45 | J10: =I10*(1+Assumptions!D12) -> -106.76 | K10: =J10*(1+Assumptions!E12) -> -80.07 | L10: =K10*(1+Assumptions!F12) -> -56.049 | M10: =L10*(1+Assumptions!G12) -> -36.43185
B11: Restructuring, transaction-related and other corporate matters | D11: -100 | E11: -585 | F11: 31 | G11: -747 | H11: -1185 | I11: =H11*(1+Assumptions!C13) -> -1208.7 | J11: =I11*(1+Assumptions!D13) -> -1112.004 | K11: =J11*(1+Assumptions!E13) -> -1023.0437 | L11: =K11*(1+Assumptions!F13) -> -941.20019 | M11: =L11*(1+Assumptions!G13) -> -865.90417
B12: Total costs and expenses | D12: =SUM(D6:D11) -> -24632 | E12: =SUM(E6:E11) -> -27868 | F12: =SUM(F6:F11) -> -30103 | G12: =SUM(G6:G11) -> -34482 | H12: =SUM(H6:H11) -> -27992 | I12: =SUM(I6:I11) -> -27044.85 | J12: =SUM(J6:J11) -> -27645.172 | K12: =SUM(K6:K11) -> -28094.507 | ... M12: =SUM(M6:M11) -> -28388.994
B13: Gain on dispositions | D13: 2343 | E13: 56 | F13: 0 | G13: 0 | H13: 35 | I13: 0 | J13: 0 | K13: 0 | L13: 0 | M13: 0
B14: Operating income (loss) | D14: =D5+D12+D13 -> 6297 | E14: =E5+E12+E13 -> 2342 | F14: =F5+F12+F13 -> -451 | G14: =G5+G12+G13 -> -5269 | H14: =H5+H12+H13 -> 934 | I14: =I5+I12+I13 -> 2199.965 | J14: =J5+J12+J13 -> 2205.0274 | K14: =K5+K12+K13 -> 2483.2971 | ... M14: =M5+M12+M13 -> 4084.3252
B15: Interest expense | D15: -986 | E15: -931 | F15: -920 | G15: -860 | H15: -882 | I15: =-I99 -> -804.78 | J15: =-J99 -> -774.63 | K15: =-K99 -> -728.16 | L15: =-L99 -> -684.21 | M15: =-M99 -> -642.09
B16: Interest income | D16: 53 | E16: 108 | F16: 137 | G16: 151 | H16: 147 | I16: 130 | J16: 130 | K16: 130 | L16: 130 | M16: 130
B17: Gain (loss) from investments | D17: 47 | E17: -9 | F17: 168 | G17: -17 | H17: -40 | I17: 0 | J17: 0 | K17: 0 | L17: 0 | M17: 0
B18: Gain (loss) on extinguishment of debt | D18: -128 | E18: -120 | F18: 29 | G18: 0 | H18: 0 | I18: 0 | J18: 0 | K18: 0 | L18: 0 | M18: 0
B19: Other items, net | D19: -77 | E19: -124 | F19: -216 | G19: -182 | H19: -131 | I19: =AVERAGE(F19:H19) -> -176.33333 | J19: =AVERAGE(G19:I19) -> -163.11111 | K19: =AVERAGE(H19:J19) -> -156.81481 | L19: =AVERAGE(I19:K19) -> -165.41975 | M19: =AVERAGE(J19:L19) -> -161.78189
B20: Pretax income (loss) | D20: =SUM(D14,D15:D19) -> 5206 | E20: =SUM(E14,E15:E19) -> 1266 | F20: =SUM(F14,F15:F19) -> -1253 | G20: =SUM(G14,G15:G19) -> -6177 | H20: =SUM(H14,H15:H19) -> 28 | I20: =SUM(I14,I15:I19) -> 1348.8517 | J20: =SUM(J14,J15:J19) -> 1397.2863 | K20: =SUM(K14,K15:K19) -> 1728.3223 | ... M20: =SUM(M14,M15:M19) -> 3410.4533
B21: Benefit from (provision for) income taxes | D21: -646 | E21: -227 | F21: 361 | G21: 305 | H21: 119 | I21: =-I20*Assumptions!C19 -> -323.7244 | J21: =-J20*Assumptions!D19 -> -335.3487 | K21: =-K20*Assumptions!E19 -> -414.79735 | L21: =-L20*Assumptions!F19 -> -604.17694 | M21: =-M20*Assumptions!G19 -> -818.5088
B22: Equity in loss of investee companies, net of tax | D22: -91 | E22: -204 | F22: -360 | G22: -291 | H22: -275 | I22: 0 | J22: 0 | K22: 0 | L22: 0 | M22: 0
B23: Net earnings (loss) from continuing operations | D23: =SUM(D20:D22) -> 4469 | E23: =SUM(E20:E22) -> 835 | F23: =SUM(F20:F22) -> -1252 | G23: =SUM(G20:G22) -> -6163 | H23: =SUM(H20:H22) -> -128 | I23: =SUM(I20:I22) -> 1025.1273 | J23: =SUM(J20:J22) -> 1061.9376 | K23: =SUM(K20:K22) -> 1313.5249 | ... M23: =SUM(M20:M22) -> 2591.9445
B24: Net earnings from discontinued operations, net of tax | D24: 162 | E24: 379 | F24: 676 | G24: 14 | H24: 0 | I24: 0 | J24: 0 | K24: 0 | L24: 0 | M24: 0
B25: Net earnings (loss) – Parent and NCI | D25: =D23+D24 -> 4631 | E25: =E23+E24 -> 1214 | F25: =F23+F24 -> -576 | G25: =G23+G24 -> -6149 | H25: =H23+H24 -> -128 | I25: =I23+I24 -> 1025.1273 | J25: =J23+J24 -> 1061.9376 | K25: =K23+K24 -> 1313.5249 | ... M25: =M23+M24 -> 2591.9445
B26: Net earnings attributable to noncontrolling interests | D26: -88 | E26: -110 | F26: -32 | G26: -41 | H26: -493 | I26: -40 | J26: -40 | K26: -40 | L26: -40 | M26: -40
B27: Net earnings (loss) attributable to Parent | D27: =D25+D26 -> 4543 | E27: =E25+E26 -> 1104 | F27: =F25+F26 -> -608 | G27: =G25+G26 -> -6190 | H27: =H25+H26 -> -621 | I27: =I25+I26 -> 985.12727 | J27: =J25+J26 -> 1021.9376 | K27: =K25+K26 -> 1273.5249 | ... M27: =M25+M26 -> 2551.9445
H28: =H9+SUM(H15:H19)+H21+H22 -> -1856
B30: Balance Sheet
B31: Cash | D31: =Historicals!C51 -> 6267 | E31: =Historicals!D51 -> 2885 | F31: =Historicals!E51 -> 2460 | G31: =Historicals!F51 -> 2661 | H31: =Historicals!G51 -> 3274 | I31: =I77 -> 4235.2173 | J31: =J77 -> 5235.7029 | K31: =K77 -> 5964.3603 | L31: =L77 -> 7464.5065 | M31: =M77 -> 9526.7943
B32: Accounts Receivable | D32: =Historicals!C52 -> 6984 | E32: =Historicals!D52 -> 7412 | F32: =Historicals!E52 -> 7115 | G32: =Historicals!F52 -> 6920 | H32: =Historicals!G52 -> 6615 | I32: =I5*Assumptions!C14/365 -> 6880.2811 | J32: =J5*Assumptions!D14/365 -> 6976.0898 | K32: =K5*Assumptions!E14/365 -> 7113.7459 | L32: =L5*Assumptions!F14/365 -> 7361.036 | M32: =M5*Assumptions!G14/365 -> 7579.4697
B33: Inventory | D33: =Historicals!C53 -> 1504 | E33: =Historicals!D53 -> 1342 | F33: =Historicals!E53 -> 1414 | G33: =Historicals!F53 -> 1429 | H33: =Historicals!G53 -> 1461 | I33: =-I6*Assumptions!C15/365 -> 1462.0755 | J33: =-J6*Assumptions!D15/365 -> 1550.228 | K33: =-K6*Assumptions!E15/365 -> 1604.2977 | L33: =-L6*Assumptions!F15/365 -> 1631.216 | M33: =-M6*Assumptions!G15/365 -> 1667.4196
B34: Other current assets | D34: =Historicals!C54+Historicals!C55 -> 1921 | E34: =Historicals!D54+Historicals!D55 -> 2095 | F34: =Historicals!E54+Historicals!E55 -> 1714 | G34: =Historicals!F54+Historicals!F55 -> 1532 | H34: =Historicals!G54+Historicals!G55 -> 1970 | I34: 1900 | J34: 1700 | K34: 1400 | L34: =1800-533.603014306042 -> 1266.397 | M34: =1800-673.709879076729 -> 1126.2901
B35: Total current assets | D35: =SUM(D31:D34) -> 16676 | E35: =SUM(E31:E34) -> 13734 | F35: =SUM(F31:F34) -> 12703 | G35: =SUM(G31:G34) -> 12542 | H35: =SUM(H31:H34) -> 13320 | I35: =SUM(I31:I34) -> 14477.574 | J35: =SUM(J31:J34) -> 15462.021 | K35: =SUM(K31:K34) -> 16082.404 | ... M35: =SUM(M31:M34) -> 19899.974
B36: Property Plant Equipment | D36: =Historicals!C57 -> 1736 | E36: =Historicals!D57 -> 1762 | F36: =Historicals!E57 -> 1666 | G36: =Historicals!F57 -> 1566 | H36: =Historicals!G57 -> 2195 | I36: =I93 -> 1957.1802 | J36: =J93 -> 1835.6776 | K36: =K93 -> 1712.5472 | L36: =L93 -> 1587.8623 | M36: =M93 -> 1461.6939
B37: Other non-current assets | D37: =SUM(Historicals!C58:C64) -> 40208 | E37: =SUM(Historicals!D58:D64) -> 42897 | F37: =SUM(Historicals!E58:E64) -> 39174 | G37: =SUM(Historicals!F58:F64) -> 32064 | H37: =SUM(Historicals!G58:G64) -> 27827 | I37: 28000 | J37: =28000-392.134524000001 -> 27607.865 | K37: =27600-594.257752635 -> 27005.742 | L37: =26500--381.813670546122 -> 26881.814 | M37: =26500+87.9608257905857 -> 26587.961
B38: Total Assets | D38: =D35+SUM(D36:D37) -> 58620 | E38: =E35+SUM(E36:E37) -> 58393 | F38: =F35+SUM(F36:F37) -> 53543 | G38: =G35+SUM(G36:G37) -> 46172 | H38: =H35+SUM(H36:H37) -> 43342 | I38: =I35+SUM(I36:I37) -> 44434.754 | J38: =J35+SUM(J36:J37) -> 44905.564 | K38: =K35+SUM(K36:K37) -> 44800.693 | ... M38: =M35+SUM(M36:M37) -> 47949.628
B40: Liabilities
B41: Accounts Payable | D41: =Historicals!C66 -> 800 | E41: =Historicals!D66 -> 1403 | F41: =Historicals!E66 -> 1100 | G41: =Historicals!F66 -> 953 | H41: =Historicals!G66 -> 906 | I41: =-I6*Assumptions!C16/365 -> 1004.3446 | J41: =-J6*Assumptions!D16/365 -> 1019.6996 | K41: =-K6*Assumptions!E16/365 -> 1050.3827 | L41: =-L6*Assumptions!F16/365 -> 1087.0627 | M41: =-M6*Assumptions!G16/365 -> 1099.883
B42: Current debt | D42: =Historicals!C71 -> 11 | E42: =Historicals!D71 -> 239 | F42: =Historicals!E71 -> 1 | G42: =Historicals!F71 -> 0 | H42: =Historicals!G71 -> 433 | I42: =D105 -> 573 | J42: =D106+D107 -> 976 | K42: =D108 -> 489 | L42: =D109 -> 915 | M42: =D110 -> 1221
B43: Other current liabilities | D43: =SUM(Historicals!C67:C70,Historicals!C72:C73) -> 8668 | E43: =SUM(Historicals!D67:D70,Historicals!D72:D73) -> 9549 | F43: =SUM(Historicals!E67:E70,Historicals!E72:E73) -> 8555 | G43: =SUM(Historicals!F67:F70,Historicals!F72:F73) -> 8678 | H43: =SUM(Historicals!G67:G70,Historicals!G72:G73) -> 9260 | I43: =8700+388.090200000006 -> 9088.0902 | J43: =8500+392.134524000001 -> 8892.1345 | K43: =8200+594.257752635 -> 8794.2578 | L43: =8100+533.6030142 -> 8633.603 | M43: =7700+673.70987907672 -> 8373.7099
B44: Total Current Liabilities | D44: =SUM(D41:D43) -> 9479 | E44: =SUM(E41:E43) -> 11191 | F44: =SUM(F41:F43) -> 9656 | G44: =SUM(G41:G43) -> 9631 | H44: =SUM(H41:H43) -> 10599 | I44: =SUM(I41:I43) -> 10665.435 | J44: =SUM(J41:J43) -> 10887.834 | K44: =SUM(K41:K43) -> 10333.64 | ... M44: =SUM(M41:M43) -> 10694.593
B45: Long-term debt | D45: =Historicals!C75 -> 17698 | E45: =Historicals!D75 -> 15607 | F45: =Historicals!E75 -> 14601 | G45: =Historicals!F75 -> 14501 | H45: =Historicals!G75 -> 13225 | I45: =I98 -> 13197 | J45: =J98 -> 12624 | K45: =K98 -> 11648 | L45: =L98 -> 11159 | M45: =M98 -> 10244
B46: Other non-current liabilities | D46: =SUM(Historicals!C76:C83) -> 8473 | E46: =SUM(Historicals!D76:D83) -> 7989 | F46: =SUM(Historicals!E76:E83) -> 6236 | G46: =SUM(Historicals!F76:F83) -> 5258 | H46: =SUM(Historicals!G76:G83) -> 6631 | I46: 6400 | J46: 6300 | K46: =6350-0.156986242909625 -> 6349.843 | L46: =5400+533.6030142 -> 5933.603 | M46: =5200+673.709879076729 -> 5873.7099
B47: Total Liabilities | D47: =SUM(D44:D46) -> 35650 | E47: =SUM(E44:E46) -> 34787 | F47: =SUM(F44:F46) -> 30493 | G47: =SUM(G44:G46) -> 29390 | H47: =SUM(H44:H46) -> 30455 | I47: =SUM(I44:I46) -> 30262.435 | J47: =SUM(J44:J46) -> 29811.834 | K47: =SUM(K44:K46) -> 28331.483 | ... M47: =SUM(M44:M46) -> 26812.303
B48: Shareholders Equity
B49: Equity Capital | D49: =Historicals!C85+Historicals!C86+Historicals!C87+Historicals!C89 -> 8059 | E49: =Historicals!D85+Historicals!D86+Historicals!D87+Historicals!D89 -> 8299 | F49: =Historicals!E85+Historicals!E86+Historicals!E87+Historicals!E89 -> 8697 | G49: =Historicals!F85+Historicals!F86+Historicals!F87+Historicals!F89 -> 8833 | H49: =Historicals!G85+Historicals!G86+Historicals!G87+Historicals!G89 -> 13446 | I49: =SUM(Assumptions!C24:C27) -> 13446 | J49: =SUM(Assumptions!D24:D27) -> 13946 | K49: =SUM(Assumptions!E24:E27) -> 13946 | L49: =SUM(Assumptions!F24:F27) -> 13946 | M49: =SUM(Assumptions!G24:G27) -> 13946
B50: Retained Earnings | D50: =Historicals!C88 -> 14343 | E50: =Historicals!D88 -> 14737 | F50: =Historicals!E88 -> 13829 | G50: =Historicals!F88 -> 7487 | H50: =Historicals!G88 -> -1753 | I50: =H50+I27-Assumptions!C21 -> -635.07273 | J50: =I50+J27-Assumptions!D21 -> 519.66483 | K50: =J50+K27-Assumptions!E21 -> 1925.9898 | L50: =K50+L27-Assumptions!F21 -> 3932.0168 | M50: =L50+M27-Assumptions!G21 -> 6616.7613
B51: Noncontrolling interests | D51: =Historicals!C91 -> 568 | E51: =Historicals!D91 -> 570 | F51: =Historicals!E91 -> 524 | G51: =Historicals!F91 -> 462 | H51: =Historicals!G91 -> 1194 | I51: =1365.87945709281-4.48755717476888 -> 1361.3919 | J51: =628.163925773566-0.0990715984371491 -> 628.06485 | K51: =600-2.77985652223288 -> 597.22014 | L51: =600-13.454085881247 -> 586.54591 | M51: =600-25.435546424771 -> 574.56445
B52: Shareholders Equity | D52: =SUM(D49:D51) -> 22970 | E52: =SUM(E49:E51) -> 23606 | F52: =SUM(F49:F51) -> 23050 | G52: =SUM(G49:G51) -> 16782 | H52: =SUM(H49:H51) -> 12887 | I52: =SUM(I49:I51) -> 14172.319 | J52: =SUM(J49:J51) -> 15093.73 | K52: =SUM(K49:K51) -> 16469.21 | ... M52: =SUM(M49:M51) -> 21137.326
B53: Total Liabilities and Equities | D53: =D52+D47 -> 58620 | E53: =E52+E47 -> 58393 | F53: =F52+F47 -> 53543 | G53: =G52+G47 -> 46172 | H53: =H52+H47 -> 43342 | I53: =I52+I47 -> 44434.754 | J53: =J52+J47 -> 44905.564 | K53: =K52+K47 -> 44800.693 | ... M53: =M52+M47 -> 47949.628
B54: Balance Check | D54: =D38-D53 -> 0 | E54: =E38-E53 -> 0 | F54: =F38-F53 -> 0 | G54: =G38-G53 -> 0 | H54: =H38-H53 -> 0 | I54: =I38-I53 -> 0 | J54: =J38-J53 -> 0 | K54: =K38-K53 -> 0 | ... M54: =M38-M53 -> 0
B57: Cash Flow
B58: Net Earnings | D58: =Historicals!C98 -> 4469 | E58: =Historicals!D98 -> 835 | F58: =Historicals!E98 -> -1252 | G58: =Historicals!F98 -> -6163 | H58: =Historicals!G98 -> -128 | I58: =I25 -> 1025.1273 | J58: =J25 -> 1061.9376 | K58: =K25 -> 1313.5249 | L58: =L25 -> 1913.227 | M58: =M25 -> 2591.9445
B59: Depreciation & Amortisation | D59: =Historicals!C100 -> 390 | E59: =Historicals!D100 -> 378 | F59: =Historicals!E100 -> 418 | G59: =Historicals!F100 -> 392 | H59: =Historicals!G100 -> 794 | I59: =-I9 -> 797.97 | J59: =-J9 -> 801.95985 | K59: =-K9 -> 805.96965 | L59: =-L9 -> 809.9995 | M59: =-M9 -> 814.04949
B60: Other operating cash flow | D60: =SUM(Historicals!C99,Historicals!C101:C114,Historicals!C116) -> -3906 | E60: =SUM(Historicals!D99,Historicals!D101:D114,Historicals!D116) -> -994 | F60: =SUM(Historicals!E99,Historicals!E101:E114,Historicals!E116) -> 1309 | G60: =SUM(Historicals!F99,Historicals!F101:F114,Historicals!F116) -> 6523 | H60: =SUM(Historicals!G99,Historicals!G101:G114,Historicals!G116) -> -17 | I60: 300 | J60: 260 | K60: 120 | L60: -100 | M60: -400
B61: Cash from Operations | D61: =SUM(D58:D60) -> 953 | E61: =SUM(E58:E60) -> 219 | F61: =SUM(F58:F60) -> 475 | G61: =SUM(G58:G60) -> 752 | H61: =SUM(H58:H60) -> 649 | I61: =SUM(I58:I60) -> 2123.0973 | J61: =SUM(J58:J60) -> 2123.8974 | K61: =SUM(K58:K60) -> 2239.4946 | ... M61: =SUM(M58:M60) -> 3005.994
B63: Investing Cash Flow
B64: Investment in Property & Equipment | D64: =Historicals!C119 -> -354 | E64: =Historicals!D119 -> -358 | F64: =Historicals!E119 -> -328 | G64: =Historicals!F119 -> -263 | H64: =Historicals!G119 -> -296 | I64: =H64*(1+Assumptions!C17) -> -290.08 | J64: =I64*(1+Assumptions!D17) -> -284.2784 | K64: =J64*(1+Assumptions!E17) -> -278.59283 | L64: =K64*(1+Assumptions!F17) -> -273.02098 | M64: =L64*(1+Assumptions!G17) -> -267.56056
B65: Other investing cash flow | D65: =SUM(Historicals!C118,Historicals!C120:C122,Historicals!C124) -> 2749 | E65: =SUM(Historicals!D118,Historicals!D120:D122,Historicals!D124) -> -168 | F65: =SUM(Historicals!E118,Historicals!E120:E122,Historicals!E124) -> 1270 | G65: =SUM(Historicals!F118,Historicals!F120:F122,Historicals!F124) -> 275 | H65: =SUM(Historicals!G118,Historicals!G120:G122,Historicals!G124) -> -140 | I65: -50 | J65: 50 | K65: 50 | L65: -50 | M65: 550
B66: Cash from Investing | D66: =SUM(D64:D65) -> 2395 | E66: =SUM(E64:E65) -> -526 | F66: =SUM(F64:F65) -> 942 | G66: =SUM(G64:G65) -> 12 | H66: =SUM(H64:H65) -> -436 | I66: =SUM(I64:I65) -> -340.08 | J66: =SUM(J64:J65) -> -234.2784 | K66: =SUM(K64:K65) -> -228.59283 | ... M66: =SUM(M64:M65) -> 282.43944
B68: Financing Cash Flow
B69: Issuance (repayment) of debt | D69: =SUM(Historicals!C126:C128) -> -2172 | E69: =SUM(Historicals!D126:D128) -> -2002 | F69: =SUM(Historicals!E126:E128) -> -1232 | G69: =SUM(Historicals!F126:F128) -> -126 | H69: =SUM(Historicals!G126:G128) -> -720 | I69: =I97 -> -432 | J69: =J97 -> -573 | K69: =K97 -> -976 | L69: =L97 -> -489 | M69: =M97 -> -915
B70: Issuance (repayment) of equity | D70: =SUM(Historicals!C129:C132) -> 2008 | E70: =SUM(Historicals!D129:D132) -> -689 | F70: =SUM(Historicals!E129:E132) -> -447 | G70: =SUM(Historicals!F129:F132) -> -168 | H70: =SUM(Historicals!G129:G132) -> -191 | I70: =Assumptions!C21 -> -132.8 | J70: =Assumptions!D21 -> -132.8 | K70: =Assumptions!E21 -> -132.8 | L70: =Assumptions!F21 -> -132.8 | M70: =Assumptions!G21 -> -132.8
B71: Other financing cash flow | D71: =SUM(Historicals!C133:C136) -> 12 | E71: =SUM(Historicals!D133:D136) -> -290 | F71: =SUM(Historicals!E133:E136) -> -162 | G71: =SUM(Historicals!F133:F136) -> -213 | H71: =SUM(Historicals!G133:G136) -> -159 | I71: =AVERAGE(F71:H71) -> -178 | J71: =AVERAGE(G71:I71) -> -183.33333 | K71: =AVERAGE(H71:J71) -> -173.44444 | L71: =AVERAGE(I71:K71) -> -178.25926 | M71: =AVERAGE(J71:L71) -> -178.34568
B72: Cash from Financing | D72: =SUM(D69:D71) -> -152 | E72: =SUM(E69:E71) -> -2981 | F72: =SUM(F69:F71) -> -1841 | G72: =SUM(G69:G71) -> -507 | H72: =SUM(H69:H71) -> -1070 | I72: =SUM(I69:I71) -> -742.8 | J72: =SUM(J69:J71) -> -889.13333 | K72: =SUM(K69:K71) -> -1282.2444 | ... M72: =SUM(M69:M71) -> -1226.1457
B74: Net Increase (decrease) in Cash | D74: =SUM(D61,D66,D72) -> 3196 | E74: =SUM(E61,E66,E72) -> -3288 | F74: =SUM(F61,F66,F72) -> -424 | G74: =SUM(G61,G66,G72) -> 257 | H74: =SUM(H61,H66,H72) -> -857 | I74: =SUM(I61,I66,I72) -> 1040.2173 | J74: =SUM(J61,J66,J72) -> 1000.4857 | K74: =SUM(K61,K66,K72) -> 728.65732 | ... M74: =SUM(M61,M66,M72) -> 2062.2878
B75: Opening Cash Balance | D75: =Historicals!C140 -> 3119 | E75: =Historicals!D140 -> 6267 | F75: =Historicals!E140 -> 2885 | G75: =Historicals!F140 -> 2460 | H75: =Historicals!G140 -> 2661 | I75: =H77 -> 3195 | J75: =I77 -> 4235.2173 | K75: =J77 -> 5235.7029 | L75: =K77 -> 5964.3603 | M75: =L77 -> 7464.5065
B76: Merger / purchase accounting cash reset | D76: =Historicals!C141 -> 0 | E76: =Historicals!D141 -> 0 | F76: =Historicals!E141 -> 0 | G76: =Historicals!F141 -> 0 | H76: =Historicals!G141 -> 1391 | I76: 0 | J76: 0 | K76: 0 | L76: 0 | M76: 0
B77: Closing Cash Balance | D77: =SUM(D74:D76) -> 6315 | E77: =SUM(E74:E76) -> 2979 | F77: =SUM(F74:F76) -> 2461 | G77: =SUM(G74:G76) -> 2717 | H77: =SUM(H74:H76) -> 3195 | I77: =SUM(I74:I76) -> 4235.2173 | J77: =SUM(J74:J76) -> 5235.7029 | K77: =SUM(K74:K76) -> 5964.3603 | ... M77: =SUM(M74:M76) -> 9526.7943
B78: Cash balance | D78: =D74+D75+D76-D77 -> 0 | E78: =E74+E75+E76-E77 -> 0 | F78: =F74+F75+F76-F77 -> 0 | G78: =G74+G75+G76-G77 -> 0 | H78: =H74+H75+H76-H77 -> 0 | I78: =I74+I75+I76-I77 -> 0 | J78: =J74+J75+J76-J77 -> 0 | K78: =K74+K75+K76-K77 -> 0 | ... M78: =M74+M75+M76-M77 -> 0
B81: Supporting Schedule
B82: Working Capital Schedule
B83: Accounts Receivable | D83: =D32 -> 6984 | E83: =E32 -> 7412 | F83: =F32 -> 7115 | G83: =G32 -> 6920 | H83: =H32 -> 6615 | I83: =I32 -> 6880.2811 | J83: =J32 -> 6976.0898 | K83: =K32 -> 7113.7459 | ... M83: =M32 -> 7579.4697
B84: Inventory | D84: =D33 -> 1504 | E84: =E33 -> 1342 | F84: =F33 -> 1414 | G84: =G33 -> 1429 | H84: =H33 -> 1461 | I84: =I33 -> 1462.0755 | J84: =J33 -> 1550.228 | K84: =K33 -> 1604.2977 | ... M84: =M33 -> 1667.4196
B85: Accounts Payable | D85: =D41 -> 800 | E85: =E41 -> 1403 | F85: =F41 -> 1100 | G85: =G41 -> 953 | H85: =H41 -> 906 | I85: =I41 -> 1004.3446 | J85: =J41 -> 1019.6996 | K85: =K41 -> 1050.3827 | ... M85: =M41 -> 1099.883
B86: Net Working Capital (NWC) | D86: =D83+D84-D85 -> 7688 | E86: =E83+E84-E85 -> 7351 | F86: =F83+F84-F85 -> 7429 | G86: =G83+G84-G85 -> 7396 | H86: =H83+H84-H85 -> 7170 | I86: =I83+I84-I85 -> 7338.0119 | J86: =J83+J84-J85 -> 7506.6182 | K86: =K83+K84-K85 -> 7667.6609 | ... M86: =M83+M84-M85 -> 8147.0063
B87: Change in NWC | D87: =D86-C86 -> 7688 | E87: =E86-D86 -> -337 | F87: =F86-E86 -> 78 | G87: =G86-F86 -> -33 | H87: =H86-G86 -> -226 | I87: =I86-H86 -> 168.0119 | J87: =J86-I86 -> 168.60629 | K87: =K86-J86 -> 161.04275 | ... M87: =M86-L86 -> 241.81706
B89: Depreciation Schedule
B90: PPE Opening | D90: =1736-354+390 -> 1772 | E90: =D93 -> 1736.39 | F90: =E93 -> 1761.75 | G90: =F93 -> 1671.75 | H90: =H36 -> 2195 | I90: =H93 -> 2076.98 | J90: =I93 -> 1957.1802 | K90: =J93 -> 1835.6776 | L90: =K93 -> 1712.5472 | M90: =L93 -> 1587.8623
B91: Plus Capex | D91: =-D64 -> 354 | E91: =-E64 -> 358 | F91: =-F64 -> 328 | G91: =-G64 -> 263 | H91: =-H64 -> 296 | I91: =-I64 -> 290.08 | J91: =-J64 -> 284.2784 | K91: =-K64 -> 278.59283 | ... M91: =-M64 -> 267.56056
B92: Less Depreciation | D92: =D59*99.9% -> 389.61 | E92: =E59*88% -> 332.64 | F92: =-F9 -> 418 | G92: =G59*94% -> 368.48 | H92: =-'2025 Reported Bridge'!C7*70%-'2025 Reported Bridge'!B7*0.5% -> 414.02 | I92: =H92*(1+-1%) -> 409.8798 | J92: =I92*(1+-1%) -> 405.781 | K92: =J92*(1+-1%) -> 401.72319 | L92: =K92*(1+-1%) -> 397.70596 | M92: =L92*(1+-1%) -> 393.7289
B93: PPE Closing | D93: =D90+D91-D92 -> 1736.39 | E93: =E90+E91-E92 -> 1761.75 | F93: =F90+F91-F92 -> 1671.75 | G93: =G90+G91-G92 -> 1566.27 | H93: =H90+H91-H92 -> 2076.98 | I93: =I90+I91-I92 -> 1957.1802 | J93: =J90+J91-J92 -> 1835.6776 | K93: =K90+K91-K92 -> 1712.5472 | ... M93: =M90+M91-M92 -> 1461.6939
B95: Debt & Interest Schedule
B96: Debt Opening | D96: =D98-D97 -> 19881 | E96: =D98 -> 17709 | F96: =E98 -> 15707 | G96: =F98 -> 14475 | H96: =G98 -> 14349 | I96: =H98 -> 13629 | J96: =I98 -> 13197 | K96: =J98 -> 12624 | L96: =K98 -> 11648 | M96: =L98 -> 11159
B97: Issuance (repayment) | D97: =D69 -> -2172 | E97: =E69 -> -2002 | F97: =F69 -> -1232 | G97: =G69 -> -126 | H97: =H69 -> -720 | I97: =-(D103+D104) -> -432 | J97: =-D105 -> -573 | K97: =-(D106+D107) -> -976 | L97: =-D108 -> -489 | M97: =-D109 -> -915
B98: Debt Closing | D98: =D45+D42 -> 17709 | E98: =SUM(E96:E97) -> 15707 | F98: =SUM(F96:F97) -> 14475 | G98: =SUM(G96:G97) -> 14349 | H98: =SUM(H96:H97) -> 13629 | I98: =SUM(I96:I97) -> 13197 | J98: =SUM(J96:J97) -> 12624 | K98: =SUM(K96:K97) -> 11648 | L98: =SUM(L96:L97) -> 11159 | M98: =SUM(M96:M97) -> 10244
B99: Interest Expense | D99: =-D15 -> 986 | E99: =-E15 -> 931 | F99: =-F15 -> 920 | G99: =-G15 -> 860 | H99: =-H15 -> 882 | I99: =AVERAGE(I96,I98)*Assumptions!C18 -> 804.78 | J99: =AVERAGE(J96,J98)*Assumptions!D18 -> 774.63 | K99: =AVERAGE(K96,K98)*Assumptions!E18 -> 728.16 | L99: =AVERAGE(L96,L98)*Assumptions!F18 -> 684.21 | M99: =AVERAGE(M96,M98)*Assumptions!G18 -> 642.09
B101: Debt
B102: Outstanding as of 2025
B103: 4.0% Senior Notes due 2026 | D103: 347
B104: 3.70% (2024) and 3.45% (2023) Senior Notes due 2026 | D104: 85
B105: 2.90% Senior Notes due 2027 | D105: 573
B106: 3.375% Senior Notes due 2028 | D106: 487
B107: 3.70% Senior Notes due 2028 | D107: 489
B108: 4.20% Senior Notes due 2029 | D108: 489
B109: 7.875% Senior Debentures due 2030 | D109: 915
B110: 4.95% Senior Notes due 2031 | D110: 1221
B111: 4.20% Senior Notes due 2032 | D111: 921
B112: 5.50% Senior Debentures due 2033 | D112: 417
B113: 4.85% Senior Debentures due 2034 | D113: 76
...

Sheet Assumptions
B3: Assumptions | C3: 2026 | D3: 2027 | E3: 2028 | F3: 2029 | G3: 2030 | H3: Rationale | J3: 2024 | K3: 2025 | L3: Growth Rate
B4: TV Media | C4: -0.03 | D4: -0.03 | E4: -0.03 | F4: -0.03 | G4: -0.03 | H4: To experience a steady decline as the whole sector is experiencing a linear cord-cutting process for TV Media, reducing the legacy of paid TV. | J4: 19450 | K4: 18780 | L4: =K4/J4-1 -> -0.034447301
B5: Streaming | C5: 0.1 | D5: 0.12 | E5: 0.13 | F5: 0.145 | G5: 0.15 | H5: Direct-to-Consumer will continue to be Paramounts primary top-line growth driver driven by pice increases, global tech consolidating and a content injection of $1.5bn investment in increments. Content such as UFC and foundationsal franches such as Star Trek. | J5: 7560 | K5: 7630 | L5: =K5/J5-1 -> 0.0092592593
B6: Film & TV Production | C6: 0.05 | D6: 0.08 | E6: 0.09 | F6: 0.1 | G6: 0.11 | H6: Following the acquisition of Skydance's IP, Pararmount can expect to experience a major volume expansion long-term. Short-term there may be headwinds due to tough YoY box office comparions, however production is expected to release at least 15 film major releases annually and 40 active TV shows by 2030 | J6: 2940 | K6: 3280 | L6: =K6/J6-1 -> 0.11564626
B7: Revenue | C7: =SUMPRODUCT($K$4:$K$6,C4:C6)/SUM($K$4:$K$6) -> 0.012246548 | D7: =SUMPRODUCT($K$4:$K$6,D4:D6)/SUM($K$4:$K$6) -> 0.020700573 | E7: =SUMPRODUCT($K$4:$K$6,E4:E6)/SUM($K$4:$K$6) -> 0.024375211 | F7: =SUMPRODUCT($K$4:$K$6,F4:F6)/SUM($K$4:$K$6) -> 0.029334793 | G7: =SUMPRODUCT($K$4:$K$6,G4:G6)/SUM($K$4:$K$6) -> 0.031724486
B8: Operating Expenses | C8: 0.02 | D8: 0.05 | E8: 0.035 | F8: 0.02 | G8: 0.02 | H8: Underlying cot of content creation is expanding as management is shifting away from unprofitable series and reinvesting into core franchise volume, the underlying ost of content is expanding. Additionally, management have set up the infrastructure to better control how Streaming growth rate that even when traffic increases, the growth will be near minimal. $1.2 bn incremental surge expected
B9: Programming Charges | C9: 0.03 | D9: 0.04 | E9: 0.05 | F9: 0.05 | G9: 0.05 | H9: Management has commited to an intentional incremental investment to supercharge Star Trek and UFC. Beyond this, management plans to cut down on underperforming, localised international content to keep the rate efficient
B10: SG&A | C10: -0.22 | D10: -0.06 | E10: -0.04 | F10: -0.045 | G10: -0.05 | H10: SG&A is the target for the cost-saving initative. General overheads will experience structural constraction through 2030. Immediate layoffs in 2026 saving 1.5bn
B11: D&A | C11: 0.005 | D11: 0.005 | E11: 0.005 | F11: 0.005 | G11: 0.005 | H11: Flat rate due to the shift in digital architecture which will amortise, Additionally CAPEX will be minimalised to repay debt. Skydance non-cash expenses were driven by Amortisation as they didn’t own large manufacturing factories or heavy machinery and Depreciation was a minor line (around 0.5% of D&A). Assumption that Depreciation is 60%-80% of D&A line prior to merger. Depreciation can be expected to grow at -1% matching managments CAPEX plan
B12: Impairement Charges | C12: -0.15 | D12: -0.2 | E12: -0.25 | F12: -0.3 | G12: -0.35 | H12: Legacy asset write downs on cable networks and underperforming content libraries in 2024 and 2025. By rebalancing asset values in the Skydance merger, Paramount expect no recurring, non-cash impairments spikes through 2030.
B13: Restructuring, transaction-related and other corporate matters | C13: 0.02 | D13: -0.08 | E13: -0.08 | F13: -0.08 | G13: -0.08 | H13: Workforce reductions and merger advisory fees are recognised early, we can expect this line will be on a downard trajectory that zeroes out as steady operations take place in 2027 onwards
B14: Accounts Receivable (Days) | C14: =AVERAGE(Historicals!E10:G10) -> 85.871721 | D14: =AVERAGE(C14,Historicals!F10:G10) -> 85.3017 | E14: =AVERAGE(C14:D14,Historicals!G10) -> 84.915098 | F14: =AVERAGE(C14:E14) -> 85.36284 | G14: =AVERAGE(D14:F14) -> 85.193213 | H14: Average past 3 years
B15: Inventory (Days) | C15: =AVERAGE(Historicals!E11:G11) -> 26.564797 | D15: =AVERAGE(C15,Historicals!F11:G11) -> 26.825201 | E15: =AVERAGE(C15:D15,Historicals!G11) -> 26.822053 | F15: =AVERAGE(C15:E15) -> 26.73735 | G15: =AVERAGE(D15:F15) -> 26.794868 | H15: Average past 3 years
B16: Accounts Payable (Days) | C16: =AVERAGE(Historicals!E12:G12) -> 18.248177 | D16: =AVERAGE(C16,Historicals!F12:G12) -> 17.644919 | E16: =AVERAGE(C16:D16,Historicals!G12) -> 17.561217 | F16: =AVERAGE(C16:E16) -> 17.818104 | G16: =AVERAGE(D16:F16) -> 17.674747 | H16: Average past 3 years
B17: CAPEX | C17: -0.02 | D17: -0.02 | E17: -0.02 | F17: -0.02 | G17: -0.02 | H17: Management is containing their physical infrastructure CAPEX growth to protect FCF and focus on debt reduction following the Warner Bros debt discovery
B18: Interest | C18: 0.06 | D18: 0.06 | E18: 0.06 | F18: 0.06 | G18: 0.06 | H18: Flat rate
B19: Tax Rate | C19: 0.24 | D19: 0.24 | E19: 0.24 | F19: 0.24 | G19: 0.24 | H19: Market Rate
B20: Dividends paid on preferred stock | C20: 0 | D20: 0 | E20: 0 | F20: 0 | G20: 0 | H20: Flat rate
B21: Dividends paid on common stock | C21: =-Historicals!$F$46*0.2 -> -132.8 | D21: =-Historicals!$F$46*0.2 -> -132.8 | E21: =-Historicals!$F$46*0.2 -> -132.8 | F21: =-Historicals!$F$46*0.2 -> -132.8 | G21: =-Historicals!$F$46*0.2 -> -132.8 | H21: Management has establisehd a unified quartely dividend rate of $0.05 per hare for both Class A and Class B common shareholders
B22: Proceeds from issuance of preferred stock | C22: 0 | D22: 0 | E22: 0 | F22: 0 | G22: 0 | H22: Flat rate
B23: Proceeds from issuance of common stock | C23: 0 | D23: 0 | E23: 0 | F23: 0 | G23: 0 | H23: Flat rate
B24: Common stock | C24: 1 | D24: 1 | E24: 1 | F24: 1 | G24: 1 | H24: Flat rate
B25: Additional paid-in capital | C25: =Historicals!G86 -> 13386 | D25: 13886 | E25: 13886 | F25: 13886 | G25: 13886 | H25: Flat rate
B26: Treasury stock | C26: =Historicals!G87 -> 0 | D26: =Historicals!H87 -> 0 | E26: =Historicals!I87 -> 0 | F26: =Historicals!J87 -> 0 | G26: =Historicals!K87 -> 0 | H26: Flat rate
B27: Accumulated other comprehensive income (loss) | C27: =Historicals!G89 -> 59 | D27: 59 | E27: 59 | F27: 59 | G27: 59 | H27: Flat rate

Sheet DCF
F3: Year -2 | G3: Year -2 | H3: Year 0 | I3: Year 1 | J3: Year 2 | K3: Year 3 | L3: Year 4 | M3: Year 5 | N3: Term
B5: Revenue Growth | G5: =G11/F11-1 -> -0.014805072 | H5: =H11/G11-1 -> -0.01102249 | I5: =I11/H11-1 -> 0.012246548 | J5: =J11/I11-1 -> 0.020700573 | K5: =K11/J11-1 -> 0.024375211 | L5: =L11/K11-1 -> 0.029334793 | M5: =M11/L11-1 -> 0.031724486 | N5: 0.04
B6: COGS | C6: (% of Revenue) | F6: =-F12/F11 -> 0.67506408 | G6: =-G12/G11 -> 0.66535447 | H6: =-H12/H11 -> 0.68170018 | I6: =-I12/I11 -> 0.68692177 | J6: =-J12/J11 -> 0.70664 | K6: =-K12/K11 -> 0.71396925 | L6: =-L12/L11 -> 0.70749443 | M6: =-M12/M11 -> 0.69945449 | N6: 0.73
B7: Expenses | C7: (% of Revenue) | F7: =F15/F11 -> 0.32604883 | G7: =G15/G11 -> 0.50159176 | H7: =H15/H11 -> 0.25970025 | I7: =I15/I11 -> 0.21056656 | J7: =J15/J11 -> 0.19262408 | K7: =K15/K11 -> 0.17846034 | L7: =L15/L11 -> 0.16392545 | M7: =M15/M11 -> 0.14970246 | N7: 0.18
B9: Depreciation Growth | G9: =G18/F18-1 -> -0.062200957 | H9: =H18/G18-1 -> 1.0255102 | I9: =I18/H18-1 -> 0.005 | J9: =J18/I18-1 -> 0.005 | K9: =K18/J18-1 -> 0.005 | L9: =L18/K18-1 -> 0.005 | M9: =M18/L18-1 -> 0.005 | N9: 0.005
B11: Revenue | F11: =Forecast!F5 -> 29652 | G11: =Forecast!G5 -> 29213 | H11: =Forecast!H5 -> 28891 | I11: =Forecast!I5 -> 29244.815 | J11: =Forecast!J5 -> 29850.199 | K11: =Forecast!K5 -> 30577.804 | L11: =Forecast!L5 -> 31474.798 | M11: =Forecast!M5 -> 32473.32 | N11: =M11*(1+N5) -> 33772.252
B12: COGS | F12: =Forecast!F6 -> -20017 | G12: =Forecast!G6 -> -19437 | H12: =Forecast!H6 -> -19695 | I12: =Forecast!I6 -> -20088.9 | J12: =Forecast!J6 -> -21093.345 | K12: =Forecast!K6 -> -21831.612 | L12: =Forecast!L6 -> -22268.244 | M12: =Forecast!M6 -> -22713.609 | N12: =-N11*N6 -> -24653.744
B13: Gross Profit | F13: =F11+F12 -> 9635 | G13: =G11+G12 -> 9776 | H13: =H11+H12 -> 9196 | I13: =I11+I12 -> 9155.915 | J13: =J11+J12 -> 8756.8544 | K13: =K11+K12 -> 8746.1922 | L13: =L11+L12 -> 9206.5536 | M13: =M11+M12 -> 9759.7105 | N13: =N11+N12 -> 9118.5082
B15: Expenses | F15: =-SUM(Forecast!F7,Forecast!F8,Forecast!F10,Forecast!F11) -> 9668 | G15: =-SUM(Forecast!G7,Forecast!G8,Forecast!G10,Forecast!G11) -> 14653 | H15: =-SUM(Forecast!H7,Forecast!H8,Forecast!H10,Forecast!H11) -> 7503 | I15: =-SUM(Forecast!I7,Forecast!I8,Forecast!I10,Forecast!I11) -> 6157.98 | J15: =-SUM(Forecast!J7,Forecast!J8,Forecast!J10,Forecast!J11) -> 5749.8672 | K15: =-SUM(Forecast!K7,Forecast!K8,Forecast!K10,Forecast!K11) -> 5456.9255 | L15: =-SUM(Forecast!L7,Forecast!L8,Forecast!L10,Forecast!L11) -> 5159.5204 | M15: =-SUM(Forecast!M7,Forecast!M8,Forecast!M10,Forecast!M11) -> 4861.3358 | N15: =N11*N7 -> 6079.0054
B16: EBIT | F16: =F13-F15 -> -33 | G16: =G13-G15 -> -4877 | H16: =H13-H15 -> 1693 | I16: =I13-I15 -> 2997.935 | J16: =J13-J15 -> 3006.9872 | K16: =K13-K15 -> 3289.2668 | L16: =L13-L15 -> 4047.0332 | M16: =M13-M15 -> 4898.3747 | N16: =N13-N15 -> 3039.5027
B18: Depreciation | F18: =Forecast!F9 -> -418 | G18: =Forecast!G9 -> -392 | H18: =Forecast!H9 -> -794 | I18: =Forecast!I9 -> -797.97 | J18: =Forecast!J9 -> -801.95985 | K18: =Forecast!K9 -> -805.96965 | L18: =Forecast!L9 -> -809.9995 | M18: =Forecast!M9 -> -814.04949 | N18: =M18*(1+N9) -> -818.11974
B19: EBITDA | F19: =F16-F18 -> 385 | G19: =G16-G18 -> -4485 | H19: =H16-H18 -> 2487 | I19: =I16-I18 -> 3795.905 | J19: =J16-J18 -> 3808.9471 | K19: =K16-K18 -> 4095.2364 | L19: =L16-L18 -> 4857.0327 | M19: =M16-M18 -> 5712.4242 | N19: =N16-N18 -> 3857.6225
B21: Tax Rate | F21: 0.224 | G21: 0.047 | H21: 0.482 | I21: =Assumptions!C19 -> 0.24 | J21: =Assumptions!D19 -> 0.24 | K21: =Assumptions!E19 -> 0.24 | L21: =Assumptions!F19 -> 0.24 | M21: =Assumptions!G19 -> 0.24 | N21: 0.24
B22: Current Tax | F22: =-Forecast!F21 -> -361 | G22: =-Forecast!G21 -> -305 | H22: =-Forecast!H21 -> -119 | I22: =-Forecast!I21 -> 323.7244 | J22: =-Forecast!J21 -> 335.3487 | K22: =-Forecast!K21 -> 414.79735 | L22: =-Forecast!L21 -> 604.17694 | M22: =-Forecast!M21 -> 818.5088 | N22: =N19*N21 -> 925.82939
B27: UNLEVERED FREE CASH FLOW
F30: Year -2 | G30: Year -2 | H30: Year 0 | I30: Year 1 | J30: Year 2 | K30: Year 3 | L30: Year 4 | M30: Year 5 | N30: Term
B31: Unlevered Free Cash Flow
B32: EBIT | F32: =F16 -> -33 | G32: =G16 -> -4877 | H32: =H16 -> 1693 | I32: =I16 -> 2997.935 | J32: =J16 -> 3006.9872 | K32: =K16 -> 3289.2668 | L32: =L16 -> 4047.0332 | M32: =M16 -> 4898.3747 | N32: =N16 -> 3039.5027
B33: Tax Rate | F33: =F21 -> 0.224 | G33: =G21 -> 0.047 | H33: =H21 -> 0.482 | I33: =I21 -> 0.24 | J33: =J21 -> 0.24 | K33: =K21 -> 0.24 | L33: =L21 -> 0.24 | M33: =M21 -> 0.24 | N33: 0.24
B34: NOPAT | F34: =F32*(1-F33) -> -25.608 | G34: =G32*(1-G21) -> -4647.781 | H34: =H32*(1-H21) -> 876.974 | I34: =I32*(1-I21) -> 2278.4306 | J34: =J32*(1-J21) -> 2285.3103 | K34: =K32*(1-K21) -> 2499.8427 | L34: =L32*(1-L21) -> 3075.7452 | M34: =M32*(1-M21) -> 3722.7648 | N34: =N32*(1-N33) -> 2310.0221
B35: D&A | F35: =-F18 -> 418 | G35: =-G18 -> 392 | H35: =-H18 -> 794 | I35: =-I18 -> 797.97 | J35: =-J18 -> 801.95985 | K35: =-K18 -> 805.96965 | L35: =-L18 -> 809.9995 | M35: =-M18 -> 814.04949 | N35: =-N18 -> 818.11974
B36: Capital Expenditure | F36: =Forecast!F64 -> -328 | G36: =Forecast!G64 -> -263 | H36: =Forecast!H64 -> -296 | I36: =Forecast!I64 -> -290.08 | J36: =Forecast!J64 -> -284.2784 | K36: =Forecast!K64 -> -278.59283 | L36: =Forecast!L64 -> -273.02098 | M36: =Forecast!M64 -> -267.56056 | N36: -260
B37: Change in Working Capital | F37: =Forecast!F87 -> 78 | G37: =Forecast!G87 -> -33 | H37: =Forecast!H87 -> -226 | I37: =Forecast!I87 -> 168.0119 | J37: =Forecast!J87 -> 168.60629 | K37: =Forecast!K87 -> 161.04275 | L37: =Forecast!L87 -> 237.52835 | M37: =Forecast!M87 -> 241.81706 | N37: 260
B38: Unlevered Free Cash Flow | F38: =SUM(F34:F37) -> 142.392 | G38: =SUM(G34:G37) -> -4551.781 | H38: =SUM(H34:H37) -> 1148.974 | I38: =SUM(I34:I37) -> 2954.3325 | J38: =SUM(J34:J37) -> 2971.598 | K38: =SUM(K34:K37) -> 3188.2623 | L38: =SUM(L34:L37) -> 3850.2521 | M38: =SUM(M34:M37) -> 4511.0708 | N38: =SUM(N34:N37) -> 3128.1418
B42: DISCOUNTED CASH FLOW SCHEDULE
I44: Year 1 | J44: Year 2 | K44: Year 3 | L44: Year 4 | M44: Year 5 | N44: Term
B46: Unlevered Free Cash Flow | I46: =I38 -> 2954.3325 | J46: =J38 -> 2971.598 | K46: =K38 -> 3188.2623 | L46: =L38 -> 3850.2521 | M46: =M38 -> 4511.0708 | N46: =N38 -> 3128.1418
B47: EBITDA | N47: =N19 -> 3857.6225
B50: UNDISCOUNTED CASH FLOW
B51: Discrete Forecast | I51: =I46 -> 2954.3325 | J51: =J46 -> 2971.598 | K51: =K46 -> 3188.2623 | L51: =L46 -> 3850.2521 | M51: =M46 -> 4511.0708 | N51: =N46 -> 3128.1418
B52: Terminal Value | I52: 0 | J52: 0 | K52: 0 | L52: 0 | M52: 0 | N52: =(N51*(1+D60))/(D61-D60) -> 70114.387
B53: Total Cash Flow | I53: =SUM(I51:I52) -> 2954.3325 | J53: =SUM(J51:J52) -> 2971.598 | K53: =SUM(K51:K52) -> 3188.2623 | L53: =SUM(L51:L52) -> 3850.2521 | M53: =SUM(M51:M52) -> 4511.0708 | N53: =SUM(N51:N52) -> 73242.529
B57: ASSUMPTIONS | G57: ENTERPRISE VALUE | K57: EQUITY VALUE PER SHARE
B58: First Year of Forecast | D58: 2026 | G58: PV of Discrete | I58: =NPV(D61,I51,J51,K51,L51,M51) -> 13873.455 | K58: Equity Value | N58: =I74 -> 52112.267
B59: Terminal Multiple | G59: PV of Terminal | I59: =NPV(D61,0,0,0,0,N52) -> 48622.812 | K59: Shares Outstanding | N59: =D79 -> 1102
B60: Growth Rate | D60: 0.03 | G60: Enterprise Value | I60: =I58+I59 -> 62496.267 | K60: Instrinsic Value per Share | N60: =N58/N59 -> 47.288809
B61: Discount Rate | D61: =(D81*D68)+(D87*D74) -> 0.07595328
B64: COST OF EQUITY | G64: NET DEBT
B65: Risk-free rate (US 10y) | D65: 0.0474 | G65: Short-term debt | I65: =Forecast!H42 -> 433
B66: Beta | D66: 1.45 | G66: Long-term debt | I66: =Forecast!H45 -> 13225
B67: Market risk premium | D67: 0.0493 | G67: Cash and cash equivalent | I67: =Forecast!H31 -> 3274
B68: CAPM | D68: =D65*D66+D67 -> 0.11803 | G68: Net debt | I68: =(I65+I66)-I67 -> 10384
B71: AFTER-TAX COST OF DEBT | G71: EQUITY VALUE
B72: Interest Rate on Debt | D72: =Forecast!H99/(Forecast!I45+Forecast!I42) -> 0.064052288 | G72: Enterprise Value | I72: =I60 -> 62496.267
B73: Tax Rate | D73: =I21 -> 0.24 | G73: Less: Net Debt | I73: =-I68 -> -10384
B74: After-tax Cost of Debt | D74: =D72*(1-D73) -> 0.048679739 | G74: Equity Value | I74: =SUM(I72:I73) -> 52112.267
B77: MARKET VALUE OF EQUITY AND DEBT | G77: AVERAGE MATURITY
B78: Share price (29/07/26) | D78: 8.07 | H78: 2026 | I78: Outstanding | J78: Maturity | K78: YTM
B79: Shares Outstanding | D79: =Historicals!G46 -> 1102 | G79: 4.0% Senior Notes 2026 | I79: 347 | J79: 2026 | K79: =J79-$H$78 -> 0 | L79: =I79*K79 -> 0
B80: Market Value of Equity | D80: =D78*D79 -> 8893.14 | G80: 3.70% Senior Notes due 2026 | I80: 85 | J80: 2026 | K80: =J80-$H$78 -> 0 | L80: =I80*K80 -> 0
B81: Weight | D81: =D80/(D80+D86) -> 0.39327236 | G81: 2.90% Senior Notes 2027 | I81: 573 | J81: 2027 | K81: =J81-$H$78 -> 1 | L81: =I81*K81 -> 573
B82: Interest Expense | D82: =Forecast!H99 -> 882 | G82: 3.375% Senior Notes 2028 | I82: 487 | J82: 2028 | K82: =J82-$H$78 -> 2 | L82: =I82*K82 -> 974
B83: Current Cost of Debt | D83: =D72 -> 0.064052288 | G83: 3.70% Senior Notes 2028 | I83: 489 | J83: 2028 | K83: =J83-$H$78 -> 2 | L83: =I83*K83 -> 978
B84: Total Debt | D84: =I65+I66 -> 13658 | G84: 4.20% Senior Notes 2029 | I84: 489 | J84: 2029 | K84: =J84-$H$78 -> 3 | L84: =I84*K84 -> 1467
B85: Average Maturity (years) | D85: =L105/D84 -> 13.003881 | G85: 7.875% Senior Debentures 2030 | I85: 915 | J85: 2030 | K85: =J85-$H$78 -> 4 | L85: =I85*K85 -> 3660
B86: Market Value of Debt | D86: =-PV(D83,D85,D82,D84) -> 13720.043 | G86: 4.95% Senior Notes 2031 | I86: 1221 | J86: 2031 | K86: =J86-$H$78 -> 5 | L86: =I86*K86 -> 6105
B87: Weight | D87: =D86/(D80+D86) -> 0.60672764 | G87: 4.20% Senior Notes 2032 | I87: 921 | J87: 2032 | K87: =J87-$H$78 -> 6 | L87: =I87*K87 -> 5526
G88: 5.50% Senior Debentures 2033 | I88: 417 | J88: 2033 | K88: =J88-$H$78 -> 7 | L88: =I88*K88 -> 2919
G89: 4.85% Senior Debentures 2034 | I89: 76 | J89: 2034 | K89: =J89-$H$78 -> 8 | L89: =I89*K89 -> 608
G90: 6.875% Senior Debentures 2036 | I90: 1119 | J90: 2036 | K90: =J90-$H$78 -> 10 | L90: =I90*K90 -> 11190
G91: 6.75% Senior Debentures 2037 | I91: 75 | J91: 2037 | K91: =J91-$H$78 -> 11 | L91: =I91*K91 -> 825
G92: 5.90% Senior Notes due 2040 | I92: 272 | J92: 2040 | K92: =J92-$H$78 -> 14 | L92: =I92*K92 -> 3808
G93: 4.50% Senior Debentures 2042 | I93: 34 | J93: 2042 | K93: =J93-$H$78 -> 16 | L93: =I93*K93 -> 544
G94: 4.85% Senior Notes due 2042 | I94: 400 | J94: 2042 | K94: =J94-$H$78 -> 16 | L94: =I94*K94 -> 6400
G95: 4.375% Senior Debentures 2043 | I95: 1079 | J95: 2043 | K95: =J95-$H$78 -> 17 | L95: =I95*K95 -> 18343
G96: 4.875% Senior Debentures 2043 | I96: 14 | J96: 2043 | K96: =J96-$H$78 -> 17 | L96: =I96*K96 -> 238
G97: 5.85% Senior Debentures 2043 | I97: 1103 | J97: 2043 | K97: =J97-$H$78 -> 17 | L97: =I97*K97 -> 18751
G98: 5.25% Senior Debentures 2044 | I98: 275 | J98: 2044 | K98: =J98-$H$78 -> 18 | L98: =I98*K98 -> 4950
G99: 4.90% Senior Notes due 2044 | I99: 432 | J99: 2044 | K99: =J99-$H$78 -> 18 | L99: =I99*K99 -> 7776
... G103: 6.375% Junior Subordinated 2062 | I103: 989 | J103: 2062 | K103: =J103-$H$78 -> 36 | L103: =I103*K103 -> 35604
G105: Total | L105: =SUM(L79:L103) -> 177607

Sheet 2025 Reported Bridge
A1: 2025 Reported Predecessor / Successor Bridge
A2: USD in millions | B2: Predecessor Jan 1–Aug 6 | C2: Successor Aug 7–Dec 31 | D2: Combined 2025
A3: Revenues | B3: 16622 | C3: 12269 | D3: =SUM(B3:C3) -> 28891
A4: Operating expenses | B4: -11287 | C4: -8408 | D4: =SUM(B4:C4) -> -19695
A5: Programming charges | B5: 0 | C5: -41 | D5: =SUM(B5:C5) -> -41
A6: Selling, general and administrative | B6: -3526 | C6: -2594 | D6: =SUM(B6:C6) -> -6120
A7: Depreciation and amortization | B7: -204 | C7: -590 | D7: =SUM(B7:C7) -> -794
A8: Impairment charges | B8: -157 | C8: 0 | D8: =SUM(B8:C8) -> -157
A9: Restructuring, transaction-related and other corporate matters | B9: -454 | C9: -731 | D9: =SUM(B9:C9) -> -1185
A10: Gain on dispositions | B10: 35 | C10: 0 | D10: =SUM(B10:C10) -> 35 | F10: =B7*0.5% -> -1.02
A11: Operating income (loss) | B11: 1029 | C11: -95 | D11: =SUM(B11:C11) -> 934
A12: Interest expense | B12: -516 | C12: -366 | D12: =SUM(B12:C12) -> -882
A13: Interest income | B13: 83 | C13: 64 | D13: =SUM(B13:C13) -> 147
A14: Gain (loss) from investments | B14: 0 | C14: -40 | D14: =SUM(B14:C14) -> -40
A15: Other items, net | B15: -92 | C15: -39 | D15: =SUM(B15:C15) -> -131
A16: Pretax income (loss) | B16: 504 | C16: -476 | D16: =SUM(B16:C16) -> 28
A17: Benefit from income taxes | B17: 79 | C17: 40 | D17: =SUM(B17:C17) -> 119
A18: Equity in loss of investee companies | B18: -171 | C18: -104 | D18: =SUM(B18:C18) -> -275
A19: Net earnings (loss) from continuing operations | B19: 412 | C19: -540 | D19: =SUM(B19:C19) -> -128
A20: Net earnings attributable to noncontrolling interests | B20: -447 | C20: -46 | D20: =SUM(B20:C20) -> -493
A21: Net loss attributable to Parent | B21: -35 | C21: -586 | D21: =SUM(B21:C21) -> -621
A22: Operating cash flow | B22: 164 | C22: 485 | D22: =SUM(B22:C22) -> 649
... A28: Ending cash | B28: 2460 | C28: 3274 | D28: =SUM(B28:C28) -> 5734
A30: Important: 2025 earnings and cash-flow figures combine two separately reported accounting periods. The Successor applied purchase accounting at 7 August 2025, so 2025 is not directly comparable with prior years. EPS and weighted-average shares are not combined because the capital structure changed.

Sheet Source Notes
A1: Period | B1: Source | C1: Use | D1: URL
A2: 2021 | B2: Paramount/ViacomCBS 2021 Form 10-K | C2: 2021 income statement, balance sheet and cash flow statement | D2: https://ir.paramount.com/static-files/357c6440-f534-480a-b0ac-abb13963f070
A3: 2022–2023 | B3: Paramount Global 2023 Form 10-K | C3: 2022–2023 financial statements and comparative cash flows | D3: https://ir.paramount.com/static-files/0f0d231a-8c49-4907-8846-7965c83591da
A4: 2024 | B4: Paramount Skydance 2025 Form 10-K – Predecessor comparatives | C4: 2024 income statement, balance sheet and cash flow statement | D4: https://ir.paramount.com/static-files/9c0a5060-140f-4b5e-ac22-e7f89e6de398
A5: 2025 | B5: Paramount Skydance 2025 Form 10-K | C5: Predecessor and Successor periods; combined for model flow statements | D5: https://ir.paramount.com/static-files/9c0a5060-140f-4b5e-ac22-e7f89e6de398
