Workbook

Sheet Historical
B1: J Sainsbury plc – Historical Three-Statement Model
B2: FY2022A–FY2026A | £m except per-share data | 2025A uses the latest restated comparative disclosed in FY2026 where available
H3: Live Case | I3: 1 | K3: Share Price | L3: =DCF!N61 -> 3.3806943
D5: 2022A | E5: 2023A | F5: 2024A | G5: 2025A* | H5: 2026A | I5: 2027E | J5: 2028E | K5: 2029E | L5: 2030E | M5: 2031E
B6: Income Statement
B7: Revenue | D7: 29895 | E7: 31491 | F7: 32238 | G7: 32772 | H7: 33647 | I7: =H7*(1+Assumptions!F45+DCF!$W75) -> 29609.36 | J7: =I7*(1+Assumptions!G45+DCF!$W75) -> 29964.672 | K7: =J7*(1+Assumptions!H45+DCF!$W75) -> 30324.248 | L7: =K7*(1+Assumptions!I45+DCF!$W75) -> 30688.139 | M7: =L7*(1+Assumptions!J45+DCF!$W75) -> 31117.773
B8: Revenue growth | E8: =E7/D7-1 -> 0.053386854 | F8: =F7/E7-1 -> 0.023721063 | G8: =G7/F7-1 -> 0.016564303 | H8: =H7/G7-1 -> 0.026699622 | I8: =I7/H7-1 -> -0.12 | J8: =J7/I7-1 -> 0.012 | K8: =K7/J7-1 -> 0.012 | L8: =L7/K7-1 -> 0.012 | M8: =M7/L7-1 -> 0.014
B9: Cost of sales | D9: -27514 | E9: -29409 | F9: -30148 | G9: -30589 | H9: -31441 | I9: =-I7*Assumptions!F46 -> -27655.142 | J9: =-J7*Assumptions!G46 -> -27942.057 | K9: =-K7*Assumptions!H46 -> -28231.875 | L9: =-L7*Assumptions!I46 -> -28539.97 | M9: =-M7*Assumptions!J46 -> -28877.294
B10: Impairment loss on financial assets | D10: -15 | E10: -78 | F10: 0 | G10: 0 | H10: 0 | I10: 0 | J10: 0 | K10: 0 | L10: 0 | M10: 0
B11: Gross profit | D11: =D7+D9+D10 -> 2366 | E11: =E7+E9+E10 -> 2004 | F11: =F7+F9+F10 -> 2090 | G11: =G7+G9+G10 -> 2183 | H11: =H7+H9+H10 -> 2206 | I11: =I7+I9+I10 -> 1954.2178 | J11: =J7+J9+J10 -> 2022.6154 | K11: =K7+K9+K10 -> 2092.3731 | ... M11: =M7+M9+M10 -> 2240.4797
B12: Gross margin | D12: =D11/D7 -> 0.07914367 | E12: =E11/E7 -> 0.06363723 | F12: =F11/F7 -> 0.064830324 | G12: =G11/G7 -> 0.066611742 | H12: =H11/H7 -> 0.065563052 | I12: =I11/I7 -> 0.066 | J12: =J11/J7 -> 0.0675 | K12: =K11/K7 -> 0.069 | ... M12: =M11/M7 -> 0.072
B13: Administrative expenses | D13: -1430 | E13: -1515 | F13: -1404 | G13: -1401 | H13: -1391 | I13: =H13*(1+Assumptions!F47+DCF!$Z75) -> -1365.962 | J13: =I13*(1+Assumptions!G47+DCF!$Z75) -> -1341.3747 | K13: =J13*(1+Assumptions!H47+DCF!$Z75) -> -1317.2299 | L13: =K13*(1+Assumptions!I47+DCF!$Z75) -> -1297.4715 | M13: =L13*(1+Assumptions!J47+DCF!$Z75) -> -1278.0094
B14: Other income | D14: 220 | E14: 73 | F14: 58 | G14: 108 | H14: 82 | I14: =AVERAGE(F14:H14) -> 82.666667 | J14: =AVERAGE(G14:I14) -> 90.888889 | K14: =AVERAGE(H14:J14) -> 85.185185 | L14: =AVERAGE(I14:K14) -> 86.246914 | M14: =AVERAGE(J14:L14) -> 87.440329
B15: Operating profit | D15: =D11+D13+D14 -> 1156 | E15: =E11+E13+E14 -> 562 | F15: =F11+F13+F14 -> 744 | G15: =G11+G13+G14 -> 890 | H15: =H11+H13+H14 -> 897 | I15: =I11+I13+I14 -> 670.92243 | J15: =J11+J13+J14 -> 772.12959 | K15: =K11+K13+K14 -> 860.32838 | ... M15: =M11+M13+M14 -> 1049.9106
B16: Operating margin | D16: =D15/D7 -> 0.038668674 | E16: =E15/E7 -> 0.017846369 | F16: =F15/F7 -> 0.023078355 | G16: =G15/G7 -> 0.027157329 | H16: =H15/H7 -> 0.026659138 | I16: =I15/I7 -> 0.022659133 | J16: =J15/J7 -> 0.025767997 | K16: =K15/K7 -> 0.028370971 | ... M16: =M15/M7 -> 0.033739901
B17: Finance income | D17: 20 | E17: 74 | F17: 81 | G17: 67 | H17: 64 | I17: =AVERAGE(F17:H17) -> 70.666667 | J17: =AVERAGE(G17:I17) -> 67.222222 | K17: =AVERAGE(H17:J17) -> 67.296296 | L17: =AVERAGE(I17:K17) -> 68.395062 | M17: =AVERAGE(J17:L17) -> 67.63786
B18: Finance costs | D18: -322 | E18: -309 | F18: -336 | G18: -350 | H18: -342 | I18: =I90 -> -260.9735 | J18: =J90 -> -256.74318 | K18: =K90 -> -239.6947 | L18: =L90 -> -235.0361 | M18: =M90 -> -228.01614
B19: Profit before tax – continuing operations | D19: =D15+D17+D18 -> 854 | E19: =E15+E17+E18 -> 327 | F19: =F15+F17+F18 -> 489 | G19: =G15+G17+G18 -> 607 | H19: =H15+H17+H18 -> 619 | I19: =I15+I17+I18 -> 480.61559 | J19: =J15+J17+J18 -> 582.60863 | K19: =K15+K17+K18 -> 687.92998 | ... M19: =M15+M17+M18 -> 889.53231
B20: Income tax expense | D20: -177 | E20: -120 | F20: -181 | G20: -186 | H20: -205 | I20: =-I19*I22+I91 -> -204.35515 | J20: =-J19*J22+J91 -> -236.43476 | K20: =-K19*K22+K91 -> -270.13759 | L20: =-L19*L22+L91 -> -296.49733 | M20: =-M19*M22+M91 -> -334.65034
B21: Profit after tax – continuing operations | D21: =D19+D20 -> 677 | E21: =E19+E20 -> 207 | F21: =F19+F20 -> 308 | G21: =G19+G20 -> 421 | H21: =H19+H20 -> 414 | I21: =I19+I20 -> 276.26045 | J21: =J19+J20 -> 346.17387 | K21: =K19+K20 -> 417.79239 | ... M21: =M19+M20 -> 554.88197
B22: Effective tax rate | D22: =IFERROR(-D20/D19,"") -> 0.20725995 | E22: =IFERROR(-E20/E19,"") -> 0.36697248 | F22: =IFERROR(-F20/F19,"") -> 0.37014315 | G22: =IFERROR(-G20/G19,"") -> 0.30642504 | H22: =IFERROR(-H20/H19,"") -> 0.33117932 | I22: =Assumptions!F55 -> 0.32 | J22: =Assumptions!G55 -> 0.32 | K22: =Assumptions!H55 -> 0.32 | L22: =Assumptions!I55 -> 0.32 | M22: =Assumptions!J55 -> 0.32
B23: Profit after tax – discontinued operations | D23: 0 | E23: 0 | F23: -171 | G23: -168 | H23: -21 | I23: -700 | J23: 0 | K23: 0 | L23: 0 | M23: 0
B24: Profit for the financial period | D24: =D21+D23 -> 677 | E24: =E21+E23 -> 207 | F24: =F21+F23 -> 137 | G24: =G21+G23 -> 253 | H24: =H21+H23 -> 393 | I24: =I21+I23 -> -423.73955 | J24: =J21+J23 -> 346.17387 | K24: =K21+K23 -> 417.79239 | ... M24: =M21+M23 -> 554.88197
B25: Net margin | D25: =D24/D7 -> 0.022645927 | E25: =E24/E7 -> 0.0065733067 | F25: =F24/F7 -> 0.0042496433 | G25: =G24/G7 -> 0.0077200049 | H25: =H24/H7 -> 0.01168009 | I25: =I24/I7 -> -0.014311 | J25: =J24/J7 -> 0.011552733 | K25: =K24/K7 -> 0.013777502 | ... M25: =M24/M7 -> 0.017831673
B26: Basic EPS – total (p) | D26: 29.8 | E26: 9 | F26: 5.9 | G26: 10.9 | H26: 17.3
B27: Diluted EPS – total (p) | D27: 28.8 | E27: 8.8 | F27: 5.7 | G27: 10.7 | H27: 16.9
B30: Balance Sheet
B31: Property, plant and equipment | D31: 8402 | E31: 8201 | F31: 9282 | G31: 9358 | H31: 9386 | I31: ='Supporting Schedules'!H76 -> 9042.75 | J31: ='Supporting Schedules'!I76 -> 8851.5 | K31: ='Supporting Schedules'!J76 -> 8660.25 | L31: ='Supporting Schedules'!K76 -> 8469 | M31: ='Supporting Schedules'!L76 -> 8277.75
B32: Right-of-use assets | D32: 5560 | E32: 5345 | F32: 4296 | G32: 4455 | H32: 4486 | I32: ='Supporting Schedules'!H60 -> 4167.68 | J32: ='Supporting Schedules'!I60 -> 3887.5584 | K32: ='Supporting Schedules'!J60 -> 3641.0514 | L32: ='Supporting Schedules'!K60 -> 3424.1252 | M32: ='Supporting Schedules'!L60 -> 3233.2302
B33: Intangible assets | D33: 1006 | E33: 1024 | F33: 806 | G33: 807 | H33: 838 | I33: ='Supporting Schedules'!H93 -> 848 | J33: ='Supporting Schedules'!I93 -> 839 | K33: ='Supporting Schedules'!J93 -> 807.2 | L33: ='Supporting Schedules'!K93 -> 748.04 | M33: ='Supporting Schedules'!L93 -> 656.048
B34: Investments in joint ventures and associates | D34: 3 | E34: 2 | F34: 2 | G34: 2 | H34: 2 | I34: 2 | J34: 2 | K34: 2 | L34: 2 | M34: 2
B35: Other financial assets / FVOCI – non-current | D35: 604 | E35: 515 | F35: 761 | G35: 769 | H35: 129 | I35: =H35 -> 129 | J35: =I35 -> 129 | K35: =J35 -> 129 | L35: =K35 -> 129 | M35: =L35 -> 129
B36: Trade and other receivables – non-current | D36: 65 | E36: 56 | F36: 108 | G36: 42 | H36: 22 | I36: =H36 -> 22 | J36: =I36 -> 22 | K36: =J36 -> 22 | L36: =K36 -> 22 | M36: =L36 -> 22
B37: Financial Services receivables – non-current | D37: 2026 | E37: 1908 | F37: 1467 | G37: 0 | H37: 0 | I37: 0 | J37: 0 | K37: 0 | L37: 0 | M37: 0
B38: Derivative financial assets – non-current | D38: 213 | E38: 217 | F38: 68 | G38: 35 | H38: 18 | I38: =H38 -> 18 | J38: =I38 -> 18 | K38: =J38 -> 18 | L38: =K38 -> 18 | M38: =L38 -> 18
B39: Net retirement benefit surplus | D39: 2283 | E39: 989 | F39: 690 | G39: 754 | H39: 548 | I39: =H39 -> 548 | J39: =I39 -> 548 | K39: =J39 -> 548 | L39: =K39 -> 548 | M39: =L39 -> 548
B40: Total non-current assets | D40: =SUM(D31:D39) -> 20162 | E40: =SUM(E31:E39) -> 18257 | F40: =SUM(F31:F39) -> 17480 | G40: =SUM(G31:G39) -> 16222 | H40: =SUM(H31:H39) -> 15429 | I40: =SUM(I31:I39) -> 14777.43 | J40: =SUM(J31:J39) -> 14297.058 | K40: =SUM(K31:K39) -> 13827.501 | ... M40: =SUM(M31:M39) -> 12886.028
B41: Inventories | D41: 1797 | E41: 1899 | F41: 1927 | G41: 1946 | H41: 1987 | I41: ='Supporting Schedules'!H64 -> 1515.3503 | J41: ='Supporting Schedules'!I64 -> 1377.9645 | K41: ='Supporting Schedules'!J64 -> 1237.5617 | L41: ='Supporting Schedules'!K64 -> 1211.9713 | M41: ='Supporting Schedules'!L64 -> 1186.7381
B42: Trade and other receivables – current | D42: 683 | E42: 627 | F42: 582 | G42: 572 | H42: 431 | I42: ='Supporting Schedules'!H65 -> 405.60767 | J42: ='Supporting Schedules'!I65 -> 410.47496 | K42: ='Supporting Schedules'!J65 -> 415.40066 | L42: ='Supporting Schedules'!K65 -> 420.38547 | M42: ='Supporting Schedules'!L65 -> 426.27087
B43: Financial Services receivables – current | D43: 3163 | E43: 3484 | F43: 3050 | G43: 0 | H43: 0 | I43: 0 | J43: 0 | K43: 0 | L43: 0 | M43: 0
B44: Other financial assets / FVOCI – current | D44: 196 | E44: 494 | F44: 17 | G44: 1167 | H44: 0 | I44: 0 | J44: 0 | K44: 0 | L44: 0 | M44: 0
B45: Derivative financial assets – current | D45: 78 | E45: 70 | F45: 8 | G45: 15 | H45: 7 | I45: =H45 -> 7 | J45: =I45 -> 7 | K45: =J45 -> 7 | L45: =K45 -> 7 | M45: =L45 -> 7
B46: Income taxes receivable | D46: 0 | E46: 0 | F46: 0 | G46: 86 | H46: 19 | I46: 0 | J46: 0 | K46: 0 | L46: 0 | M46: 0
B47: Cash and cash equivalents | D47: 825 | E47: 1319 | F47: 1987 | G47: 2222 | H47: 1067 | I47: =I117 -> 652.87787 | J47: =J117 -> -181.74847 | K47: =K117 -> -768.23246 | L47: =L117 -> -1275.5885 | M47: =M117 -> -1777.8979
B48: Current assets before held for sale | D48: =SUM(D41:D47) -> 6742 | E48: =SUM(E41:E47) -> 7893 | F48: =SUM(F41:F47) -> 7571 | G48: =SUM(G41:G47) -> 6008 | H48: =SUM(H41:H47) -> 3511 | I48: =SUM(I41:I47) -> 2580.8358 | J48: =SUM(J41:J47) -> 1613.6909 | K48: =SUM(K41:K47) -> 891.72985 | ... M48: =SUM(M41:M47) -> -157.88898
B49: Assets held for sale / disposal group | D49: 8 | E49: 8 | F49: 10 | G49: 2527 | H49: 3 | I49: 0 | J49: 0 | K49: 0 | L49: 0 | M49: 0
B50: Total current assets | D50: =D48+D49 -> 6750 | E50: =E48+E49 -> 7901 | F50: =F48+F49 -> 7581 | G50: =G48+G49 -> 8535 | H50: =H48+H49 -> 3514 | I50: =I48+I49 -> 2580.8358 | J50: =J48+J49 -> 1613.6909 | K50: =K48+K49 -> 891.72985 | ... M50: =M48+M49 -> -157.88898
B51: Total assets | D51: =D40+D50 -> 26912 | E51: =E40+E50 -> 26158 | F51: =F40+F50 -> 25061 | G51: =G40+G50 -> 24757 | H51: =H40+H50 -> 18943 | I51: =I40+I50 -> 17358.266 | J51: =J40+J50 -> 15910.749 | K51: =K40+K50 -> 14719.231 | ... M51: =M40+M50 -> 12728.139
B52: Trade and other payables – current | D52: 4546 | E52: 4837 | F52: 5091 | G52: 5489 | H52: 5565 | I52: =-'Supporting Schedules'!H66 -> 4849.1208 | J52: =-'Supporting Schedules'!I66 -> 4899.4292 | K52: =-'Supporting Schedules'!J66 -> 4950.2466 | L52: =-'Supporting Schedules'!K66 -> 5004.2686 | M52: =-'Supporting Schedules'!L66 -> 5063.4159
B53: Financial Services customer deposits – current | D53: 4444 | E53: 4880 | F53: 5515 | G53: 1955 | H53: 0 | I53: 0 | J53: 0 | K53: 0 | L53: 0 | M53: 0
B54: Borrowings – current | D54: 54 | E54: 53 | F54: 65 | G54: 72 | H54: 80 | I54: =-'Supporting Schedules'!H8 -> 77.2 | J54: =-'Supporting Schedules'!I8 -> 202.2 | K54: =-'Supporting Schedules'!J8 -> 77.2 | L54: =-'Supporting Schedules'!K8 -> 327.2 | M54: =-'Supporting Schedules'!L8 -> 77.2
B55: Lease liabilities – current | D55: 526 | E55: 1533 | F55: 515 | G55: 483 | H55: 505 | I55: ='Supporting Schedules'!H50 -> 491.4 | J55: ='Supporting Schedules'!I50 -> 493.832 | K55: ='Supporting Schedules'!J50 -> 496.45856 | L55: ='Supporting Schedules'!K50 -> 499.29524 | M55: ='Supporting Schedules'!L50 -> 502.35886
B56: Other financial liabilities – current | D56: 0 | E56: 0 | F56: 0 | G56: 0 | H56: 21 | I56: 0 | J56: 0 | K56: 0 | L56: 0 | M56: 0
B57: Derivative financial liabilities – current | D57: 29 | E57: 16 | F57: 28 | G57: 15 | H57: 20 | I57: =H57 -> 20 | J57: =I57 -> 20 | K57: =J57 -> 20 | L57: =K57 -> 20 | M57: =L57 -> 20
B58: Income taxes payable | D58: 169 | E58: 155 | F58: 125 | G58: 4 | H58: 0 | I58: =H58 -> 0 | J58: =I58 -> 0 | K58: =J58 -> 0 | L58: =K58 -> 0 | M58: =L58 -> 0
B59: Provisions – current | D59: 100 | E59: 140 | F59: 113 | G59: 230 | H59: 140 | I59: =-'Supporting Schedules'!H67 -> 130 | J59: =-'Supporting Schedules'!I67 -> 120 | K59: =-'Supporting Schedules'!J67 -> 110 | L59: =-'Supporting Schedules'!K67 -> 110 | M59: =-'Supporting Schedules'!L67 -> 110
B60: Current liabilities before disposal group | D60: =SUM(D52:D59) -> 9868 | E60: =SUM(E52:E59) -> 11614 | F60: =SUM(F52:F59) -> 11452 | G60: =SUM(G52:G59) -> 8248 | H60: =SUM(H52:H59) -> 6331 | I60: =SUM(I52:I59) -> 5567.7208 | J60: =SUM(J52:J59) -> 5735.4612 | K60: =SUM(K52:K59) -> 5653.9052 | ... M60: =SUM(M52:M59) -> 5772.9747
B61: Liabilities of disposal group held for sale | D61: 0 | E61: 0 | F61: 0 | G61: 3136 | H61: 0 | I61: 0 | J61: 0 | K61: 0 | L61: 0 | M61: 0
B62: Total current liabilities | D62: =D60+D61 -> 9868 | E62: =E60+E61 -> 11614 | F62: =F60+F61 -> 11452 | G62: =G60+G61 -> 11384 | H62: =H60+H61 -> 6331 | I62: =I60+I61 -> 5567.7208 | J62: =J60+J61 -> 5735.4612 | K62: =K60+K61 -> 5653.9052 | ... M62: =M60+M61 -> 5772.9747
B63: Trade and other payables – non-current | D63: 24 | E63: 0 | F63: 11 | G63: 24 | H63: 22 | I63: =H63 -> 22 | J63: =I63 -> 22 | K63: =J63 -> 22 | L63: =K63 -> 22 | M63: =L63 -> 22
B64: Financial Services customer deposits – non-current | D64: 815 | E64: 1066 | F64: 206 | G64: 13 | H64: 0 | I64: =H64 -> 0 | J64: =I64 -> 0 | K64: =J64 -> 0 | L64: =K64 -> 0 | M64: =L64 -> 0
B65: Borrowings – non-current | D65: 707 | E65: 603 | F65: 1130 | G65: 1042 | H65: 981 | I65: ='Supporting Schedules'!H38 -> 978.8 | J65: ='Supporting Schedules'!I38 -> 781.6 | K65: ='Supporting Schedules'!J38 -> 704.4 | L65: ='Supporting Schedules'!K38 -> 627.2 | M65: ='Supporting Schedules'!L38 -> 550
B66: Lease liabilities – non-current | D66: 6095 | E66: 4956 | F66: 4839 | G66: 5011 | H66: 5035 | I66: ='Supporting Schedules'!H51 -> 4687.8 | J66: ='Supporting Schedules'!I51 -> 4619.704 | K66: ='Supporting Schedules'!J51 -> 4546.1603 | L66: ='Supporting Schedules'!K51 -> 4466.7331 | M66: ='Supporting Schedules'!L51 -> 4380.9518
B67: Other financial liabilities – non-current | D67: 0 | E67: 0 | F67: 0 | G67: 0 | H67: 0 | I67: 0 | J67: 0 | K67: 0 | L67: 0 | M67: 0
B68: Derivative financial liabilities – non-current | D68: 3 | E68: 58 | F68: 59 | G68: 11 | H68: 3 | I68: =H68 -> 3 | J68: =I68 -> 3 | K68: =J68 -> 3 | L68: =K68 -> 3 | M68: =L68 -> 3
B69: Retirement benefit deficit | D69: 0 | E69: 0 | F69: 0 | G69: 23 | H69: 23 | I69: =H69 -> 23 | J69: =I69 -> 23 | K69: =J69 -> 23 | L69: =K69 -> 23 | M69: =L69 -> 23
B70: Deferred income tax liability | D70: 806 | E70: 476 | F70: 329 | G70: 327 | H70: 302 | I70: =H70 -> 302 | J70: =I70 -> 302 | K70: =J70 -> 302 | L70: =K70 -> 302 | M70: =L70 -> 302
B71: Provisions – non-current | D71: 171 | E71: 132 | F71: 167 | G71: 157 | H71: 96 | I71: =H71 -> 96 | J71: =I71 -> 96 | K71: =J71 -> 96 | L71: =K71 -> 96 | M71: =L71 -> 96
B72: Total non-current liabilities | D72: =SUM(D63:D71) -> 8621 | E72: =SUM(E63:E71) -> 7291 | F72: =SUM(F63:F71) -> 6741 | G72: =SUM(G63:G71) -> 6608 | H72: =SUM(H63:H71) -> 6462 | I72: =SUM(I63:I71) -> 6112.6 | J72: =SUM(J63:J71) -> 5847.304 | K72: =SUM(K63:K71) -> 5696.5603 | ... M72: =SUM(M63:M71) -> 5376.9518
B73: Total liabilities | D73: =D62+D72 -> 18489 | E73: =E62+E72 -> 18905 | F73: =F62+F72 -> 18193 | G73: =G62+G72 -> 17992 | H73: =H62+H72 -> 12793 | I73: =I62+I72 -> 11680.321 | J73: =J62+J72 -> 11582.765 | K73: =K62+K72 -> 11350.465 | ... M73: =M62+M72 -> 11149.927
B74: Called up share capital | D74: 668 | E74: 672 | F74: 678 | G74: 669 | H74: 647 | I74: =H74 -> 647 | J74: =I74 -> 647 | K74: =J74 -> 647 | L74: =K74 -> 647 | M74: =L74 -> 647
B75: Share premium | D75: 1406 | E75: 1418 | F75: 1430 | G75: 1448 | H75: 1465 | I75: =H75 -> 1465 | J75: =I75-54.9961039870263 -> 1410.0039 | K75: =J75 -> 1410.0039 | L75: =K75 -> 1410.0039 | M75: =L75 -> 1410.0039
B76: Merger reserve | D76: 568 | E76: 568 | F76: 568 | G76: 173 | H76: 173 | I76: =H76 -> 173 | J76: =I76 -> 173 | K76: =J76 -> 173 | L76: =K76 -> 173 | M76: =L76 -> 173
B77: Capital redemption and other reserves | D77: 1021 | E77: 954 | F77: 955 | G77: -54 | H77: -65 | I77: =H77-300 -> -365 | J77: =I77-300 -> -665 | K77: =J77-300 -> -965 | L77: =K77-300 -> -1265 | M77: =L77-300 -> -1565
B78: Retained earnings | D78: 4760 | E78: 3641 | F78: 3237 | G78: 4529 | H78: 3930 | I78: =H78+I24+I107 -> 2906.2604 | J78: =I78+J24+J107 -> 2652.4343 | K78: =J78+K24+K107 -> 2470.2267 | L78: =K78+L24+L107 -> 2264.0335 | M78: =L78+M24+M107 -> 2088.9155
B79: Total equity | D79: =SUM(D74:D78) -> 8423 | E79: =SUM(E74:E78) -> 7253 | F79: =SUM(F74:F78) -> 6868 | G79: =SUM(G74:G78) -> 6765 | H79: =SUM(H74:H78) -> 6150 | I79: =SUM(I74:I78) -> 4826.2604 | J79: =SUM(J74:J78) -> 4217.4382 | K79: =SUM(K74:K78) -> 3735.2306 | ... M79: =SUM(M74:M78) -> 2753.9194
B80: Total liabilities and equity | D80: =D73+D79 -> 26912 | E80: =E73+E79 -> 26158 | F80: =F73+F79 -> 25061 | G80: =G73+G79 -> 24757 | H80: =H73+H79 -> 18943 | I80: =I73+I79 -> 16506.581 | J80: =J73+J79 -> 15800.203 | K80: =K73+K79 -> 15085.696 | ... M80: =M73+M79 -> 13903.846
B84: Cash Flow Statement
B85: Operating profit – CF starting point | D85: =D15 -> 1156 | E85: =E15 -> 562 | F85: =F15 -> 744 | G85: =G15 -> 890 | H85: =H15 -> 897 | I85: =I15 -> 670.92243 | J85: =J15 -> 772.12959 | K85: =K15 -> 860.32838 | ... M85: =M15 -> 1049.9106
B86: Depreciation and amortisation | D86: 1220 | E86: 1208 | F86: 1160 | G86: 1215 | H86: 1238 | I86: =Assumptions!F52 -> 1200 | J86: =Assumptions!G52 -> 1200 | K86: =Assumptions!H52 -> 1200 | L86: =Assumptions!I52 -> 1200 | M86: =Assumptions!J52 -> 1200
B87: Net impairment loss on non-financial assets | D87: 9 | E87: 315 | F87: 45 | G87: 22 | H87: 23 | I87: 0 | J87: 54.996104 | K87: 78.985433 | L87: 58.007704 | M87: 0
B88: Other non-cash items & working capital | D88: -1024 | E88: 519 | F88: 561 | G88: -913 | H88: 29 | I88: ='Supporting Schedules'!H69 -> 228.8371 | J88: ='Supporting Schedules'!I69 -> -172.82685 | K88: ='Supporting Schedules'!J69 -> -176.29455 | L88: ='Supporting Schedules'!K69 -> -74.62756 | M88: ='Supporting Schedules'!L69 -> -78.495048
B89: Cash generated from operations – continuing | D89: =SUM(D85:D88) -> 1361 | E89: =SUM(E85:E88) -> 2604 | F89: =SUM(F85:F88) -> 2510 | G89: =SUM(G85:G88) -> 1214 | H89: =SUM(H85:H88) -> 2187 | I89: =SUM(I85:I88) -> 2099.7595 | J89: =SUM(J85:J88) -> 1854.2988 | K89: =SUM(K85:K88) -> 1963.0193 | ... M89: =SUM(M85:M88) -> 2171.4155
B90: Interest paid | D90: -329 | E90: -316 | F90: -336 | G90: -359 | H90: -348 | I90: =-('Supporting Schedules'!H11+'Supporting Schedules'!H48) -> -260.9735 | J90: =-('Supporting Schedules'!I11+'Supporting Schedules'!I48) -> -256.74318 | K90: =-('Supporting Schedules'!J11+'Supporting Schedules'!J48) -> -239.6947 | L90: =-('Supporting Schedules'!K11+'Supporting Schedules'!K48) -> -235.0361 | M90: =-('Supporting Schedules'!L11+'Supporting Schedules'!L48) -> -228.01614
B91: Corporation tax paid | D91: -23 | E91: -103 | F91: -61 | G91: -53 | H91: -65 | I91: -50.558156 | J91: -50 | K91: -50 | L91: -50 | M91: -50
B92: Net cash generated from operating activities – continuing | D92: =SUM(D89:D91) -> 1009 | E92: =SUM(E89:E91) -> 2185 | F92: =SUM(F89:F91) -> 2113 | G92: =SUM(G89:G91) -> 802 | H92: =SUM(H89:H91) -> 1774 | I92: =SUM(I89:I91) -> 1788.2279 | J92: =SUM(J89:J91) -> 1547.5557 | K92: =SUM(K89:K91) -> 1673.3246 | ... M92: =SUM(M89:M91) -> 1893.3994
B93: Purchase of property, plant and equipment | D93: -416 | E93: -525 | F93: -1381 | G93: -617 | H93: -613 | I93: =-Assumptions!F53*75% -> -618.75 | J93: =-Assumptions!G53*75% -> -618.75 | K93: =-Assumptions!H53*75% -> -618.75 | L93: =-Assumptions!I53*75% -> -618.75 | M93: =-Assumptions!J53*75% -> -618.75
B94: Initial direct costs on new leases | D94: -3 | E94: -16 | F94: -6 | G94: -34 | H94: -8 | I94: -5 | J94: -5 | K94: -5 | L94: -5 | M94: -5
B95: Purchase of intangible assets | D95: -278 | E95: -213 | F95: -178 | G95: -208 | H95: -230 | I95: =-'Supporting Schedules'!H81 -> -205 | J95: =-'Supporting Schedules'!I81 -> -205 | K95: =-'Supporting Schedules'!J81 -> -205 | L95: =-'Supporting Schedules'!K81 -> -205 | M95: =-'Supporting Schedules'!L81 -> -205
B96: Proceeds from disposal of property, plant and equipment | D96: 46 | E96: 29 | F96: 77 | G96: 45 | H96: 41 | I96: 40 | J96: 40 | K96: 40 | L96: 40 | M96: 40
B97: Dividends and distributions received | D97: 2 | E97: 1 | F97: 0 | G97: 0 | H97: 0 | I97: 0 | J97: 0 | K97: 0 | L97: 0 | M97: 0
B98: Interest received | D98: 0 | E98: 0 | F98: 27 | G98: 27 | H98: 23 | I98: 0 | J98: 0 | K98: 0 | L98: 0 | M98: 0
B99: Net cash used in investing activities – continuing | D99: =SUM(D93:D98) -> -649 | E99: =SUM(E93:E98) -> -724 | F99: =SUM(F93:F98) -> -1461 | G99: =SUM(G93:G98) -> -787 | H99: =SUM(H93:H98) -> -787 | I99: =SUM(I93:I98) -> -788.75 | J99: =SUM(J93:J98) -> -788.75 | K99: =SUM(K93:K98) -> -788.75 | ... M99: =SUM(M93:M98) -> -788.75
B100: Proceeds from issuance of ordinary shares | D100: 21 | E100: 13 | F100: 15 | G100: 20 | H100: 20 | I100: 20 | J100: 20 | K100: 20 | L100: 20 | M100: 20
B101: Proceeds from borrowings | D101: 0 | E101: 0 | F101: 575 | G101: 544 | H101: 0 | I101: ='Supporting Schedules'!H7 -> 0 | J101: ='Supporting Schedules'!I7 -> 0 | K101: ='Supporting Schedules'!J7 -> 0 | L101: ='Supporting Schedules'!K7 -> 250 | M101: ='Supporting Schedules'!L7 -> 0
B102: Repayment of borrowings | D102: -248 | E102: -95 | F102: -41 | G102: -623 | H102: -59 | I102: ='Supporting Schedules'!H8 -> -77.2 | J102: ='Supporting Schedules'!I8 -> -202.2 | K102: ='Supporting Schedules'!J8 -> -77.2 | L102: ='Supporting Schedules'!K8 -> -327.2 | M102: ='Supporting Schedules'!L8 -> -77.2
B103: Repayment of perpetual capital securities | D103: -8 | E103: 0 | F103: 0 | G103: 0 | H103: 0 | I103: 0 | J103: 0 | K103: 0 | L103: 0 | M103: 0
B104: Purchase of own shares – share schemes | D104: -48 | E104: -45 | F104: -18 | G104: -63 | H104: -64 | I104: -35 | J104: -35 | K104: -35 | L104: -35 | M104: -35
B105: Purchase of own shares – cancellation | D105: 0 | E105: 0 | F105: 0 | G105: -200 | H105: -251 | I105: -300 | J105: -300 | K105: -300 | L105: -300 | M105: -300
B106: Repayment of lease liabilities | D106: -493 | E106: -514 | F106: -507 | G106: -487 | H106: -504 | I106: ='Supporting Schedules'!H43 -> -490.4 | J106: ='Supporting Schedules'!I43 -> -492.832 | K106: ='Supporting Schedules'!J43 -> -495.45856 | L106: ='Supporting Schedules'!K43 -> -498.29524 | M106: ='Supporting Schedules'!L43 -> -501.35886
...

Sheet Assumptions
E1: Assumptions | F1: 2027 | G1: 2028 | H1: 2029 | I1: 2030 | J1: 2031
E2: Base Case
B3: Cases | E3: Revenue | F3: -0.12 | G3: 0.012 | H3: 0.012 | I3: 0.012 | J3: 0.014
C4: 1 | E4: Cost of Sales | F4: 0.934 | G4: 0.9325 | H4: 0.931 | I4: 0.93 | J4: 0.928
C5: 2 | E5: Admin Expenses | F5: -0.018 | G5: -0.018 | H5: -0.018 | I5: -0.015 | J5: -0.015
C6: 3 | E6: Inventory | F6: 20 | G6: 18 | H6: 16 | I6: 15.5 | J6: 15
E7: Trade and other receivables | F7: 5 | G7: 5 | H7: 5 | I7: 5 | J7: 5
E8: Trade and other payables | F8: 64 | G8: 64 | H8: 64 | I8: 64 | J8: 64
E9: Operating provisions | F9: -130 | G9: -120 | H9: -110 | I9: -110 | J9: -110
E10: Depreciation & Amortisation | F10: 1200 | G10: 1200 | H10: 1200 | I10: 1200 | J10: 1200
E11: CapEx | F11: 825 | G11: 825 | H11: 825 | I11: 825 | J11: 825
E12: Dividend paid | F12: 600 | G12: 600 | H12: 600 | I12: 680 | J12: 730
E13: Tax Rate | F13: 0.32 | G13: 0.32 | H13: 0.32 | I13: 0.32 | J13: 0.32
E14: D&A | F14: 1200 | G14: 1200 | H14: 1200 | I14: 1200 | J14: 1200
E16: Downside Case
E17: Revenue | F17: -0.135 | G17: 0.003 | H17: 0.005 | I17: 0.007 | J17: 0.008
E18: Cost of Sales | F18: 0.94 | G18: 0.94 | H18: 0.939 | I18: 0.938 | J18: 0.937
E19: Admin Expenses | F19: 0 | G19: -0.005 | H19: -0.005 | I19: -0.01 | J19: -0.01
E20: Inventory | F20: 22 | G20: 21 | H20: 20 | I20: 19 | J20: 18
E21: Trade and other receivables | F21: 6 | G21: 6 | H21: 6 | I21: 6 | J21: 6
E22: Trade and other payables | F22: 60 | G22: 60 | H22: 60 | I22: 60 | J22: 60
E23: Operating provisions | F23: -180 | G23: -170 | H23: -150 | I23: -130 | J23: -120
E24: Depreciation & Amortisation | F24: 1200 | G24: 1200 | H24: 1200 | I24: 1200 | J24: 1200
E25: CapEx | F25: 900 | G25: 900 | H25: 875 | I25: 875 | J25: 850
E26: Dividend paid | F26: 450 | G26: 500 | H26: 525 | I26: 550 | J26: 575
E27: Tax Rate | F27: 0.32 | G27: 0.32 | H27: 0.32 | I27: 0.32 | J27: 0.32
E29: Upside Case
E30: Revenue | F30: -0.105 | G30: 0.02 | H30: 0.022 | I30: 0.023 | J30: 0.025
E31: Cost of Sales | F31: 0.93 | G31: 0.927 | H31: 0.925 | I31: 0.923 | J31: 0.921
E32: Admin Expenses | F32: -0.03 | G32: -0.03 | H32: -0.025 | I32: -0.025 | J32: -0.02
E33: Inventory | F33: 18 | G33: 16 | H33: 15 | I33: 14.5 | J33: 14
E34: Trade and other receivables | F34: 4.5 | G34: 4.5 | H34: 4.5 | I34: 4.5 | J34: 4.5
E35: Trade and other payables | F35: 65 | G35: 65 | H35: 65 | I35: 65 | J35: 65
E36: Operating provisions | F36: -100 | G36: -90 | H36: -80 | I36: -80 | J36: -80
E37: Depreciation & Amortisation | F37: 1200 | G37: 1200 | H37: 1200 | I37: 1200 | J37: 1200
E38: CapEx | F38: 800 | G38: 800 | H38: 800 | I38: 800 | J38: 800
E39: Dividend paid | F39: 650 | G39: 650 | H39: 700 | I39: 750 | J39: 800
E40: Tax Rate | F40: 0.32 | G40: 0.32 | H40: 0.32 | I40: 0.32 | J40: 0.32
E44: Live Case | K44: Rationale
E45: Revenue | F45: =CHOOSE(Historical!$I$3,Assumptions!F3,Assumptions!F17,Assumptions!F30) -> -0.12 | G45: =CHOOSE(Historical!$I$3,Assumptions!G3,Assumptions!G17,Assumptions!G30) -> 0.012 | H45: =CHOOSE(Historical!$I$3,Assumptions!H3,Assumptions!H17,Assumptions!H30) -> 0.012 | I45: =CHOOSE(Historical!$I$3,Assumptions!I3,Assumptions!I17,Assumptions!I30) -> 0.012 | J45: =CHOOSE(Historical!$I$3,Assumptions!J3,Assumptions!J17,Assumptions!J30) -> 0.014 | K45: "Next Level Sainsbury's" blueprint aims to priortise volume increases ahead of price inflation (2.6%). Aim to grow revenue by winning big weekly shops (£80+ baskets) from competitors through aggressive value scheme like Nectar Prices and the Aldi Price Match, which will force internal price deflation. Rapid home delivery serves as a major growth vector for digital sales. Sainsbury's commerce divison expanded by 69% in 2026. Argos sales have fell 0.5% due to cautious consumer spending, and is expected to reamin a heavy drag on total revenue. Argos sale expected to finalise in 2027. We can expect to see a signficant drop in revenue as the retail brought in roughly 4bn to the top-line revenue
E46: Cost of Sales | F46: =CHOOSE(Historical!$I$3,Assumptions!F4,Assumptions!F18,Assumptions!F31) -> 0.934 | G46: =CHOOSE(Historical!$I$3,Assumptions!G4,Assumptions!G18,Assumptions!G31) -> 0.9325 | H46: =CHOOSE(Historical!$I$3,Assumptions!H4,Assumptions!H18,Assumptions!H31) -> 0.931 | I46: =CHOOSE(Historical!$I$3,Assumptions!I4,Assumptions!I18,Assumptions!I31) -> 0.93 | J46: =CHOOSE(Historical!$I$3,Assumptions!J4,Assumptions!J18,Assumptions!J31) -> 0.928 | K46: Supply chain costas are highly sensitive to fluctuating global commodity prices and the core policy is to intentioanlly compress their gross margins whenever commodity prices fall and use that the extra cash to expand their value schemes rather than keep extra profit. To protect profit, management is mapping a £1bn savings program split across COS and Admin Expenses.
E47: Admin Expenses | F47: =CHOOSE(Historical!$I$3,Assumptions!F5,Assumptions!F19,Assumptions!F32) -> -0.018 | G47: =CHOOSE(Historical!$I$3,Assumptions!G5,Assumptions!G19,Assumptions!G32) -> -0.018 | H47: =CHOOSE(Historical!$I$3,Assumptions!H5,Assumptions!H19,Assumptions!H32) -> -0.018 | I47: =CHOOSE(Historical!$I$3,Assumptions!I5,Assumptions!I19,Assumptions!I32) -> -0.015 | J47: =CHOOSE(Historical!$I$3,Assumptions!J5,Assumptions!J19,Assumptions!J32) -> -0.015 | K47: Primary goal is to keep Admin at £1.25bn annually by March 2027. This will be achieved by over 3,000 role reductions in all central head office function, combining redundant corporate divisions and eliminating overlapping managerial layers between the grocery team and Argos. Additionally, there will be a heavy consolidation of corporate software footprint, moving from legacy retail systems to cloud infrastructure lowering software licensing and central support costs. £150 million in one-off cash implementation costs to achieve these goals. With wages increasing, management must use aggressive measures to hit their goal. As Sainsburys is restructuring their core banking services by completing the sale to NatWest, a lof of the infrastructure and product management have been transferred, allowing them to maintain brand presence and customer relationshps without impacting operations.
E48: Inventory | F48: =CHOOSE(Historical!$I$3,Assumptions!F6,Assumptions!F20,Assumptions!F33) -> 20 | G48: =CHOOSE(Historical!$I$3,Assumptions!G6,Assumptions!G20,Assumptions!G33) -> 18 | H48: =CHOOSE(Historical!$I$3,Assumptions!H6,Assumptions!H20,Assumptions!H33) -> 16 | I48: =CHOOSE(Historical!$I$3,Assumptions!I6,Assumptions!I20,Assumptions!I33) -> 15.5 | J48: =CHOOSE(Historical!$I$3,Assumptions!J6,Assumptions!J20,Assumptions!J33) -> 15 | K48: The 22 days was mainly from Argos as tey have a lot of non-food items that can sit in the warehouse for months. The £120m sale of Argos removes the weight of slow-moving inventory which will tranform the business into a pure-play grocery model once argos has been de-consolidated.
E49: Trade and other receivables | F49: =CHOOSE(Historical!$I$3,Assumptions!F7,Assumptions!F21,Assumptions!F34) -> 5 | G49: =CHOOSE(Historical!$I$3,Assumptions!G7,Assumptions!G21,Assumptions!G34) -> 5 | H49: =CHOOSE(Historical!$I$3,Assumptions!H7,Assumptions!H21,Assumptions!H34) -> 5 | I49: =CHOOSE(Historical!$I$3,Assumptions!I7,Assumptions!I21,Assumptions!I34) -> 5 | J49: =CHOOSE(Historical!$I$3,Assumptions!J7,Assumptions!J21,Assumptions!J34) -> 5 | K49: Flat rate
E50: Trade and other payables | F50: =CHOOSE(Historical!$I$3,Assumptions!F8,Assumptions!F22,Assumptions!F35) -> 64 | G50: =CHOOSE(Historical!$I$3,Assumptions!G8,Assumptions!G22,Assumptions!G35) -> 64 | H50: =CHOOSE(Historical!$I$3,Assumptions!H8,Assumptions!H22,Assumptions!H35) -> 64 | I50: =CHOOSE(Historical!$I$3,Assumptions!I8,Assumptions!I22,Assumptions!I35) -> 64 | J50: =CHOOSE(Historical!$I$3,Assumptions!J8,Assumptions!J22,Assumptions!J35) -> 64 | K50: UK payments practices legislation and amendments is making large corporations purchasers face a strict 60-day contractual ceiling, dragging payables days down
E51: Operating provisions | F51: =CHOOSE(Historical!$I$3,Assumptions!F9,Assumptions!F23,Assumptions!F36) -> -130 | G51: =CHOOSE(Historical!$I$3,Assumptions!G9,Assumptions!G23,Assumptions!G36) -> -120 | H51: =CHOOSE(Historical!$I$3,Assumptions!H9,Assumptions!H23,Assumptions!H36) -> -110 | I51: =CHOOSE(Historical!$I$3,Assumptions!I9,Assumptions!I23,Assumptions!I36) -> -110 | J51: =CHOOSE(Historical!$I$3,Assumptions!J9,Assumptions!J23,Assumptions!J36) -> -110 | K51: £150m structural restructuring program
E52: Depreciation & Amortisation | F52: =CHOOSE(Historical!$I$3,Assumptions!F10,Assumptions!F24,Assumptions!F37) -> 1200 | G52: =CHOOSE(Historical!$I$3,Assumptions!G10,Assumptions!G24,Assumptions!G37) -> 1200 | H52: =CHOOSE(Historical!$I$3,Assumptions!H10,Assumptions!H24,Assumptions!H37) -> 1200 | I52: =CHOOSE(Historical!$I$3,Assumptions!I10,Assumptions!I24,Assumptions!I37) -> 1200 | J52: =CHOOSE(Historical!$I$3,Assumptions!J10,Assumptions!J24,Assumptions!J37) -> 1200 | K52: Management expects it to flat line at 1200m annually
E53: CapEx | F53: =CHOOSE(Historical!$I$3,Assumptions!F11,Assumptions!F25,Assumptions!F38) -> 825 | G53: =CHOOSE(Historical!$I$3,Assumptions!G11,Assumptions!G25,Assumptions!G38) -> 825 | H53: =CHOOSE(Historical!$I$3,Assumptions!H11,Assumptions!H25,Assumptions!H38) -> 825 | I53: =CHOOSE(Historical!$I$3,Assumptions!I11,Assumptions!I25,Assumptions!I38) -> 825 | J53: =CHOOSE(Historical!$I$3,Assumptions!J11,Assumptions!J25,Assumptions!J38) -> 825 | K53: Focus shifts away from expanding store square footage and focus entirely on efficiency and returns
E54: Dividend paid | F54: =CHOOSE(Historical!$I$3,Assumptions!F12,Assumptions!F26,Assumptions!F39) -> 600 | G54: =CHOOSE(Historical!$I$3,Assumptions!G12,Assumptions!G26,Assumptions!G39) -> 600 | H54: =CHOOSE(Historical!$I$3,Assumptions!H12,Assumptions!H26,Assumptions!H39) -> 600 | I54: =CHOOSE(Historical!$I$3,Assumptions!I12,Assumptions!I26,Assumptions!I39) -> 680 | J54: =CHOOSE(Historical!$I$3,Assumptions!J12,Assumptions!J26,Assumptions!J39) -> 730 | K54: Target cover ratio of 1.9x / 53% payout of net income
E55: Tax Rate | F55: =CHOOSE(Historical!$I$3,Assumptions!F13,Assumptions!F27,Assumptions!F40) -> 0.32 | G55: =CHOOSE(Historical!$I$3,Assumptions!G13,Assumptions!G27,Assumptions!G40) -> 0.32 | H55: =CHOOSE(Historical!$I$3,Assumptions!H13,Assumptions!H27,Assumptions!H40) -> 0.32 | I55: =CHOOSE(Historical!$I$3,Assumptions!I13,Assumptions!I27,Assumptions!I40) -> 0.32 | J55: =CHOOSE(Historical!$I$3,Assumptions!J13,Assumptions!J27,Assumptions!J40) -> 0.32
E56: D&A | F56: =CHOOSE(Historical!$I$3,Assumptions!F14,Assumptions!F28,Assumptions!F41) -> 1200 | G56: =CHOOSE(Historical!$I$3,Assumptions!G14,Assumptions!G28,Assumptions!G41) -> 1200 | H56: =CHOOSE(Historical!$I$3,Assumptions!H14,Assumptions!H28,Assumptions!H41) -> 1200 | I56: =CHOOSE(Historical!$I$3,Assumptions!I14,Assumptions!I28,Assumptions!I41) -> 1200 | J56: =CHOOSE(Historical!$I$3,Assumptions!J14,Assumptions!J28,Assumptions!J41) -> 1200

Sheet DCF
F3: Year -2 | G3: Year -1 | H3: Year 0 | I3: Year 1 | J3: Year 2 | K3: Year 3 | L3: Year 4 | M3: Year 5 | N3: Term
B5: Revenue Growth | G5: =G11/F11-1 -> 0.016564303 | H5: =H11/G11-1 -> 0.026699622 | I5: =I11/H11-1 -> -0.12 | J5: =J11/I11-1 -> 0.012 | K5: =K11/J11-1 -> 0.012 | L5: =L11/K11-1 -> 0.012 | M5: =M11/L11-1 -> 0.014 | N5: 0.02
B6: COGS | C6: (% of Revenue) | F6: =-F12/F11 -> 0.93516968 | G6: =-G12/G11 -> 0.93338826 | H6: =-H12/H11 -> 0.93443695 | I6: =-I12/I11 -> 0.934 | J6: =-J12/J11 -> 0.9325 | K6: =-K12/K11 -> 0.931 | L6: =-L12/L11 -> 0.93 | M6: =-M12/M11 -> 0.928 | N6: 0.928
B7: Expenses | C7: (% of Revenue) | F7: =F15/F11 -> 0.04175197 | G7: =G15/G11 -> 0.039454412 | H7: =H15/H11 -> 0.038903914 | I7: =I15/I11 -> 0.043340867 | J7: =J15/J11 -> 0.041732003 | K7: =K15/K11 -> 0.040629029 | L7: =L15/L11 -> 0.039468818 | M7: =M15/M11 -> 0.038260099 | N7: 0.035
B9: Depreciation Growth | G9: =G18/F18-1 -> 0.045546559 | H9: =H18/G18-1 -> 0.0058083253 | I9: =I18/H18-1 -> -0.018286814 | J9: =J18/I18-1 -> 0 | K9: =K18/J18-1 -> 0 | L9: =L18/K18-1 -> 0 | M9: =M18/L18-1 -> 0 | N9: 0
B11: Revenue | F11: =Historical!F7 -> 32238 | G11: =Historical!G7 -> 32772 | H11: =Historical!H7 -> 33647 | I11: =Historical!I7 -> 29609.36 | J11: =Historical!J7 -> 29964.672 | K11: =Historical!K7 -> 30324.248 | L11: =Historical!L7 -> 30688.139 | M11: =Historical!M7 -> 31117.773 | N11: =M11*(1+N5) -> 31740.129
B12: COGS | F12: =Historical!F9 -> -30148 | G12: =Historical!G9 -> -30589 | H12: =Historical!H9 -> -31441 | I12: =Historical!I9 -> -27655.142 | J12: =Historical!J9 -> -27942.057 | K12: =Historical!K9 -> -28231.875 | L12: =Historical!L9 -> -28539.97 | M12: =Historical!M9 -> -28877.294 | N12: =-N11*N6 -> -29454.84
B13: Gross Profit | F13: =F11+F12 -> 2090 | G13: =G11+G12 -> 2183 | H13: =H11+H12 -> 2206 | I13: =I11+I12 -> 1954.2178 | J13: =J11+J12 -> 2022.6154 | K13: =K11+K12 -> 2092.3731 | L13: =L11+L12 -> 2148.1698 | M13: =M11+M12 -> 2240.4797 | N13: =N11+N12 -> 2285.2893
B15: Expenses | F15: =-SUM(Historical!F13:F14) -> 1346 | G15: =-SUM(Historical!G13:G14) -> 1293 | H15: =-SUM(Historical!H13:H14) -> 1309 | I15: =-SUM(Historical!I13:I14) -> 1283.2953 | J15: =-SUM(Historical!J13:J14) -> 1250.4858 | K15: =-SUM(Historical!K13:K14) -> 1232.0448 | L15: =-SUM(Historical!L13:L14) -> 1211.2246 | M15: =-SUM(Historical!M13:M14) -> 1190.5691 | N15: =N11*N7 -> 1110.9045
B16: EBIT | F16: =F13-F15 -> 744 | G16: =G13-G15 -> 890 | H16: =H13-H15 -> 897 | I16: =I13-I15 -> 670.92243 | J16: =J13-J15 -> 772.12959 | K16: =K13-K15 -> 860.32838 | L16: =L13-L15 -> 936.94518 | M16: =M13-M15 -> 1049.9106 | N16: =N13-N15 -> 1174.3848
B18: Depreciation | F18: ='Supporting Schedules'!E75 -> 988 | G18: ='Supporting Schedules'!F75 -> 1033 | H18: ='Supporting Schedules'!G75 -> 1039 | I18: ='Supporting Schedules'!H75 -> 1020 | J18: ='Supporting Schedules'!I75 -> 1020 | K18: ='Supporting Schedules'!J75 -> 1020 | L18: ='Supporting Schedules'!K75 -> 1020 | M18: ='Supporting Schedules'!L75 -> 1020 | N18: =M18*(1+N9) -> 1020
B19: EBITDA | F19: =F16+F18 -> 1732 | G19: =G16+G18 -> 1923 | H19: =H16+H18 -> 1936 | I19: =I16+I18 -> 1690.9224 | J19: =J16+J18 -> 1792.1296 | K19: =K16+K18 -> 1880.3284 | L19: =L16+L18 -> 1956.9452 | M19: =M16+M18 -> 2069.9106 | N19: =N16+N18 -> 2194.3848
B21: Tax Rate | F21: =Historical!F22 -> 0.37014315 | G21: =Historical!G22 -> 0.30642504 | H21: =Historical!H22 -> 0.33117932 | I21: =Historical!I22 -> 0.32 | J21: =Historical!J22 -> 0.32 | K21: =Historical!K22 -> 0.32 | L21: =Historical!L22 -> 0.32 | M21: =Historical!M22 -> 0.32 | N21: 0.32
B22: Current Tax | F22: =-Historical!F20 -> 181 | G22: =-Historical!G20 -> 186 | H22: =-Historical!H20 -> 205 | I22: =-Historical!I20 -> 204.35515 | J22: =-Historical!J20 -> 236.43476 | K22: =-Historical!K20 -> 270.13759 | L22: =-Historical!L20 -> 296.49733 | M22: =-Historical!M20 -> 334.65034 | N22: =N16*N21 -> 375.80312
B27: UNLEVERED FREE CASH FLOW
F30: Year -2 | G30: Year -1 | H30: Year 0 | I30: Year 1 | J30: Year 2 | K30: Year 3 | L30: Year 4 | M30: Year 5 | N30: Term
B31: Unlevered Free Cash Flow
B32: EBIT | F32: =F16 -> 744 | G32: =G16 -> 890 | H32: =H16 -> 897 | I32: =I16 -> 670.92243 | J32: =J16 -> 772.12959 | K32: =K16 -> 860.32838 | L32: =L16 -> 936.94518 | M32: =M16 -> 1049.9106 | N32: =N16 -> 1174.3848
B33: Tax Rate | F33: =F21 -> 0.37014315 | G33: =G21 -> 0.30642504 | H33: =H21 -> 0.33117932 | I33: =I21 -> 0.32 | J33: =J21 -> 0.32 | K33: =K21 -> 0.32 | L33: =L21 -> 0.32 | M33: =M21 -> 0.32 | N33: 0.32
B34: NOPAT | F34: =F32*(1-F33) -> 468.6135 | G34: =G32*(1-G21) -> 617.28171 | H34: =H32*(1-H21) -> 599.93215 | I34: =I32*(1-I21) -> 456.22725 | J34: =J32*(1-J21) -> 525.04812 | K34: =K32*(1-K21) -> 585.0233 | L34: =L32*(1-L21) -> 637.12272 | M34: =M32*(1-M21) -> 713.9392 | N34: =N32*(1-N33) -> 798.58164
B35: D&A | F35: =Historical!F86 -> 1160 | G35: =Historical!G86 -> 1215 | H35: =Historical!H86 -> 1238 | I35: =Historical!I86 -> 1200 | J35: =Historical!J86 -> 1200 | K35: =Historical!K86 -> 1200 | L35: =Historical!L86 -> 1200 | M35: =Historical!M86 -> 1200 | N35: 1200
B36: Capital Expenditure | F36: =-'Supporting Schedules'!E74 -> -1559 | G36: =-'Supporting Schedules'!F74 -> -825 | H36: =-'Supporting Schedules'!G74 -> -843 | I36: =-'Supporting Schedules'!H74 -> -828.75 | J36: =-'Supporting Schedules'!I74 -> -828.75 | K36: =-'Supporting Schedules'!J74 -> -828.75 | L36: =-'Supporting Schedules'!K74 -> -828.75 | M36: =-'Supporting Schedules'!L74 -> -828.75 | N36: -825
B37: Change in Working Capital | F37: ='Supporting Schedules'!E69 -> -244 | G37: ='Supporting Schedules'!F69 -> -506 | H37: ='Supporting Schedules'!G69 -> -86 | I37: ='Supporting Schedules'!H69 -> 228.8371 | J37: ='Supporting Schedules'!I69 -> -172.82685 | K37: ='Supporting Schedules'!J69 -> -176.29455 | L37: ='Supporting Schedules'!K69 -> -74.62756 | M37: ='Supporting Schedules'!L69 -> -78.495048 | N37: -85
B38: Lease liability repayments | F38: =Historical!F106 -> -507 | G38: =Historical!G106 -> -487 | H38: =Historical!H106 -> -504 | I38: =Historical!I106 -> -490.4 | J38: =Historical!J106 -> -492.832 | K38: =Historical!K106 -> -495.45856 | L38: =Historical!L106 -> -498.29524 | M38: =Historical!M106 -> -501.35886 | N38: -610
B39: Unlevered Free Cash Flow | F39: =F34+F35+F36-F37+F38 -> -193.3865 | G39: =G34+G35+G36-G37+G38 -> 1026.2817 | H39: =H34+H35+H36-H37+H38 -> 576.93215 | I39: =I34+I35+I36-I37+I38 -> 108.24015 | J39: =J34+J35+J36-J37+J38 -> 576.29297 | K39: =K34+K35+K36-K37+K38 -> 637.1093 | L39: =L34+L35+L36-L37+L38 -> 584.70504 | M39: =M34+M35+M36-M37+M38 -> 662.32538 | N39: =N34+N35+N36-N37+N38 -> 648.58164
B43: DISCOUNTED CASH FLOW SCHEDULE
I45: Year 1 | J45: Year 2 | K45: Year 3 | L45: Year 4 | M45: Year 5 | N45: Term
B47: Unlevered Free Cash Flow | I47: =I39 -> 108.24015 | J47: =J39 -> 576.29297 | K47: =K39 -> 637.1093 | L47: =L39 -> 584.70504 | M47: =M39 -> 662.32538 | N47: =N39 -> 648.58164
B48: EBITDA | N48: =N19 -> 2194.3848
B51: UNDISCOUNTED CASH FLOW
B52: Discrete Forecast | I52: =I47 -> 108.24015 | J52: =J47 -> 576.29297 | K52: =K47 -> 637.1093 | L52: =L47 -> 584.70504 | M52: =M47 -> 662.32538 | N52: =N47 -> 648.58164
B53: Terminal Value | I53: 0 | J53: 0 | K53: 0 | L53: 0 | M53: 0 | N53: =(N52*(1+D61))/(D62-D61) -> 8682.387
B54: Total Cash Flow | I54: =SUM(I52:I53) -> 108.24015 | J54: =SUM(J52:J53) -> 576.29297 | K54: =SUM(K52:K53) -> 637.1093 | L54: =SUM(L52:L53) -> 584.70504 | M54: =SUM(M52:M53) -> 662.32538 | N54: =SUM(N52:N53) -> 9330.9687
B58: ASSUMPTIONS | G58: ENTERPRISE VALUE | K58: EQUITY VALUE PER SHARE
B59: First Year of Forecast | D59: 2026 | G59: PV of Discrete | I59: =NPV(D62,I52,J52,K52,L52,M52) -> 1885.3757 | K59: Equity Value | N59: =I75 -> 7376.675
B60: Terminal Multiple | G60: PV of Terminal | I60: =NPV(D62,0,0,0,0,N53) -> 5485.2993 | K60: Shares Outstanding | N60: =D80 -> 2182
B61: Growth Rate | D61: =2%+Q75 -> 0.02 | G61: Enterprise Value | I61: =I59+I60 -> 7370.675 | K61: Instrinsic Value per Share | N61: =N59/N60 -> 3.3806943
B62: Discount Rate | D62: =(D82*D69)+(D88*D75)+T75 -> 0.096194861
R63: Share Price Sensitivity
T64: Growth Rate
B65: COST OF EQUITY | G65: NET DEBT | S65: =DCF!N61 -> 3.3806943 | T65: 0 | U65: =T65+1% -> 0.01 | V65: =U65+0.5% -> 0.015 | W65: =V65+0.5% -> 0.02 | X65: =W65+0.5% -> 0.025 | Y65: =X65+0.5% -> 0.03 | Z65: =Y65+0.5% -> 0.035
B66: Risk-free rate (UK 10y) | D66: 0.0499 | G66: Short-term debt | I66: =Historical!H54 -> 80 | R66: WACC | S66: =6.6% -> 0.066 | T66: 4.2225207 | U66: 4.8453214 | V66: 5.2483101 | W66: 5.7389051 | X66: 6.3491574 | Y66: 7.1289241 | Z66: 8.1602286
B67: Beta | D67: 1.01 | G67: Long-term debt | I67: =Historical!H65 -> 981 | S67: =S66+1.5% -> 0.081 | T67: 3.3936375 | U67: 3.7721357 | V67: 4.0043959 | W67: 4.2747316 | X67: 4.5933415 | Y67: 4.9744239 | Z67: 5.4383504
B68: Market risk premium | D68: 0.055 | G68: Cash and cash equivalent | I68: =Historical!H47 -> 1067 | S68: =S67+1.5% -> 0.096 | T68: 2.8251945 | U68: 3.0747103 | V68: 3.2225715 | W68: 3.3898881 | X68: 3.5807705 | Y68: 3.8005744 | Z68: 4.0564117
B69: CAPM | D69: =D66*D67+D68 -> 0.105399 | G69: Net debt | I69: =(I66+I67)-I68 -> -6 | S69: =S68+1.5% -> 0.111 | T69: 2.4115416 | U69: 2.5855657 | V69: 2.6861734 | W69: 2.7978368 | X69: 2.9224844 | Y69: 3.0625206 | Z69: 3.2209825
S70: =S69+1.5% -> 0.126 | T70: 2.0973426 | U70: 2.2238534 | V70: 2.2956569 | W70: 2.3742342 | X70: 2.4605916 | Y70: 2.5559444 | Z70: 2.6617756
B72: AFTER-TAX COST OF DEBT | G72: EQUITY VALUE
B73: Interest Rate on Debt | D73: ='Supporting Schedules'!G11/'Supporting Schedules'!G10 -> 0.047125353 | G73: Enterprise Value | I73: =I61 -> 7370.675 | Q73: Growth Rate +/-2% | T73: Discount Rate +/-2% | W73: Revenue Growth +/-2% | Z73: Admin Expenses +/-2%
B74: Tax Rate | D74: =I21 -> 0.32 | G74: Less: Net Debt | I74: =-I69 -> 6 | Q74: Change | R74: £/Share | T74: Change | U74: £/Share | W74: Change | X74: £/Share | Z74: Change | AA74: £/Share
B75: After-tax Cost of Debt | D75: =D73*(1-D74) -> 0.03204524 | G75: Equity Value | I75: =SUM(I73:I74) -> 7376.675 | Q75: 0 | R75: =N61 -> 3.3806943 | T75: 0 | U75: =N61 -> 3.3806943 | W75: 0 | X75: =N61 -> 3.3806943 | Z75: 0 | AA75: =N61 -> 3.3806943
Q76: -0.02 | R76: 2.8189854 | T76: -0.02 | U76: 4.6584703 | W76: -0.02 | X76: 2.8154846 | Z76: -0.02 | AA76: -0.02
Q77: 0.02 | R77: 4.3422326 | T77: 0.02 | U77: 2.6360713 | W77: 0.02 | X77: 3.9883461 | Z77: 0.02 | AA77: 0.02
B78: MARKET VALUE OF EQUITY AND DEBT | G78: AVERAGE MATURITY
B79: Share price (13/08/26) | D79: 3.389 | H79: 2026 | I79: Outstanding | J79: Maturity | K79: YTM | Q79: Assumptions | T79: -5% ∆ | U79: Abs Change | V79: Rank | W79: Output | X79: Driver | Z79: Pos | AA79: Neg
B80: Shares Outstanding | D80: 2182 | G80: Revolving Credit | I80: 0 | J80: 2029 | K80: =J80-$H$79 -> 3 | L80: =I80*K80 -> 0 | Q80: =Q73 -> Growth Rate +/-2% | T80: =R76/R75-1 -> -0.16615193 | U80: =ABS(T80) -> 0.16615193 | V80: 1 | W80: =SMALL($U$80:$U$83,V80) -> 0.16615193 | X80: =INDEX($Q$80:$W$83, MATCH(W80,$U$80:$U$83,0),MATCH($Q$80,$Q$80:$W$80)) -> Growth Rate +/-2% | Z80: =W80 -> 0.16615193 | AA80: =-Z80 -> -0.16615193
B81: Market Value of Equity | D81: =D79*D80 -> 7394.798 | G81: Revolving Credit | I81: 0 | J81: 2028 | K81: =J81-$H$79 -> 2 | L81: =I81*K81 -> 0 | Q81: =T73 -> Discount Rate +/-2% | T81: =U76/U75-1 -> 0.3779626 | U81: =ABS(T81) -> 0.3779626 | V81: =V80+1 -> 2 | W81: =SMALL($U$80:$U$83,V81) -> 0.16718746 | X81: =INDEX($Q$80:$W$83, MATCH(W81,$U$80:$U$83,0),MATCH($Q$80,$Q$80:$W$80)) -> Revenue Growth +/-2% | Z81: =W81 -> 0.16718746 | AA81: =-Z81 -> -0.16718746
B82: Weight | D82: =D81/(D81+D87) -> 0.87452397 | G82: Unsecured Bond | I82: 250 | J82: 2030 | K82: =J82-$H$79 -> 4 | L82: =I82*K82 -> 1000 | Q82: =W73 -> Revenue Growth +/-2% | T82: =X76/X75-1 -> -0.16718746 | U82: =ABS(T82) -> 0.16718746 | V82: =V81+1 -> 3 | W82: =SMALL($U$80:$U$83,V82) -> 0.3779626 | X82: =INDEX($Q$80:$W$83, MATCH(W82,$U$80:$U$83,0),MATCH($Q$80,$Q$80:$W$80)) -> Discount Rate +/-2% | Z82: =W82 -> 0.3779626 | AA82: =-Z82 -> -0.3779626
B83: Interest Expense | D83: ='Supporting Schedules'!G11 -> 50 | G83: Unsecured Bond | I83: 300 | J83: 2035 | K83: =J83-$H$79 -> 9 | L83: =I83*K83 -> 2700 | Q83: =Z73 -> Admin Expenses +/-2% | T83: =AA76/AA75-1 -> -1.0059159 | U83: =ABS(T83) -> 1.0059159 | V83: =V82+1 -> 4 | W83: =SMALL($U$80:$U$83,V83) -> 1.0059159 | X83: =INDEX($Q$80:$W$83, MATCH(W83,$U$80:$U$83,0),MATCH($Q$80,$Q$80:$W$80)) -> Admin Expenses +/-2% | Z83: =W83 -> 1.0059159 | AA83: =-Z83 -> -1.0059159
B84: Current Cost of Debt | D84: =D73 -> 0.047125353 | G84: Bank Tier 2 Capital | I84: 125 | J84: 2028 | K84: =J84-$H$79 -> 2 | L84: =I84*K84 -> 250
B85: Total Debt | D85: =I66+I67 -> 1061 | G85: Loan | I85: 386 | J85: 2031 | K85: =J85-$H$79 -> 5 | L85: =I85*K85 -> 1930
B86: Average Maturity (years) | D86: =L86/D85 -> 5.5419416 | G86: Total | L86: =SUM(L80:L85) -> 5880 | R86: Impact on Share Price by Change in Assumption
B87: Market Value of Debt | D87: =-PV(D84,D86,D83,D85) -> 1061
B88: Weight | D88: =D87/(D81+D87) -> 0.12547603

Sheet Supporting Schedules
B1: J Sainsbury plc – Supporting Schedules
C3: 2022A | D3: 2023A | E3: 2024A | F3: 2025A* | G3: 2026A | H3: 2027E | I3: 2028E | J3: 2029E | K3: 2030E | L3: 2031E
B5: Borrowings Schedule
B6: Opening borrowings | C6: 1104 | D6: =C10 -> 761 | E6: =D10 -> 656 | F6: =E10 -> 1195 | G6: =F10 -> 1114 | H6: =G10 -> 1061 | I6: =H10 -> 983.8 | J6: =I10 -> 781.6 | K6: =J10 -> 704.4 | L6: =K10 -> 627.2
B7: New borrowings | C7: =Historical!D101 -> 0 | D7: =Historical!E101 -> 0 | E7: =Historical!F101 -> 575 | F7: =Historical!G101 -> 544 | G7: =Historical!H101 -> 0 | H7: =SUM(H15,H19,H22,H25,H29,H33) -> 0 | I7: =SUM(I15,I19,I22,I25,I29,I33) -> 0 | J7: =SUM(J15,J19,J22,J25,J29,J33) -> 0 | K7: =SUM(K15,K19,K22,K25,K29,K33) -> 250 | L7: =SUM(L15,L19,L22,L25,L29,L33) -> 0
B8: Repayments | C8: =Historical!D102 -> -248 | D8: =Historical!E102 -> -95 | E8: =Historical!F102 -> -41 | F8: =Historical!G102 -> -623 | G8: =Historical!H102 -> -59 | H8: =SUM(H16,H20,H23,H26,H30,H34) -> -77.2 | I8: =SUM(I16,I20,I23,I26,I30,I34) -> -202.2 | J8: =SUM(J16,J20,J23,J26,J30,J34) -> -77.2 | K8: =SUM(K16,K20,K23,K26,K30,K34) -> -327.2 | L8: =SUM(L16,L20,L23,L26,L30,L34) -> -77.2
B9: Other / classification changes | C9: =C10-SUM(C6:C8) -> -95 | D9: =D10-SUM(D6:D8) -> -10 | E9: =E10-SUM(E6:E8) -> 5 | F9: =F10-SUM(F6:F8) -> -2 | G9: =G10-SUM(G6:G8) -> 6 | H9: 0 | I9: 0 | J9: 0 | K9: 0 | L9: 0
B10: Closing borrowings | C10: =Historical!D132 -> 761 | D10: =Historical!E132 -> 656 | E10: =Historical!F132 -> 1195 | F10: =Historical!G132 -> 1114 | G10: =Historical!H132 -> 1061 | H10: =SUM(H6:H9) -> 983.8 | I10: =SUM(I6:I9) -> 781.6 | J10: =SUM(J6:J9) -> 704.4 | K10: =SUM(K6:K9) -> 627.2 | L10: =SUM(L6:L9) -> 550
B11: Interest Expense | G11: 50 | H11: =SUM(H17,H27,H31,H35) -> 51.3735 | I11: =SUM(I17,I27,I31,I35) -> 49.57518 | J11: =SUM(J17,J27,J31,J35) -> 35.15326 | K11: =SUM(K17,K27,K31,K35) -> 33.33134 | L11: =SUM(L17,L27,L31,L35) -> 29.375
B13: Debt
B14: Loan (due in 2031 at a 2.36% rate (principal and interst rae uplifted annually by RPI subject to a cap at 5% and floor at 0%))
B15: New Borrowings | C15: 0 | D15: 0 | E15: 0 | F15: 0 | G15: 0 | H15: 0 | I15: 0 | J15: 0 | K15: 0 | L15: 0
B16: Repayments | C16: -45 | D16: -48 | E16: -41 | F16: -52 | G16: -59 | H16: =-386/5 -> -77.2 | I16: =-(386+H16)/4 -> -77.2 | J16: =-(386+I16)/4 -> -77.2 | K16: =-(386+J16)/4 -> -77.2 | L16: =-(386+K16)/4 -> -77.2
B17: Interest | H17: =385*2.36% -> 9.086 | I17: =(386+I16)*2.36% -> 7.28768 | J17: =(386+J16+I16)*2.36% -> 5.46576 | K17: =(386+K16+J16+I16)*2.36% -> 3.64384
B18: Revolving Credit (Facility A due in 2029: 500m)
B19: New Borrowings | C19: 0 | D19: 0 | E19: 0 | F19: 0 | G19: 0 | H19: 0 | I19: 0 | J19: 0
B20: Repayments | C20: 0 | D20: 0 | E20: 0 | F20: 0 | G20: 0 | H20: 0 | I20: 0 | J20: 0
B21: Revolving Credit (Facility B due in 2028: 500m)
B22: New Borrowings | C22: 0 | D22: 0 | E22: 0 | F22: 0 | G22: 0 | H22: 0 | I22: 0
B23: Repayments | C23: 0 | D23: 0 | E23: 0 | F23: 0 | G23: 0 | H23: 0 | I23: 0
B24: Unsecured Bond (£250m 5-year due in 2030 5.125%)
B25: New Borrowings | C25: 0 | D25: 0 | E25: 0 | F25: 250 | G25: 0 | H25: 0 | I25: 0 | J25: 0 | K25: 250
B26: Repayments | C26: 0 | D26: 0 | E26: 0 | F26: 0 | G26: 0 | H26: 0 | I26: 0 | J26: 0 | K26: -250
B27: Interest | G27: =250*5.125% -> 12.8125 | H27: =250*5.125% -> 12.8125 | I27: =250*5.125% -> 12.8125 | J27: =250*5.125% -> 12.8125 | K27: =250*5.125% -> 12.8125 | L27: =250*5% -> 12.5
B28: Unsecured Bond (£300m 10-year due in 2035 5.625%)
B29: New Borrowings | C29: 0 | D29: 0 | E29: 0 | F29: 300 | G29: 0 | H29: 0 | I29: 0 | J29: 0 | K29: 0 | L29: 0
B30: Repayments | C30: 0 | D30: 0 | E30: 0 | F30: 0 | G30: 0 | H30: 0 | I30: 0 | J30: 0 | K30: 0 | L30: 0
B31: Interest | G31: =300*5.625% -> 16.875 | H31: =300*5.625% -> 16.875 | I31: =300*5.625% -> 16.875 | J31: =300*5.625% -> 16.875 | K31: =300*5.625% -> 16.875 | L31: =300*5.625% -> 16.875
B32: Bank Tier 2 Capital (£120m 10.5% due in 2028)
B33: New Borrowings | C33: 0 | D33: 120 | E33: 0 | F33: 0 | G33: 0 | H33: 0 | I33: 0
B34: Repayments | C34: 0 | D34: -175 | E34: 0 | F34: 0 | G34: 0 | H34: 0 | I34: -125
B35: Interest | E35: =120*10.5% -> 12.6 | F35: =120*10.5% -> 12.6 | G35: =120*10.5% -> 12.6 | H35: =120*10.5% -> 12.6 | I35: =120*10.5% -> 12.6
B37: Current liabilities | H37: =386+H16 -> 308.8 | I37: =H37+I16 -> 231.6 | J37: =I37+J16 -> 154.4 | K37: =J37+K16 -> 77.2 | L37: =K37+L16 -> 0
B38: Non-current liabilities | H38: =F25+F29+D33+H37 -> 978.8 | I38: =F25+F29+I37 -> 781.6 | J38: =F25+F29+J37 -> 704.4 | K38: =F29+K25+K37 -> 627.2 | L38: =F29+K25 -> 550
B41: Lease Liability Schedule
B42: Opening lease liabilities | C42: 5834 | D42: =C45 -> 6621 | E42: =D45 -> 6489 | F42: =E45 -> 5354 | G42: =F45 -> 5494 | H42: =G45-300 -> 5240 | I42: =H45 -> 5179.2 | J42: =I45 -> 5113.536 | K42: =J45 -> 5042.6189 | L42: =K45 -> 4966.0284
B43: Principal repayments | C43: =-(C47-C48) -> -493 | D43: =-(D47-D48) -> -514 | E43: =-(E47-E48) -> -507 | F43: =-(F47-F48) -> -487 | G43: =-(G47-G48) -> -504 | H43: =-(H47-H48) -> -490.4 | I43: =-(I47-I48) -> -492.832 | J43: =-(J47-J48) -> -495.45856 | ... L43: =-(L47-L48) -> -501.35886
B44: New leases / interest / remeasurements / other | C44: =C45-SUM(C42:C43) -> 1280 | D44: =D45-SUM(D42:D43) -> 382 | E44: =E45-SUM(E42:E43) -> -628 | F44: =F45-SUM(F42:F43) -> 627 | G44: =G45-SUM(G42:G43) -> 550 | H44: =220+H48 -> 429.6 | I44: =220+I48 -> 427.168 | J44: =220+J48 -> 424.54144 | K44: =220+K48 -> 421.70476 | L44: =220+L48 -> 418.64114
B45: Closing lease liabilities | C45: =Historical!D133 -> 6621 | D45: =Historical!E133 -> 6489 | E45: =Historical!F133 -> 5354 | F45: =Historical!G133 -> 5494 | G45: =Historical!H133 -> 5540 | H45: =SUM(H42:H44) -> 5179.2 | I45: =SUM(I42:I44) -> 5113.536 | J45: =SUM(J42:J44) -> 5042.6189 | K45: =SUM(K42:K44) -> 4966.0284 | L45: =SUM(L42:L44) -> 4883.3107
B46: Lease liabilities / EBITDA | C46: =IFERROR(C45/Historical!D126,"") -> 2.7866162 | D46: =IFERROR(D45/Historical!E126,"") -> 3.6661017 | E46: =IFERROR(E45/Historical!F126,"") -> 2.8119748 | F46: =IFERROR(F45/Historical!G126,"") -> 2.6099762 | G46: =IFERROR(G45/Historical!H126,"") -> 2.5948478 | H46: =IFERROR(H45/Historical!I126,"") -> 2.7682602 | I46: =IFERROR(I45/Historical!J126,"") -> 2.5929006 | J46: =IFERROR(J45/Historical!K126,"") -> 2.4474831 | ... L46: =IFERROR(L45/Historical!M126,"") -> 2.1704465
B47: Payments | C47: 774 | D47: 781 | E47: 771 | F47: 759 | G47: 782 | H47: 700 | I47: 700 | J47: 700 | K47: 700 | L47: 700
B48: Interest Expense | C48: 281 | D48: 267 | E48: 264 | F48: 272 | G48: 278 | H48: =H42*4% -> 209.6 | I48: =I42*4% -> 207.168 | J48: =J42*4% -> 204.54144 | K48: =K42*4% -> 201.70476 | L48: =L42*4% -> 198.64114
B50: Current lease liability | C50: =Historical!D55 -> 526 | D50: =Historical!E55 -> 1533 | E50: =Historical!F55 -> 515 | F50: =Historical!G55 -> 483 | G50: =Historical!H55 -> 505 | H50: =-H43+1 -> 491.4 | I50: =-I43+1 -> 493.832 | J50: =-J43+1 -> 496.45856 | K50: =-K43+1 -> 499.29524 | L50: =-L43+1 -> 502.35886
B51: Non-current lease liability | C51: =Historical!D66 -> 6095 | D51: =Historical!E66 -> 4956 | E51: =Historical!F66 -> 4839 | F51: =Historical!G66 -> 5011 | G51: =Historical!H66 -> 5035 | H51: =H45-H50 -> 4687.8 | I51: =I45-I50 -> 4619.704 | J51: =J45-J50 -> 4546.1603 | K51: =K45-K50 -> 4466.7331 | L51: =L45-L50 -> 4380.9518
B54: Right-of-Use Schedule
B55: Opening RoU Assets | C55: 4747 | D55: =C60 -> 5560 | E55: =D60 -> 5345 | F55: =E60 -> 4296 | G55: =F60 -> 4455 | H55: =G60 -> 4486 | I55: =H60 -> 4167.68 | J55: =I60 -> 3887.5584 | K55: =J60 -> 3641.0514 | L55: =K60 -> 3424.1252
B56: New Leases and Modifications | C56: 1294 | D56: 398 | E56: 438 | F56: 676 | G56: 572 | H56: =220 -> 220 | I56: =220 -> 220 | J56: =220 -> 220 | K56: =220 -> 220 | L56: =220 -> 220
B57: Impairment Loss | C57: 3 | D57: 143 | E57: 6 | F57: 16 | G57: 11 | H57: 0 | I57: 0 | J57: 0 | K57: 0 | L57: 0
B58: Depreciation Expense | C58: 478 | D58: 470 | E58: 450 | F58: 501 | G58: 530 | H58: =H55*12% -> 538.32 | I58: =I55*12% -> 500.1216 | J58: =J55*12% -> 466.50701 | K58: =K55*12% -> 436.92617 | L58: =L55*12% -> 410.89503
B59: Deregonised as part of asset acquistion | C59: 0 | D59: 0 | E59: 1031 | F59: 0 | G59: 0 | H59: 0 | I59: 0 | J59: 0 | K59: 0 | L59: 0
B60: Closing RoU Assets | C60: =C55+C56-C57-C58 -> 5560 | D60: =D55+D56-D57-D58 -> 5345 | E60: =E55+E56-E57-E58-E59 -> 4296 | F60: =F55+F56-F57-F58 -> 4455 | G60: =G55+G56-G57-G58 -> 4486 | H60: =H55+H56-H57-H58 -> 4167.68 | I60: =I55+I56-I57-I58 -> 3887.5584 | J60: =J55+J56-J57-J58 -> 3641.0514 | K60: =K55+K56-K57-K58 -> 3424.1252 | L60: =L55+L56-L57-L58 -> 3233.2302
B63: Retail Working Capital Snapshot
B64: Inventories | C64: =Historical!D41 -> 1797 | D64: =Historical!E41 -> 1899 | E64: =Historical!F41 -> 1927 | F64: =Historical!G41 -> 1946 | G64: =Historical!H41 -> 1987 | H64: =-Historical!I9*Assumptions!F48/365 -> 1515.3503 | I64: =-Historical!J9*Assumptions!G48/365 -> 1377.9645 | J64: =-Historical!K9*Assumptions!H48/365 -> 1237.5617 | K64: =-Historical!L9*Assumptions!I48/365 -> 1211.9713 | L64: =-Historical!M9*Assumptions!J48/365 -> 1186.7381
B65: Trade and other receivables – current | C65: =Historical!D42 -> 683 | D65: =Historical!E42 -> 627 | E65: =Historical!F42 -> 582 | F65: =Historical!G42 -> 572 | G65: =Historical!H42 -> 431 | H65: =Historical!I7*Assumptions!F49/365 -> 405.60767 | I65: =Historical!J7*Assumptions!G49/365 -> 410.47496 | J65: =Historical!K7*Assumptions!H49/365 -> 415.40066 | K65: =Historical!L7*Assumptions!I49/365 -> 420.38547 | L65: =Historical!M7*Assumptions!J49/365 -> 426.27087
B66: Trade payables – current | C66: =-Historical!D52 -> -4546 | D66: =-Historical!E52 -> -4837 | E66: =-Historical!F52 -> -5091 | F66: =-Historical!G52 -> -5489 | G66: =-Historical!H52 -> -5565 | H66: =Historical!I9*Assumptions!F50/365 -> -4849.1208 | I66: =Historical!J9*Assumptions!G50/365 -> -4899.4292 | J66: =Historical!K9*Assumptions!H50/365 -> -4950.2466 | K66: =Historical!L9*Assumptions!I50/365 -> -5004.2686 | L66: =Historical!M9*Assumptions!J50/365 -> -5063.4159
B67: Provisions – current | C67: =-Historical!D59 -> -100 | D67: =-Historical!E59 -> -140 | E67: =-Historical!F59 -> -113 | F67: =-Historical!G59 -> -230 | G67: =-Historical!H59 -> -140 | H67: =Assumptions!F51 -> -130 | I67: =Assumptions!G51 -> -120 | J67: =Assumptions!H51 -> -110 | K67: =Assumptions!I51 -> -110 | L67: =Assumptions!J51 -> -110
B68: Net operating working capital | C68: =SUM(C64:C67) -> -2166 | D68: =SUM(D64:D67) -> -2451 | E68: =SUM(E64:E67) -> -2695 | F68: =SUM(F64:F67) -> -3201 | G68: =SUM(G64:G67) -> -3287 | H68: =SUM(H64:H67) -> -3058.1629 | I68: =SUM(I64:I67) -> -3230.9897 | J68: =SUM(J64:J67) -> -3407.2843 | ... L68: =SUM(L64:L67) -> -3560.4069
B69: Change in NWC | D69: =D68-C68 -> -285 | E69: =E68-D68 -> -244 | F69: =F68-E68 -> -506 | G69: =G68-F68 -> -86 | H69: =H68-G68 -> 228.8371 | I69: =I68-H68 -> -172.82685 | J69: =J68-I68 -> -176.29455 | K69: =K68-J68 -> -74.62756 | L69: =L68-K68 -> -78.495048
B72: Depreciation Schedule
B73: PPE Opening | C73: 9740 | D73: =C76 -> 9365 | E73: =D76 -> 9067 | F73: =E76 -> 9638 | G73: =F76 -> 9430 | H73: =G76 -> 9234 | I73: =H76 -> 9042.75 | J73: =I76 -> 8851.5 | K73: =J76 -> 8660.25 | L73: =K76 -> 8469
B74: Capex | C74: =-Historical!D93-Historical!D95 -> 694 | D74: =-Historical!E93-Historical!E95 -> 738 | E74: =-Historical!F93-Historical!F95 -> 1559 | F74: =-Historical!G93-Historical!G95 -> 825 | G74: =-Historical!H93-Historical!H95 -> 843 | H74: =-SUM(Historical!I93:I95) -> 828.75 | I74: =-SUM(Historical!J93:J95) -> 828.75 | J74: =-SUM(Historical!K93:K95) -> 828.75 | K74: =-SUM(Historical!L93:L95) -> 828.75 | L74: =-SUM(Historical!M93:M95) -> 828.75
B75: Depreciation | C75: 1069 | D75: 1036 | E75: 988 | F75: 1033 | G75: 1039 | H75: =Historical!I86*85% -> 1020 | I75: =Historical!J86*85% -> 1020 | J75: =Historical!K86*85% -> 1020 | K75: =Historical!L86*85% -> 1020 | L75: =Historical!M86*85% -> 1020
B76: PPE Closing | C76: =C73+C74-C75 -> 9365 | D76: =D73+D74-D75 -> 9067 | E76: =E73+E74-E75 -> 9638 | F76: =F73+F74-F75 -> 9430 | G76: =G73+G74-G75 -> 9234 | H76: =H73+H74-H75 -> 9042.75 | I76: =I73+I74-I75 -> 8851.5 | J76: =J73+J74-J75 -> 8660.25 | ... L76: =L73+L74-L75 -> 8277.75
B79: Intangible Assets Schedule
B80: Opening Cost | C80: 1554 | D80: =C84 -> 1730 | E80: =D84 -> 1757 | F80: =E84 -> 1880 | G80: =F84 -> 1894 | H80: =G84 -> 1688 | I80: =H84 -> 1793 | J80: =I84 -> 1898 | K80: =J84 -> 2003 | L80: =K84 -> 2108
B81: Additions | C81: 278 | D81: 213 | E81: 178 | F81: 208 | G81: 230 | H81: 205 | I81: 205 | J81: 205 | K81: 205 | L81: 205
B82: Disposals | C82: -102 | D82: -186 | E82: -55 | F82: -117 | G82: -436 | H82: -100 | I82: -100 | J82: -100 | K82: -100 | L82: -100
B83: Transfer to assets held for sale | C83: 0 | D83: 0 | E83: 0 | F83: -77 | G83: 0 | H83: 0 | I83: 0 | J83: 0 | K83: 0 | L83: 0
B84: Closing Cost | C84: =SUM(C80:C83) -> 1730 | D84: =SUM(D80:D83) -> 1757 | E84: =SUM(E80:E83) -> 1880 | F84: =SUM(F80:F83) -> 1894 | G84: =SUM(G80:G83) -> 1688 | H84: =SUM(H80:H83) -> 1793 | I84: =SUM(I80:I83) -> 1898 | J84: =SUM(J80:J83) -> 2003 | ... L84: =SUM(L80:L83) -> 2213
B86: Opening accumulate amortisation and impairment | C86: 640 | D86: =C91 -> 724 | E86: =D91 -> 733 | F86: =E91 -> 1074 | G86: =F91 -> 1087 | H86: =G91 -> 850 | I86: =H91 -> 945 | J86: =I91 -> 1059 | K86: =J91 -> 1195.8 | L86: =K91 -> 1359.96
B87: Amortisation expense | C87: 151 | D87: 172 | E87: 189 | F87: 182 | G87: 199 | H87: =H86*20% -> 170 | I87: =I86*20% -> 189 | J87: =J86*20% -> 211.8 | K87: =K86*20% -> 239.16 | L87: =L86*20% -> 271.992
B88: Impairment loss | C88: 0 | D88: 23 | E88: 200 | F88: 0 | G88: 0 | H88: 0 | I88: 0 | J88: 0 | K88: 0 | L88: 0
B89: Disposals | C89: -67 | D89: -186 | E89: -48 | F89: -92 | G89: -436 | H89: -75 | I89: -75 | J89: -75 | K89: -75 | L89: -75
B90: Transfer to assets held for sale | C90: 0 | D90: 0 | E90: 0 | F90: -77 | G90: 0 | H90: 0 | I90: 0 | J90: 0 | K90: 0 | L90: 0
B91: Closing | C91: =SUM(C86:C90) -> 724 | D91: =SUM(D86:D90) -> 733 | E91: =SUM(E86:E90) -> 1074 | F91: =SUM(F86:F90) -> 1087 | G91: =SUM(G86:G90) -> 850 | H91: =SUM(H86:H90) -> 945 | I91: =SUM(I86:I90) -> 1059 | J91: =SUM(J86:J90) -> 1195.8 | ... L91: =SUM(L86:L90) -> 1556.952
B93: NBV Closing | C93: =C84-C91 -> 1006 | D93: =D84-D91 -> 1024 | E93: =E84-E91 -> 806 | F93: =F84-F91 -> 807 | G93: =G84-G91 -> 838 | H93: =H84-H91 -> 848 | I93: =I84-I91 -> 839 | J93: =J84-J91 -> 807.2 | ... L93: =L84-L91 -> 656.048

Sheet Source Notes
A1: Fiscal year(s) | B1: Source | C1: Use in model | D1: Restatement / modelling note | E1: URL
A2: FY2022 | B2: J Sainsbury plc Annual Report and Financial Statements 2023 / 2022 | C2: FY2022 income statement, balance sheet, cash flow and opening schedule balances | D2: FY2022 balance-sheet presentation follows the latest comparative presentation in the FY2023 report. | E2: https://www.about.sainsburys.co.uk/~/media/Files/S/Sainsburys/documents/reports-and-presentations/2023/annual-report-2023/annual-report-and-financial-statements-2023.pdf
A3: FY2023 | B3: J Sainsbury plc Annual Report and Financial Statements 2023 | C3: FY2023 consolidated income statement, balance sheet and cash flow statement | E3: https://www.about.sainsburys.co.uk/~/media/Files/S/Sainsburys/documents/reports-and-presentations/2023/annual-report-2023/annual-report-and-financial-statements-2023.pdf
A4: FY2024 | B4: J Sainsbury plc Annual Report and Financial Statements 2025 | C4: FY2024 comparative income statement, balance sheet and cash flow statement | D4: Comparatives are re-presented for discontinued operations where disclosed. | E4: https://corporate.sainsburys.co.uk/media/e1lfnybd/sainsbury-annual-report-and-financial-statements-2025.pdf
A5: FY2025 | B5: J Sainsbury plc Annual Report and Financial Statements 2026 | C5: Latest restated FY2025 comparative figures, particularly discontinued Financial Services and deferred-tax presentation | D5: These values can differ from the originally filed FY2025 annual report. | E5: https://corporate.sainsburys.co.uk/media/z01g231u/j-sainsbury-plc-annual-report-and-financial-statements-2026.pdf
A6: FY2026 | B6: J Sainsbury plc Annual Report and Financial Statements 2026 | C6: FY2026 consolidated statements and latest operating metrics | D6: Financial Services core banking exit materially reduces consolidated FS receivables/deposits versus prior years. | E6: https://corporate.sainsburys.co.uk/media/z01g231u/j-sainsbury-plc-annual-report-and-financial-statements-2026.pdf
A9: Additional official results sources used for Operating Metrics
A10: FY2022 | B10: Preliminary Results 2021/22 | C10: Underlying PBT, Retail FCF, net debt, ROCE, underlying EPS | E10: https://corporate.sainsburys.co.uk/news/press-releases/preliminary-results-for-the-52-weeks-ended-5-march-2022/
A11: FY2025–FY2026 | B11: Annual Report 2026 / Preliminary Results 2025/26 | C11: Latest underlying PBT, Retail FCF, net debt, ROCE and EPS | E11: https://corporate.sainsburys.co.uk/investors/annual-report-2026/
A12: FY2023–FY2024 | B12: Annual reports / preliminary results | C12: Underlying PBT, Retail FCF, net debt and ROCE | E12: https://corporate.sainsburys.co.uk/investors/results-reports-and-presentations/
